Workbook

Sheet Version Control
A1: Version Control
A2: ID | B2: Description | C2: Date | D2: Reviewer | E2: File Name | F2: Additional Comments
A3: V1 | B3: Initial Version Copyright 2021-2023, CMMC Information Institute, Inc. Released under the Creative Commons CC-BY-SA license. | C3: 46051 | D3: G. Lazo | E3: 20250130_AGL_v2023-02a-far-and-above-and-nist-sp-800-171-self-assessment-dod-score-tool | F3: Source: https://cmmcinfo.org/home/cmmc-info-tools/maturity-level-1-gap-assessment-tool/
A4: V2 | B4: Updated to include version tracking documentation and re-branded for AirGap Labs | C4: 46053 | D4: G. Lazo | E4: 20260131_AGLv2_v2023-02a-far-and-above-and-nist-sp-800-171-self-assessment-dod-score-tool | F4: Internal version:

Sheet Introduction
G1: Welcome! This Tool is designed to provide guidance to government contractors who handle Controlled Unclassified Information as they try to meet the requirements in NIST SP 800-171. The Tool organizes the 800-171 requirements using the FAR and Above program's 5-stage approach, providing contractors a step-by-step path for their compliance journey. The Tool allows you to perform a self-assessment, record the results, and create Plans of Action and Milestones ("POA&Ms") for requirements that are not met. This Tool also automatically calculates both the FAR and Above and DoD Assessment Methodology scores (also called the SPRS score) based on the self-assessment results. This Tool will be most beneficial to small businesses with a limited number of employees and a small IT infrastructure. As the organization grows, we suggest migrating to a more robust platform, like FutureFeed (https://www.FutureFeed.co), to better build and manage your cybersecurity and compliance programs. FutureFeed is a sponsor of the CMMC Information Institute.
G4: This Tool was created through the generous support of the CMMC Information Institute's donors and sponsors. Please click here to make a tax-deductable donation to the Institute. Even small donations help us offset the cost of providing valuable resources like this Tool. If you are interested in sponsoring the Institute, please contact us at info@cmmcinfo.org.
G5: This tool is updated periodically with feature enhancements, bug fixes, and other changes. Be sure to register for our newsletter so that we can alert you when changes are made.
A6: THIS TOOL IS PROVIDED BY THE COPYRIGHT HOLDERS AND CONTRIBUTORS "AS IS" AND ANY EXPRESS OR IMPLIED WARRANTIES, INCLUDING, BUT NOT LIMITED TO, THE IMPLIED WARRANTIES OF MERCHANTABILITY AND FITNESS FOR A PARTICULAR PURPOSE ARE DISCLAIMED. IN NO EVENT SHALL THE COPYRIGHT HOLDER OR CONTRIBUTORS BE LIABLE FOR ANY DIRECT, INDIRECT, INCIDENTAL, SPECIAL, EXEMPLARY, OR CONSEQUENTIAL DAMAGES (INCLUDING, BUT NOT LIMITED TO, PROCUREMENT OF SUBSTITUTE GOODS OR SERVICES; LOSS OF USE, DATA, OR PROFITS; OR BUSINESS INTERRUPTION) HOWEVER CAUSED AND ON ANY THEORY OF LIABILITY, WHETHER IN CONTRACT, STRICT LIABILITY, OR TORT (INCLUDING NEGLIGENCE OR OTHERWISE) ARISING IN ANY WAY OUT OF THE USE OF THIS SOFTWARE, EVEN IF ADVISED OF THE POSSIBILITY OF SUCH DAMAGE. | G6: This Tool consists of several worksheets, including:
G7: Introduction - This page. It provides a basic introduction to the tool and the different worksheets.
G8: Questionnaire - Used by organizations or their Managed Services Provider, Managed Security Service Provider, Consultant, etc. to help evaluate the overall maturity of the organization's cybersecurity program. For organizations with scores below about 70 points, and those who do not handle CUI, a gap analysis and remediation that focuses on FAR and Above Phase 1 may be more appropriate due to their relative immaturity. Organizations with scores above 70 are more likely to meet most of the Phase 1 requirements and thus could benefit from performing a gap analysis against all 110 controls. Remediation of any gaps can be prioritized based on the corresponding control/requirement's order in FAR and Above. For more details, please visit https://cmmcinfo.org/2022/05/11/cmmc-gap-analysis-client-engagement-process-and-questionnaire/
G9: System Overview & SSP Preamble - Provides a template for the "front matter", or preamble of a System Security Plan ("SSP"). This worksheet collects additional, basic information which must be defined under NIST SP 800-171/CMMC. Also displays FAR and Above and SPRS scores based on your answers in the SSP - DoD SPRS & Far and Above worksheet (described below). As a reminder, this SSP is used to define the security of a "system", or collection of devices, software, people, and information. The system that is the subject of this SSP may be made up of one or more subsystems.
G10: SSP - DoD SPRS & FAR and Above - Presents the NIST SP 800-171 requirements organized in the FAR and Above Program's recommended implementation order. This is where you should record your self-assessment results. Be sure to evaluate your organization against all of the objectives defined in NIST SP 800-171A (https://csrc.nist.gov/publications/detail/sp/800-171a/final) for each requirement when you perform your self-assessment. We include a recommendation as to whether a particular requirement/objective is something a typical small or medium business is likely to be able to handle themselves ("DIY") or if it is something that should probably be outsourced ("Outsource"). In a few cases, the requirements will require a combination of outside help and company resources, and we refer to these as "Hybrid". See below for additional details.
G11: POA&Ms - Create and manage plans of action and milestones ("POA&Ms") here. POA&Ms describe how your organization will meet any requirements that are not fully implemented in the assessed system. References to the relevant control automatically appear in the POA&M list if the control is not fully implemented. You can reference NIST SP 800-53, specifically CA-5 and PM-4, for additional assistance in creating the POA&Ms. See below for additional details.
G12: The System Overview & SSP Preamble, SSP - DoD SPRS & FAR and Above, and POA&Ms worksheets are required to submit a SPRS score. As you conduct your gap assessment (on the SSP - DoD SPRS & FAR and Above worksheet), you will note that your organization is expected to have certain lists and other such information. The following worksheets help you build those lists.
G13: Privileged Accounts - NIST SP 800-171 and CMMC 2.0 require that you identify all of the "privileged accounts" in use in the system. These include administrator accounts, developer accounts, and other accounts that can change security settings, alter the operation/configuration of the system, sub-system, or component, or take other actions that impact the security of the system.
G14: Physical Location(s) Info - This is a list of all of the physical locations where FCI and/or CUI is created, processed, stored, and/or transmitted (i.e., "handled"). In some cases, your organization may decide to limit access to some physical locations to only certain employee roles. For example, if your organization has a closet where your servers are stored (i.e., a "data center"), you may limit physical access to that data center to only employees who are systems administrators to help reduce the likelihood of malicious activities. The physical locations list is referenced in the Hardware Inventory worksheet (below) to help you identify the user roles which are permitted to access the different physical locations where FCI or CUI is handled.
G15: Users Auth. to Access System - This is a list of all users who are authorized to access the system.
G16: User Roles - This is a list of all of the user roles relevant to the system. Roles are used to defined categories of users who are authorized to access certain information, take certain actions, etc. This allows the organization to more easily allocate and track authorizations as employees join the organization, change jobs within the organization, and/or leave the organization.
G17: Authorized Visitor List - A list of individuals authorized to visit the location, including whether the individual is authorized to access sensitive information (including CUI) and the area(s) the user is authorized to visit.
G18: Visitor Access Log - A log of individuals who have visited the location
... G42: For each security requirement that the organization has not fully implemented, indicate a date by which the organization currently plans to fully implement that requirement. The date farthest in the future will be used to populate the "Date When 110 Score Expected" field in the Information for SPRS Submission portion of the worksheet.
A43: Version 2023.02a
AA47: Copyright 2021-2023, CMMC Information Institute, Inc. Released under the Creative Commons CC-BY-SA license. | AG47: Although we have tried to make the Tool useful, it is being provided to you as-is, and nothing in the Tool is intended to serve as, nor does it serve as, legal or technical advice. To be clear, if you use the Tool or any of the information in it, you do so at your own risk. If you do not agree, you must not use the Tool. It's that simple.
AG48: Worksheet Listing (Be sure to scroll down for additional information, including a background of the CMMC and SPRS programs and instructions for using the worksheets to conduct a self-assessment and calculate SPRS and FAR and Above scores)

Sheet Questionnaire
A1: Client Name: | B1: Canopy Aerospace and Defense
A2: Client Point of Contact (POC) Name: | B2: Richard Bays
A3: Client POC Title: | B3: CIO
A4: Client POC E-mail Address: | B4: richard.bays@canopy-ad.com
A5: Client POC Phone Number: | B5: 909-321-2001
A6: Date Questionnaire Completed:
A7: Questionnaire Score (calculated - 0 to 107) | B7: {=SUM(C22:C45)}
A9: At how many physical locations (offices, data centers, or other facilities) does your organization handle CUI or FCI? | B9: 4
A10: How many employees do you have, and how many are authorized to access government information? | B10: 180 employees, about 50 employees have access
A11: Total employees and contractors: | B11: 180 employees and 3 contractors | F11: Need to get a count of Airgap employees
A12: Authorized to access Government Information
A13: How many accounts of the following types do you have in your organization's systems?
A14: Users | B14: 180
A15: Local Administrators | B15: 0
A16: Application
A17: Service
A18: Domain Administrator
A19: Other
A20: Do you allow employees to access your systems, including E-mail, collaboration, and cloud resources, from their personal devices (i.e., BYOD)?
A21: Can any of your employees work remotely? If so, can they work remotely using their own equipment or only organization-provided equipment?
A22: Do your organization's employees periodically receive security awareness training regarding the risks associated with their activities and any applicable policies, procedures, standards, etc. relevant to the systems they use to conduct the activities? | C22: {=IF(OR(B22=References!A28,B22=""),0,IF(B22=References!A29,3,5))}
A23: Is your staff trained to recognize and properly handle sensitive information, such as bank accounts, social security numbers, design specifications, blueprints, Federal Contract Information (“FCI”) and Controlled Unclassified Information (“CUI”)? | C23: {=IF(OR(B23="No",B23=""),0,3)}
A24: Do you have a comprehensive list of all of the types of sensitive information (including FCI, CUI by type, and non-government information) in received, created, processed, stored, and/or transmitted by your organization? (If yes, we will ask you for a copy once a nondisclosure agreement is in place) | C24: {=IF(OR(B24="No",B24=""),0,5)}
A25: Do you have a comprehensive list of all hardware (including laptops, mobile devices, workstations, servers, printers, networking equipment, “smart devices” (like TVs, Alexas, etc.)) in use by your organization? (If yes, we will ask you for a copy once a nondisclosure agreement is in place) | C25: {=IF(OR(B25="No",B25=""),0,3)}
A26: Do you have a comprehensive list of all software (including operating systems, end-user software, and drivers) installed on the organization’s equipment? (If yes, we will ask you for a copy once a nondisclosure agreement is in place) | C26: {=IF(OR(B26="No",B26=""),0,5)}
A27: Do you have a comprehensive list of all cloud resources (including E-mail, file sharing, chat, collaboration, HR, payroll, and other resources) used by the organization? (If yes, we will ask you for a copy once a nondisclosure agreement is in place) | C27: {=IF(OR(B27="No",B27=""),0,5)}
A28: Do you have a network diagram? (If yes, we will ask you for a copy once a nondisclosure agreement is in place) | C28: {=IF(OR(B28="No",B28=""),0,5)}
A29: Can you show how and where sensitive information, and in particular FCI and CUI, is received, processed, stored, and transmitted within your organization? (If yes, we will ask you for a copy once a nondisclosure agreement is in place) | C29: {=IF(OR(B29="No",B29=""),0,10)}
A30: Do you have a list of all of your employees and contractors that includes their roles? If so, have you defined which roles are authorized to handle different categories of information (e.g., CUI vs FCI)? | C30: {=IF(OR(B30=References!A32,B30=""),0,IF(B30=References!A33,3,5))}
A31: Do all of your users have administrative privileges on their local computer (i.e., they are local administrators)? | C31: {=IF(OR(B31="Yes",B31=""),0,5)}
A32: Does your organization require multifactor authentication for:
A33: Remote Administration | C33: {=IF(OR(B33="Yes",B33=""),0,5)}
A34: All user remote access | C34: {=IF(OR(B34="Yes",B34=""),0,3)}
A35: All administrator logins | C35: {=IF(OR(B35="Yes",B35=""),0,5)}
A36: All user logins | C36: {=IF(OR(B36="Yes",B36=""),0,3)}
A37: Administrator access to cloud resources | C37: {=IF(OR(B37="Yes",B37=""),0,5)}
A38: All user access to cloud resources | C38: {=IF(OR(B38="Yes",B38=""),0,3)}
A39: Does your organization deploy Wi-Fi? If so, is the Wi-Fi network part of your corporate network or external to it? | C39: {=IF(OR(B39="",B39=References!A37),0,IF(B39=References!A36,3,5))}
A40: Does your organization have an incident response plan that describes roles and responsibilities? If so, do you routinely test the plan? (If you have a plan, we will ask for a copy once a nondisclosure agreement is in place)
A41: Plan | C41: {=IF(OR(B41="Yes",B41=""),0,3)}
A42: Roles and responsibilities are identified | C42: {=IF(OR(B42="Yes",B42=""),0,3)}
A43: Plan has been tested at least once in the past 12 months | C43: {=IF(OR(B43="Yes",B43=""),0,5)}
A44: Has your organization already performed a self-assessment against NIST SP 800-171? If so, did your assessment consider only the requirements themselves or also the objectives defined in NIST SP 800-171A? (If yes, we will ask for the results once a nondisclosure agreement is in place) | C44: {=IF(OR(B44="",B44=References!A40),0,IF(B44=References!A41,3,8))}
A45: Do you have a comprehensive set of policies, procedures, plans, and/or other documents that define your IT and cybersecurity programs? (If yes, we will ask you for copies once a nondisclosure agreement is in place) | C45: {=IF(OR(B45="",B45="No"),0,IF(B45=References!A45,3,8))}

Sheet System Overview & SSP Preamble
A1: System Security Plan | E1: Additional Assessor/Preparer Notes | F1: Relevant Notes from NIST
A2: FAR and Above Score (0 to 500) [Auto-calculated] | C2: {='SSP - DoD SPRS & FAR and Above'!D1}
A3: Information for SPRS Submission | B3: SPRS Score (-203 to 110) [Auto-calculated] | C3: {=IF('SSP - DoD SPRS & FAR and Above'!O80=-1000,"No SSP, therefore an assessment could not be completed due to incomplete information and noncompliance with DFARS clause 252.204-7012. See NIST SP 800-171 3.12.4.",'SSP - DoD SPRS & FAR and Above'!B1)}
B4: Date when 110 Score Expected [Auto-calculated] | C4: N/A
B5: Prepared by (Assessor Name) | C5: Onnex AI Agency (MSP)
B6: Prepared for (Organization Name) | C6: Canopy Aerospace and Defense
B7: Date of Assessment | C7: 2026-04-17
B8: CAGE Code(s) Supported by System | C8: CANPY
B9: System Description | C9: IT systems handling Controlled Unclassified Information (CUI) in support of DoD contracts
A10: System Identification | B10: Canopy Aerospace and Defense — CMMC IT System
B11: System Categorization - Confidentiality [MUST be at least Moderate if system handles CUI] | C11: Moderate
B12: System Categorization - Integrity | C12: Moderate
B13: System Categorization - Availability | C13: Moderate
B14: System Unique Identifier | C14: CANOPY-CMMC-001
B15: Responsible Organization | C15: Name: | D15: Canopy Aerospace and Defense
C16: Address: | D16: On file with MSP
C17: Phone: | D17: On file with MSP
B18: Information Owner(s): [Government point(s) of contact responsible for providing and/or receiving CUI] | C18: Name: | D18: To Be Determined — Contracting Officer
C19: Title: | D19: Contracting Officer
C20: Office Address: | D20: N/A
C21: Work Phone: | D21: N/A
C22: E-mail Address: | D22: N/A
B23: System Owner: [Assignment of security responsibility] | C23: Name: | D23: Canopy IT Admin
C24: Title: | D24: IT Administrator
C25: Office Address: | D25: On file with MSP
C26: Work Phone: | D26: On file with MSP
C27: E-mail Address: | D27: it@canopyaerospace.com
B28: System Security Officer: | C28: Name: | D28: Canopy IT Admin
C29: Title: | D29: IT Administrator / ISSO
C30: Office Address: | D30: On file with MSP
C31: Work Phone: | D31: On file with MSP
C32: E-mail Address: | D32: it@canopyaerospace.com
B33: General Description/Purpose of the system: What is the function/purpose of the system? [Provide a short, high-level description of the function/purpose of the system]
B34: TBD — pending full system inventory
B35: System Management Functions (3.13.3b): | D35: See Security Functions defined below.
B36: Security Functions (3.1.5c): | D36: Establishing System Accounts, Configuring Access Authorizations (i.e. Permissions, Privileges), Configuring Settings for Events to be Audited, Establishing Intrusion Detection Parameters, Reviewing Audit Logs [Add Additional Relevant Functions As Necessary]
B37: Security Information | D37: Filtering Rules for Routers/Firewalls, Configuration Parameters for Security Services/Devices, Cryptographic Key Management Information, Access Control Lists, Audit Logs [Add Additional Relevant Information As Necessary]
B38: Non-Security Functions (3.1.6a, 3.13.3a): | D38: All functions/activities except the Security Functions identified above.
B39: Number of Privileged Users: [Provide the approximate number of administrators, including system administrators, database administrators, application administrators, etc.] | C39: System Administrators:
C40: Database Administrators:
C41: Application Administrators:
C42: Other Administrators:
C43: Application/System Programmers:
C44: Other Privileged Users:
B45: General Description of Information: [See CUI Types worksheet or NARA CUI Registry for descriptions] | C45: CUI Types processed, stored, or transmitted by the system:
A46: System Environment | B46: Type(s) of Remote Access Permitted (Dial-up, Broadband, Wireless, VPN, etc.) (3.1.12b):
B47: Link to system topology graphic:
B48: Detailed system topology narrative: | F48: Include a detailed topology narrative and graphic that clearly depicts the system boundaries, system interconnections, and key devices. (Note: this does not require depicting every workstation or desktop, but include an instance for each operating system in use, an instance for portable components (if applicable), all virtual and physical servers (e.g., file, print, web, database, application), as well as any networked workstations (e.g., Unix, Windows, Mac, Linux), firewalls, routers, switches, copiers, printers, lab equipment, handhelds). If components of other systems that interconnect/interface with this system need to be shown on the diagram, denote the system boundaries by referencing the security plans or names and owners of the other system(s) in the diagram.
B49: Architectural Design Concepts used to Promote Effective Information Security (3.13.2a):
B50: Software Development Techniques used to Promote Effective Information Security (3.13.2b):
B51: Systems Engineering Principles used that Promote Effective Information Security (3.13.2c): | D51: [See NIST SP 800-160 (https://csrc.nist.gov/publications/detail/sp/800-160/vol-1/final) volume 1 for more details about systems engineering]
B52: Complete and accurate listing of all hardware (or link to it): | D52: (See Hardware Inventory Worksheet in this document) | F52: A reference to the organizational component inventory database is acceptable. Include the manufacturer/OEM, model, version, BIOS version, and responsible person/role.
B53: Complete and accurate listing of all software (or link to it): | D53: (See Software Inventory Worksheet in this document) | F53: Include both system software and application software. Provide the make/OEM/developer, model, version, service packs, and responsible person/role.
B54: Complete and accurate listing of all cloud applications/services (or link to it): | D54: (See Cloud Svc. & Ext. System Invent. Worksheet in this document)
A55: Policies, Procedures, Plans, Standards, Etc. | B55: Listing of, and Links to, Relevant Policies, Procedures, Plans, Standards, and Related Documents (3.2.1b): | D55: [See CMMCInfo.org for document templates]
B56: Procedure to Ensure CUI is not Posted or Processed on Publicly Accessible Systems (3.1.22b): | D56: [Describe Procedure or Point to Where the Procedure is Stored]
B57: Privacy and Security Notices Required by CUI Specified Rules (if the environment contains CUI-specified information) (3.1.9a):
B58: Limits on the Use of Portable Storage Devices Containing CUI on External Systems (3.1.21b): | D58: [Describe Limits or Point to Policy or other Document Describing the Limits]
B59: Security Risks Associated with the Organization's Activities Involving CUI:
B60: Potential Indicators of Insider Threat (3.2.3a): | D60: Potential indicators and possible precursors of insider threats against this system include behaviors such as: inordinate, long-term job dissatisfaction; attempts to gain access to information that is not required for job performance; unexplained access to financial resources; unexplained deviations from normal working hours; bullying or sexual harassment of fellow employees; workplace violence; and other serious violations of the policies, procedures, directives, rules, or practices of organizations. [Remove/Add Additional Potential Indicators of Insider Threat as Appropriate]
B61: External security alerts, advisories, and directives from reputable external organizations that are relevant to the industry and technology used by our organization: | D61: [e.g., subscribe to alerts/RSS feeds from https://www.cisa.gov/uscert/ncas/alerts, https://www.cyber.nj.gov]
B62: Alerts and Advisory Response Plan (3.14.3a): | D62: [Describe Plan or Point to Where the Plan is Stored]
B63: Audit logs needed (i.e., event types to be logged) to enable the monitoring, analysis, investigation, and reporting of unlawful or unauthorized system activity (3.3.1a):
A64: Key Personnel | B64: Personnel to be Alerted in the Event of an Audit Logging Failure (3.3.4a):
B65: Personnel to be Alerted in the Event an Incident is Detected (3.6.2d):
A66: Notice | B66: Authorities to be Notified if an Incident is Detected (3.6.2c):
A67: Compliance | B67: SSP Preamble Information (this page) Last Reviewed on and by:
A69: Helpful Links
A70: SPRS Website: | B70: Supplier Performance Risk System (disa.mil)
A71: SPRS FAQ: | B71: SPRS - Frequently Asked Questions (disa.mil)
A72: SPRS 3.3 Training: | B72: NISTSP800-171QuickEntryGuide.pdf (disa.mil)
A73: NARA CUI Registry: | B73: CUI Categories | National Archives

Sheet SSP - DoD SPRS & FAR and Above
A1: SPRS Score | B1: {=110+(SUM(O89:O409)+SUM(O3:O79))} | C1: FAR and Above Score | D1: {=V323+V233+V164+V77+V3} | E1: FAR and AboveTM Phased Implementation Plan for NIST SP 800-171 and CMMC 2.0 Level 2 Compliance
A2: FAR and Above Phase | B2: FAR and Above Sort Order | C2: SMB DIY or Outsource | D2: NIST SP 800-171 Family/ CMMC Domain | E2: NIST SP 800-171 ID | F2: NIST SP 800-171 Sort Order | G2: CMMC Control | H2: DoD Score Value | I2: Security Requirement | J2: Assessment Objective | K2: DoD Comment to Assessor | L2: Description of how your organization meets the Security Requirement or Assessment Objective and Link to Evidence | M2: Implementation Status | N2: Target Implementation Completion Date | O2: Score Impact | P2: Responsible Office/Organization | T2: FAR and Above Control Score | U2: FAR and Above Raw Score | V2: FAR and Above Phase Score
A3: 1 | B3: 1.01.0 | C3: Outsource | D3: System and Communications Protection | E3: 3.13.1 | F3: 03.13.01.0 | G3: SC.L1-3.13.1 | H3: 5 | I3: Monitor, control, and protect communications (i.e., information transmitted or received by organizational systems) at the external boundaries and key internal boundaries of organizational systems. | J3: Determine if: | L3: Overall Stats Meets Partially Updates required to documentation Test required for validating controls in place Examine - Policy updates required. Interview Controls are currently being implemented. - Test - Does not pass due to policy updates and required controls in place. | M3: {=IF(AND(M4="Fully Implemented",M5="Fully Implemented",M6="Fully Implemented",M7="Fully Implemented",M8="Fully Implemented",M9="Fully Implemented",M10="Fully Implemented",M11="Fully Implemented"),"Fully Implemented","")} | O3: {=IF(AND(M4="Fully Implemented",M5="Fully Implemented",M6="Fully Implemented",M7="Fully Implemented",M8="Fully Implemented",M9="Fully Implemented",M10="Fully Implemented",M11="Fully Implemented"),0,-1*H3)} | T3: {=IF(O3=0,H3,0)} | U3: {=SUM(T3:T76)} | V3: {=IF(U3=SUM(H3:H76),100,U3)}
A4: 1 | B4: 1.01.a | C4: Outsource | D4: System and Communications Protection | E4: 3.13.1[a] | F4: 03.13.01.a | G4: SC.L1-3.13.1 | J4: the external system boundary is defined. | K4: Meets Partially | L4: See the following document for details. 20260303_2023_CMMC_SC_L2-3.13.1_Assessment_by_AO Canopy-Azure-Ref-Arch Hera Network Diagrams 11-20-2025.pdf Hera All Sites IP Subnets-11-15-2025 | M4: Implementation Begun
A5: 1 | B5: 1.01.b | C5: Outsource | D5: System and Communications Protection | E5: 3.13.1[b] | F5: 03.13.01.b | G5: SC.L1-3.13.1 | J5: key internal system boundaries are defined. | K5: Meets Partially | L5: See the following document for details. 20260303_2023_CMMC_SC_L2-3.13.1_Assessment_by_AO | M5: Implementation Begun
A6: 1 | B6: 1.01.c | C6: Outsource | D6: System and Communications Protection | E6: 3.13.1[c] | F6: 03.13.01.c | G6: SC.L1-3.13.1 | J6: communications are monitored at the external system boundary. | K6: Meets Partially | L6: See the following document for details. 20260303_2023_CMMC_SC_L2-3.13.1_Assessment_by_AO | M6: Implementation Begun
A7: 1 | B7: 1.01.d | C7: Outsource | D7: System and Communications Protection | E7: 3.13.1[d] | F7: 03.13.01.d | G7: SC.L1-3.13.1 | J7: communications are monitored at key internal boundaries. | K7: Meets Partially | L7: See the following document for details. 20260303_2023_CMMC_SC_L2-3.13.1_Assessment_by_AO | M7: Implementation Begun
A8: 1 | B8: 1.01.e | C8: Outsource | D8: System and Communications Protection | E8: 3.13.1[e] | F8: 03.13.01.e | G8: SC.L1-3.13.1 | J8: communications are controlled at the external system boundary. | K8: Meets Partially | L8: See the following document for details. 20260303_2023_CMMC_SC_L2-3.13.1_Assessment_by_AO | M8: Implementation Begun
A9: 1 | B9: 1.01.f | C9: Outsource | D9: System and Communications Protection | E9: 3.13.1[f] | F9: 03.13.01.f | G9: SC.L1-3.13.1 | J9: communications are controlled at key internal boundaries. | K9: Meets Partially | L9: See the following document for details. 20260303_2023_CMMC_SC_L2-3.13.1_Assessment_by_AO | M9: Implementation Begun
A10: 1 | B10: 1.01.g | C10: Outsource | D10: System and Communications Protection | E10: 3.13.1[g] | F10: 03.13.01.g | G10: SC.L1-3.13.1 | J10: communications are protected at the external system boundary. | K10: Meets Partially | L10: See the following document for details. 20260303_2023_CMMC_SC_L2-3.13.1_Assessment_by_AO | M10: Implementation Begun
A11: 1 | B11: 1.01.h | C11: Outsource | D11: System and Communications Protection | E11: 3.13.1[h] | F11: 03.13.01.h | G11: SC.L1-3.13.1 | J11: communications are protected at key internal boundaries. | K11: Meets Partially | L11: See the following document for details. 20260303_2023_CMMC_SC_L2-3.13.1_Assessment_by_AO | M11: Implementation Begun
A12: 1 | B12: 1.02.0 | C12: Hybrid | D12: System and Communications Protection | E12: 3.13.5 | F12: 03.13.05.0 | G12: SC.L1-3.13.5 | H12: 5 | I12: Implement subnetworks for publicly accessible system components that are physically or logically separated from internal networks. | J12: Determine if: | K12: [No Comment Provided] | L12: Overall Status Meets Partially Updates required to documentation Test required for validating controls in place Examine - Policy updates required. Interview Controls are currently being implemented. - Test - Does not pass due to policy updates and required controls in place. | M12: Implementation Begun | O12: {=IF(AND(M13="Fully Implemented",M14="Fully Implemented"),0,-1*H12)} | T12: {=IF(O12=0,H12,0)}
A13: 1 | B13: 1.02.a | C13: DIY | D13: System and Communications Protection | E13: 3.13.5[a] | F13: 03.13.05.a | G13: SC.L1-3.13.5 | J13: publicly accessible system components are identified. | K13: Meets Partially | L13: Request: Inventory of all exernally facing systems. See the following document for details. 20260303_2023_CMMC_SC_L2-3.13.1_Assessment_by_AO | M13: Implementation Begun
A14: 1 | B14: 1.02.b | C14: Outsource | D14: System and Communications Protection | E14: 3.13.5[b] | F14: 03.13.05.b | G14: SC.L1-3.13.5 | J14: subnetworks for publicly accessible system components are physically or logically separated from internal networks. | K14: Meets Partially | L14: See the following document for details. 20260303_2023_CMMC_SC_L2-3.13.1_Assessment_by_AO Intune GCC - MDM VPN Information Cloud authentication Cloudflare Project Documentation Firewall Information OKTA project information VLAN information / Could update | M14: Implementation Begun
A15: 1 | B15: 1.03.0 | C15: DIY | D15: Physical Protection | E15: 3.10.1 | F15: 03.10.01.0 | G15: PE.L1-3.10.1 | H15: 5 | I15: Limit physical access to organizational systems, equipment, and the respective operating environments to authorized individuals. | J15: Determine if: | K15: [No Comment Provided] | L15: Overall Status Meets Partially Updates required to documentation Test required for validating controls in place Examine - Policy updates required. Interview Controls are currently being implemented. - Test - Pending evaluation of controls, policy/procedure updates and evidence of required controls in place. Canopy A&D - 3.10 - Physical and Environmental Protection Policy Physical Security Measures -Surveillance: Surveillance cameras shall be installed at all entry points and sensitive areas to monitor access activities. -Physical Barriers: Physical barriers such as locked doors, turnstiles, and security gates shall be used to prevent unauthorized access. Safeguarding Measures at alternate work sites -Ensure all CUI is stored in locked containers, cabinets, or desks when not in use. | M15: Implementation Begun | O15: {=IF(AND(M16="Fully Implemented",M17="Fully Implemented",M18="Fully Implemented",M19="Fully Implemented"),0,-1*H15)} | T15: {=IF(O15=0,H15,0)}
A16: 1 | B16: 1.03.a | C16: DIY | D16: Physical Protection | E16: 3.10.1[a] | F16: 03.10.01.a | G16: PE.L1-3.10.1 | J16: authorized individuals allowed physical access are identified. | K16: Meets Partially | L16: See the following document for details. 20260316_2252_CMMC_PE.L1-3.10.1_Assessment_by_AO | M16: Implementation Begun
A17: 1 | B17: 1.03.b | C17: DIY | D17: Physical Protection | E17: 3.10.1[b] | F17: 03.10.01.b | G17: PE.L1-3.10.1 | J17: physical access to organizational systems is limited to authorized individuals. | K17: Meets Partially | L17: See the following document for details. 20260316_2252_CMMC_PE.L1-3.10.1_Assessment_by_AO | M17: Implementation Begun
A18: 1 | B18: 1.03.c | C18: DIY | D18: Physical Protection | E18: 3.10.1[c] | F18: 03.10.01.c | G18: PE.L1-3.10.1 | J18: physical access to equipment is limited to authorized individuals. | K18: Meets Partially | L18: See the following document for details. 20260316_2252_CMMC_PE.L1-3.10.1_Assessment_by_AO | M18: Implementation Begun
A19: 1 | B19: 1.03.d | C19: DIY | D19: Physical Protection | E19: 3.10.1[d] | F19: 03.10.01.d | G19: PE.L1-3.10.1 | J19: physical access to operating environments is limited to authorized individuals. | K19: Meets Partially | L19: See the following document for details. 20260316_2252_CMMC_PE.L1-3.10.1_Assessment_by_AO | M19: Implementation Begun
A20: 1 | B20: 1.04.0 | C20: DIY | D20: Physical Protection | E20: 3.10.3 | F20: 03.10.03.0 | G20: PE.L1-3.10.3 | H20: 1 | I20: Escort visitors and monitor visitor activity. | J20: Determine if: | K20: [No Comment Provided] | L20: Overall Status Meets - Pending policy/procedure review meeting and observation of controls in place. Updates required to documentation Test required for validating controls in place Examine - Policy updates required. Interview Controls are currently being implemented. - Test - Review testing measures in place. Canopy A&D - 3.10 - Physical and Environmental Protection Policy, Page 1-4 | M20: Implementation Begun | O20: {=IF(AND(M21="Fully Implemented",M22="Fully Implemented"),0,-1*H20)} | T20: {=IF(O20=0,H20,0)}
A21: 1 | B21: 1.04.a | C21: DIY | D21: Physical Protection | E21: 3.10.3[a] | F21: 03.10.03.a | G21: PE.L1-3.10.3 | J21: visitors are escorted. | K21: Meets Partially | L21: See the following document for details. 20260322_2023_CMMC_PE.L1-3.10.3_Assessment_by_AO | M21: Implementation Begun
A22: 1 | B22: 1.04.b | C22: DIY | D22: Physical Protection | E22: 3.10.3[b] | F22: 03.10.03.b | G22: PE.L1-3.10.3 | J22: visitor activity is monitored. | K22: Meets Partially | L22: See the following document for details. 20260322_2023_CMMC_PE.L1-3.10.3_Assessment_by_AO | M22: Implementation Begun
A23: 1 | B23: 1.05.0 | C23: DIY | D23: Physical Protection | E23: 3.10.4 | F23: 03.10.04.0 | G23: PE.L1-3.10.4 | H23: 1 | I23: Maintain audit logs of physical access. | J23: Determine if audit logs of physical access are maintained. | K23: [No Comment Provided] | L23: Overall Status Meets - Pending policy/procedure review meeting and observation of controls in place. Updates required to documentation Test required for validating controls in place Examine - Policy updates required. Interview Controls are currently being implemented. - Test - Review testing measures in place. Canopy A&D - 3.10 - Physical and Environmental Protection Policy, Page 1-4 | M23: Implementation Begun | O23: {=IF(M23<>"Fully Implemented",-1*H23,0)} | T23: {=IF(O23=0,H23,0)}
A24: 1 | B24: 1.06.0 | C24: DIY | D24: Physical Protection | E24: 3.10.5 | F24: 03.10.05.0 | G24: PE.L1-3.10.5 | H24: 1 | I24: Control and manage physical access devices. | J24: Determine if: | K24: [No Comment Provided] | L24: Overall Status Meets - Pending policy/procedure review meeting and observation of controls in place. Updates required to documentation Test required for validating controls in place Examine - Policy updates required. Interview Controls are currently being implemented. - Test - Review testing measures in place. Canopy A&D - 3.10 - Physical and Environmental Protection Policy, Page 1-4 | M24: Implementation Begun | O24: {=IF(AND(OR(M25="Fully Implemented",M25="Not Permitted"),OR(M26="Fully Implemented",M26="Not Permitted"),OR(M27="Fully Implemented",M27="Not Permitted")),0,-1*H24)} | T24: {=IF(O24=0,H24,0)}
A25: 1 | B25: 1.06.a | C25: DIY | D25: Physical Protection | E25: 3.10.5[a] | F25: 03.10.05.a | G25: PE.L1-3.10.5 | J25: physical access devices are identified. | M25: Implementation Begun
A26: 1 | B26: 1.06.b | C26: DIY | D26: Physical Protection | E26: 3.10.5[b] | F26: 03.10.05.b | G26: PE.L1-3.10.5 | J26: physical access devices are controlled. | M26: Implementation Begun
A27: 1 | B27: 1.06.c | C27: DIY | D27: Physical Protection | E27: 3.10.5[c] | F27: 03.10.05.c | G27: PE.L1-3.10.5 | J27: physical access devices are managed. | M27: Implementation Begun
A28: 1 | B28: 1.07.0 | C28: DIY | D28: Media Protection | E28: 3.8.3 | F28: 03.08.03.0 | G28: MP.L1-3.8.3 | H28: 5 | I28: Sanitize or destroy system media containing CUI before disposal or release for reuse. | J28: Determine if: | K28: [No Comment Provided] | L28: Overall Status Meets - Pending policy/procedure review meeting and observation of controls in place. Updates required to documentation Test required for validating controls in place Examine - Policy updates required. Interview Controls are currently being implemented. - Test - Review testing measures in place. DOC-012 Canopy A&D - 3.8 - System Media Protection Policy.docx DOC-023 Certificate of Destruction-Sanitization.pdf | M28: {=IF(AND(M29="Fully Implemented",M30="Fully Implemented"),"Fully Implemented","")} | O28: {=IF(AND(M29="Fully Implemented",M30="Fully Implemented"),0,-1*H28)} | T28: {=IF(O28=0,H28,0)}
A29: 1 | B29: 1.07.a | C29: DIY | D29: Media Protection | E29: 3.8.3[a] | F29: 03.08.03.a | G29: MP.L1-3.8.3 | J29: system media containing CUI is sanitized or destroyed before disposal. | K29: Meets pending meeting | L29: See the following document for details. 20260322_2233_CMMC_MP.L1-3.8.3_Assessment_by_AO | M29: Implementation Begun
A30: 1 | B30: 1.07.b | C30: DIY | D30: Media Protection | E30: 3.8.3[b] | F30: 03.08.03.b | G30: MP.L1-3.8.3 | J30: system media containing CUI is sanitized before it is released for reuse. | K30: Meets pending meeting | L30: See the following document for details. 20260322_2233_CMMC_MP.L1-3.8.3_Assessment_by_AO | M30: Implementation Begun
A31: 1 | B31: 1.08.0 | C31: DIY | D31: System and Information Integrity | E31: 3.14.1 | F31: 03.14.01.0 | G31: SI.L1-3.14.1 | H31: 5 | I31: Identify, report, and correct system flaws in a timely manner. | J31: Determine if: | K31: [No Comment Provided] | L31: Overall Status - Pending policy/procedure review meeting and observation of controls in place. Updates required to documentation Test required for validating controls in place Examine - Policy updates may be required based on interviews/walkthroughs. Interview Controls are currently being implemented. - Test - Review testing measures in place. | M31: Implementation Begun | O31: {=IF(AND(M32="Fully Implemented",M33="Fully Implemented",M34="Fully Implemented",M35="Fully Implemented",M36="Fully Implemented",M37="Fully Implemented"),0,-1*H31)} | T31: {=IF(O31=0,H31,0)}
A32: 1 | B32: 1.08.a | C32: DIY | D32: System and Information Integrity | E32: 3.14.1[a] | F32: 03.14.01.a | G32: SI.L1-3.14.1 | J32: the time within which to identify system flaws is specified. | M32: Implementation Begun
A33: 1 | B33: 1.08.b | C33: DIY | D33: System and Information Integrity | E33: 3.14.1[b] | F33: 03.14.01.b | G33: SI.L1-3.14.1 | J33: system flaws are identified within the specified time frame. | M33: Implementation Begun
A34: 1 | B34: 1.08.c | C34: DIY | D34: System and Information Integrity | E34: 3.14.1[c] | F34: 03.14.01.c | G34: SI.L1-3.14.1 | J34: the time within which to report system flaws is specified. | M34: Implementation Begun
A35: 1 | B35: 1.08.d | C35: DIY | D35: System and Information Integrity | E35: 3.14.1[d] | F35: 03.14.01.d | G35: SI.L1-3.14.1 | J35: system flaws are reported within the specified time frame. | M35: Implementation Begun
A36: 1 | B36: 1.08.e | C36: DIY | D36: System and Information Integrity | E36: 3.14.1[e] | F36: 03.14.01.e | G36: SI.L1-3.14.1 | J36: the time within which to correct system flaws is specified. | M36: Implementation Begun
A37: 1 | B37: 1.08.f | C37: DIY | D37: System and Information Integrity | E37: 3.14.1[f] | F37: 03.14.01.f | G37: SI.L1-3.14.1 | J37: system flaws are corrected within the specified time frame. | M37: Implementation Begun
A38: 1 | B38: 1.09.0 | C38: DIY | D38: System and Information Integrity | E38: 3.14.2 | F38: 03.14.02.0 | G38: SI.L1-3.14.2 | H38: 5 | I38: Provide protection from malicious code at designated locations within organizational systems. | J38: Determine if: | K38: [No Comment Provided] | L38: Overall Status - Pending policy/procedure review meeting and observation of controls in place. Updates required to documentation Test required for validating controls in place Examine - Policy updates may be required based on interviews/walkthroughs. Interview Controls are currently being implemented. - Test - Review testing measures in place. | M38: Implementation Begun | O38: {=IF(AND(M39="Fully Implemented",M40="Fully Implemented"),0,-1*H38)} | T38: {=IF(O38=0,H38,0)}
A39: 1 | B39: 1.09.a | C39: DIY | D39: System and Information Integrity | E39: 3.14.2[a] | F39: 03.14.02.a | G39: SI.L1-3.14.2 | J39: designated locations for malicious code protection are identified. | M39: Implementation Begun
A40: 1 | B40: 1.09.b | C40: DIY | D40: System and Information Integrity | E40: 3.14.2[b] | F40: 03.14.02.b | G40: SI.L1-3.14.2 | J40: protection from malicious code at designated locations is provided. | M40: Implementation Begun
A41: 1 | B41: 1.10.0 | C41: DIY | D41: System and Information Integrity | E41: 3.14.4 | F41: 03.14.04.0 | G41: SI.L1-3.14.4 | H41: 5 | I41: Update malicious code protection mechanisms when new releases are available. | J41: Determine if malicious code protection mechanisms are updated when new releases are available. | K41: [No Comment Provided] | L41: Overall Status - Pending policy/procedure review meeting and observation of controls in place. Updates required to documentation Test required for validating controls in place Examine - Policy updates may be required based on interviews/walkthroughs. Interview Controls are currently being implemented. - Test - Review testing measures in place. | M41: Implementation Begun | O41: {=IF(M41<>"Fully Implemented",-1*H41,0)} | T41: {=IF(O41=0,H41,0)}
A42: 1 | B42: 1.11.0 | C42: DIY | D42: System and Information Integrity | E42: 3.14.5 | F42: 03.14.05.0 | G42: SI.L1-3.14.5 | H42: 3 | I42: Perform periodic scans of organizational systems and real-time scans of files from external sources as files are downloaded, opened, or executed. | J42: Determine if: | K42: [No Comment Provided] | L42: Overall Status - Pending policy/procedure review meeting and observation of controls in place. Updates required to documentation Test required for validating controls in place Examine - Policy updates may be required based on interviews/walkthroughs. Interview Controls are currently being implemented. - Test - Review testing measures in place. | M42: Implementation Begun | O42: {=IF(AND(OR(M43="Fully Implemented",M43="Not Permitted"),OR(M44="Fully Implemented",M44="Not Permitted"),OR(M45="Fully Implemented",M45="Not Permitted")),0,-1*H42)} | T42: {=IF(O42=0,H42,0)}
A43: 1 | B43: 1.11.a | C43: DIY | D43: System and Information Integrity | E43: 3.14.5[a] | F43: 03.14.05.a | G43: SI.L1-3.14.5 | J43: the frequency for malicious code scans is defined. | M43: Implementation Begun
A44: 1 | B44: 1.11.b | C44: DIY | D44: System and Information Integrity | E44: 3.14.5[b] | F44: 03.14.05.b | G44: SI.L1-3.14.5 | J44: malicious code scans are performed with the defined frequency. | M44: Implementation Begun
A45: 1 | B45: 1.11.c | C45: DIY | D45: System and Information Integrity | E45: 3.14.5[c] | F45: 03.14.05.c | G45: SI.L1-3.14.5 | J45: real-time malicious code scans of files from external sources as files are downloaded, opened, or executed are performed. | M45: Implementation Begun
A46: 1 | B46: 1.12.0 | C46: Hybrid | D46: Identification and Authentication | E46: 3.5.1 | F46: 03.05.01.0 | G46: IA.L1-3.5.1 | H46: 5 | I46: Identify system users, processes acting on behalf of users, and devices. | J46: Determine if: | K46: [No Comment Provided] | L46: Overall Status - Pending policy/procedure review meeting and observation of controls in place. Updates required to documentation Test required for validating controls in place Examine - Policy updates may be required based on interviews/walkthroughs. Interview Controls are currently being implemented. - Test - Review testing measures in place. | M46: Implementation Begun | O46: {=IF(AND(OR(M47="Fully Implemented",M47="Not Permitted"),OR(M48="Fully Implemented",M48="Not Permitted"),OR(M49="Fully Implemented",M49="Not Permitted")),0,-1*H46)} | T46: {=IF(O46=0,H46,0)}
A47: 1 | B47: 1.12.a | C47: DIY | D47: Identification and Authentication | E47: 3.5.1[a] | F47: 03.05.01.a | G47: IA.L1-3.5.1 | J47: system users are identified. | M47: Implementation Begun
A48: 1 | B48: 1.12.b | C48: Outsource | D48: Identification and Authentication | E48: 3.5.1[b] | F48: 03.05.01.b | G48: IA.L1-3.5.1 | J48: processes acting on behalf of users are identified. | M48: Implementation Begun
A49: 1 | B49: 1.12.c | C49: DIY | D49: Identification and Authentication | E49: 3.5.1[c] | F49: 03.05.01.c | G49: IA.L1-3.5.1 | J49: devices accessing the system are identified. | M49: Implementation Begun
A50: 1 | B50: 1.13.0 | C50: Hybrid | D50: Identification and Authentication | E50: 3.5.2 | F50: 03.05.02.0 | G50: IA.L1-3.5.2 | H50: 5 | I50: Authenticate (or verify) the identities of users, processes, or devices, as a prerequisite to allowing access to organizational systems | J50: Determine if: | K50: [No Comment Provided] | L50: Overall Status - Pending policy/procedure review meeting and observation of controls in place. Updates required to documentation Test required for validating controls in place Examine - Policy updates may be required based on interviews/walkthroughs. Interview Controls are currently being implemented. - Test - Review testing measures in place. | M50: Implementation Begun | O50: {=IF(AND(OR(M51="Fully Implemented",M51="Not Permitted"),OR(M52="Fully Implemented",M52="Not Permitted"),OR(M53="Fully Implemented",M53="Not Permitted")),0,-1*H50)} | T50: {=IF(O50=0,H50,0)}
A51: 1 | B51: 1.13.a | C51: DIY | D51: Identification and Authentication | E51: 3.5.2[a] | F51: 03.05.02.a | G51: IA.L1-3.5.2 | J51: the identity of each user is authenticated or verified as a prerequisite to system access. | M51: Implementation Begun
A52: 1 | B52: 1.13.b | C52: Outsource | D52: Identification and Authentication | E52: 3.5.2[b] | F52: 03.05.02.b | G52: IA.L1-3.5.2 | J52: the identity of each process acting on behalf of a user is authenticated or verified as a prerequisite to system access. | M52: Implementation Begun
A53: 1 | B53: 1.13.c | C53: Outsource | D53: Identification and Authentication | E53: 3.5.2[c] | F53: 03.05.02.c | G53: IA.L1-3.5.2 | J53: the identity of each device accessing or connecting to the system is authenticated or verified as a prerequisite to system access. | M53: Implementation Begun
A54: 1 | B54: 1.14.0 | C54: Hybrid | D54: Access Control | E54: 3.1.1 | F54: 03.01.01.0 | G54: AC.L1-3.1.1 | H54: 5 | I54: Limit system access to authorized users, processes acting on behalf of authorized users, and devices (including other systems). | J54: Determine If: | K54: [No Comment Provided] | L54: All access to corporate resources is routed through Cloudflare Zero Trust for Government (Access). Cloudflare Access enforces identity-based policies in conjunction with Okta for Government authentication, ensuring only authorized, verified users reach CUI-bearing systems regardless of network location. | M54: Implementation Begun | O54: {=IF(AND(M55="Fully Implemented",M56="Fully Implemented",M57="Fully Implemented",M58="Fully Implemented",M59="Fully Implemented",M60="Fully Implemented"),0,-1*H54)} | T54: {=IF(O54=0,H54,0)}
A55: 1 | B55: 1.14.a | C55: DIY | D55: Access Control | E55: 3.1.1[a] | F55: 03.01.01.a | G55: AC.L1-3.1.1 | J55: authorized users are identified. | M55: Implementation Begun
A56: 1 | B56: 1.14.b | C56: Outsource | D56: Access Control | E56: 3.1.1[b] | F56: 03.01.01.b | G56: AC.L1-3.1.1 | J56: processes acting on behalf of authorized users are identified. | M56: Implementation Begun
A57: 1 | B57: 1.14.c | C57: DIY | D57: Access Control | E57: 3.1.1[c] | F57: 03.01.01.c | G57: AC.L1-3.1.1 | J57: devices (including other systems) authorized to connect to the system are identified. | M57: Implementation Begun
A58: 1 | B58: 1.14.d | C58: DIY | D58: Access Control | E58: 3.1.1[d] | F58: 03.01.01.d | G58: AC.L1-3.1.1 | J58: system access is limited to authorized users. | M58: Implementation Begun
A59: 1 | B59: 1.14.e | C59: Outsource | D59: Access Control | E59: 3.1.1[e] | F59: 03.01.01.e | G59: AC.L1-3.1.1 | J59: system access is limited to processes acting on behalf of authorized users. | M59: Implementation Begun
A60: 1 | B60: 1.14.f | C60: Outsource | D60: Access Control | E60: 3.1.1[f] | F60: 03.01.01.f | G60: AC.L1-3.1.1 | J60: system access is limited to authorized devices (including other systems). | M60: Implementation Begun
A61: 1 | B61: 1.15.0 | C61: Outsource | D61: Access Control | E61: 3.1.2 | F61: 03.01.02.0 | G61: AC.L1-3.1.2 | H61: 5 | I61: Limit system access to the types of transactions and functions that authorized users are permitted to execute. | J61: Determine if: | K61: [No Comment Provided] | L61: Role-based access control (RBAC) is enforced through Okta group-to-application assignments. Cloudflare Access application policies provide a second enforcement layer, restricting which Okta groups may reach each application. M365 GCCH enforces SharePoint and Teams permissions aligned to job function. | M61: Implementation Begun | O61: {=IF(AND(M62="Fully Implemented",M63="Fully Implemented"),0,-1*H61)} | T61: {=IF(O61=0,H61,0)}
A62: 1 | B62: 1.15.a | C62: Outsource | D62: Access Control | E62: 3.1.2[a] | F62: 03.01.02.a | G62: AC.L1-3.1.2 | J62: the types of transactions and functions that authorized users are permitted to execute are defined | M62: Implementation Begun
A63: 1 | B63: 1.15.b | C63: Outsource | D63: Access Control | E63: 3.1.2[b] | F63: 03.01.02.b | G63: AC.L1-3.1.2 | J63: system access is limited to the defined types of transactions and functions for authorized users. | M63: Implementation Begun
A64: 1 | B64: 1.16.0 | C64: Hybrid | D64: Access Control | E64: 3.1.20 | F64: 03.01.20.0 | G64: AC.L1-3.1.20 | H64: 1 | I64: Verify and control/limit connections to and use of external systems. | J64: Determine if: | K64: [No Comment Provided] | L64: Connections to and use of external systems are controlled per the External System Connection Policy. All outbound connections from managed endpoints to external systems are subject to Cloudflare Gateway DNS and HTTP filtering policies — connections to non-approved external destinations are blocked at the network layer. Cloudflare CASB continuously monitors for unsanctioned external SaaS usage that could expose CUI. External user access to internal systems is provisioned through Okta for Government with scoped, time-limited application assignments and mandatory MFA. Azure AD B2B governance controls external identity access to M365 GCCH. Azure GCCH workloads use Private Endpoints and Private Link — no public internet-facing endpoints exist for CUI-bearing systems. All external system connection requests must be approved per the External System Connection Approval Procedure prior to provisioning. | M64: Implementation Begun | O64: {=IF(AND(M65="Fully Implemented",M66="Fully Implemented",M67="Fully Implemented",M68="Fully Implemented",M69="Fully Implemented",M70="Fully Implemented"),0,-1*H64)} | T64: {=IF(O64=0,H64,0)}
A65: 1 | B65: 1.16.a | C65: DIY | D65: Access Control | E65: 3.1.20[a] | F65: 03.01.20.a | G65: AC.L1-3.1.20 | J65: connections to external systems are identified. | M65: Implementation Begun
A66: 1 | B66: 1.16.b | C66: DIY | D66: Access Control | E66: 3.1.20[b] | F66: 03.01.20.b | G66: AC.L1-3.1.20 | J66: use of external systems is identified. | M66: Implementation Begun
A67: 1 | B67: 1.16.c | C67: Outsource | D67: Access Control | E67: 3.1.20[c] | F67: 03.01.20.c | G67: AC.L1-3.1.20 | J67: connections to external systems are verified. | M67: Implementation Begun
A68: 1 | B68: 1.16.d | C68: Outsource | D68: Access Control | E68: 3.1.20[d] | F68: 03.01.20.d | G68: AC.L1-3.1.20 | J68: use of external systems is verified. | M68: Implementation Begun
A69: 1 | B69: 1.16.e | C69: Outsource | D69: Access Control | E69: 3.1.20[e] | F69: 03.01.20.e | G69: AC.L1-3.1.20 | J69: connections to external systems are controlled/limited. | M69: Implementation Begun
A70: 1 | B70: 1.16.f | C70: Outsource | D70: Access Control | E70: 3.1.20[f] | F70: 03.01.20.f | G70: AC.L1-3.1.20 | J70: use of external systems is controlled/limited. | M70: Implementation Begun
A71: 1 | B71: 1.17.0 | C71: DIY | D71: Access Control | E71: 3.1.22 | F71: 03.01.22.0 | G71: AC.L1-3.1.22 | H71: 1 | I71: Control CUI posted or processed on publicly accessible systems. | J71: Determine if CUI posted or processed on publicly accessible systems is controlled. | K71: [No Comment Provided] | L71: CUI posted or processed on publicly accessible systems is controlled per the Public Posting Policy and CUI Program Policy. The organization's architecture is designed such that no CUI-bearing system has a publicly accessible endpoint — all organizational systems require authentication through Cloudflare Zero Trust for Government before any access is granted, regardless of whether the user is internal or external. | M71: Implementation Begun | O71: {=IF(AND(M72="Fully Implemented",M73="Fully Implemented",M74="Fully Implemented",M75="Fully Implemented",M76="Fully Implemented"),0,-1*H71)} | T71: {=IF(O71=0,H71,0)}
A72: 1 | B72: 1.17.a | C72: DIY | D72: Access Control | E72: 3.1.22[a] | F72: 03.01.22.a | G72: AC.L1-3.1.22 | J72: individuals authorized to post or process information on publicly accessible systems are identified. | M72: Implementation Begun
A73: 1 | B73: 1.17.b | C73: DIY | D73: Access Control | E73: 3.1.22[b] | F73: 03.01.22.b | G73: AC.L1-3.1.22 | J73: procedures to ensure CUI is not posted or processed on publicly accessible systems are identified. | L73: Microsoft Purview sensitivity labels classify all CUI within M365 GCCH. DLP policies enforce that CUI-labeled content cannot be posted to public SharePoint sites, external Teams channels, or any external-facing M365 surface. SharePoint external sharing is disabled at the tenant level. Azure Policy enforces that all Azure GCCH storage accounts have public blob access disabled — any attempt to enable public access is blocked and generates an alert in Microsoft Defender for Cloud. All Azure GCCH services are accessible only via Private Endpoints within the authorization boundary. | M73: Implementation Begun
A74: 1 | B74: 1.17.c | C74: DIY | D74: Access Control | E74: 3.1.22[c] | F74: 03.01.22.c | G74: AC.L1-3.1.22 | J74: a review process in in place prior to posting of any content to publicly accessible systems. | M74: Implementation Begun
A75: 1 | B75: 1.17.d | C75: DIY | D75: Access Control | E75: 3.1.22[d] | F75: 03.01.22.d | G75: AC.L1-3.1.22 | J75: content on publicly accessible information systems is reviewed to ensure that it does not include CUI. | L75: Cloudflare Gateway DLP policies scan all outbound HTTP traffic from managed endpoints for CUI data patterns, blocking or alerting on any attempt to upload or post CUI to external or public destinations. Cloudflare CASB performs continuous scanning of connected SaaS applications to detect publicly shared files or content containing CUI. Intune App Protection Policies prevent copy-paste transfer of CUI from managed applications to unmanaged or public-facing applications on all enrolled devices. | M75: Implementation Begun
A76: 1 | B76: 1.17.e | C76: DIY | D76: Access Control | E76: 3.1.22[e] | F76: 03.01.22.e | G76: AC.L1-3.1.22 | J76: mechanisms are in place to remove and address improper posting of CUI. | M76: Implementation Begun
A77: 2 | B77: 2.01.0 | C77: Hybrid | D77: Security Assessment | E77: 3.12.1 | F77: 03.12.01.0 | G77: CA.L2-3.12.1 | H77: 5 | I77: Periodically assess the security controls in organizational systems to determine if the controls are effective in their application. | J77: Determine if: | K77: [No Comment Provided] | L77: A designated Content Review Officer conducts quarterly reviews of all publicly accessible organizational web properties and content per the Publicly Accessible System Review SOP. Purview Content Explorer is used during each review cycle to identify any CUI-labeled content residing outside the authorization boundary. All findings are documented, remediated within 72 hours, and recorded in the organization's Plan of Action and Milestones (POA&M) if systemic issues are identified. | M77: Implementation Begun | O77: {=IF(AND(M78="Fully Implemented",M79="Fully Implemented"),0,-1*H77)} | T77: {=IF(O77=0,H77,0)} | U77: {=SUM(T77:T163)} | V77: 0
A78: 2 | B78: 2.01.a | C78: DIY | D78: Security Assessment | E78: 3.12.1[a] | F78: 03.12.01.a | G78: CA.L2-3.12.1 | J78: the frequency of security control assessments is defined. | M78: Implementation Begun
A79: 2 | B79: 2.01.b | C79: Outsource | D79: Security Assessment | E79: 3.12.1[b] | F79: 03.12.01.b | G79: CA.L2-3.12.1 | J79: security controls are assessed with the defined frequency to determine if the controls are effective in their application. | M79: Implementation Begun
A80: 2 | B80: 2.02.0 | C80: Hybrid | D80: Security Assessment | E80: 3.12.4 | F80: 03.12.04.0 | G80: CA.L2-3.12.4 | H80: 0 | I80: Develop, document, and periodically update system security plans that describe system boundaries, system environments of operation, how security requirements are implemented, and the relationships with or connections to other systems. | J80: Determine if: | K80: The absence of a system security plan would result in a finding that ‘an assessment could not be completed due to incomplete information and noncompliance with DFARS clause 252.204-7012.’ | M80: {=IF(AND(M81="Fully Implemented",M82="Fully Implemented",M83="Fully Implemented",M84="Fully Implemented",M85="Fully Implemented",M86="Fully Implemented",M87="Fully Implemented"),"Fully Implemented","")} | O80: {=IF(AND(M81="Fully Implemented",M82="Fully Implemented",M83="Fully Implemented",M84="Fully Implemented",M85="Fully Implemented",M86="Fully Implemented",M87="Fully Implemented"),0,-1000)} | T80: {=IF(O80=0,10,0)}
A81: 2 | B81: 2.02.a | C81: DIY | D81: Security Assessment | E81: 3.12.4[a] | F81: 03.12.04.a | G81: CA.L2-3.12.4 | J81: a system security plan is developed. | M81: Implementation Begun
A82: 2 | B82: 2.02.b | C82: Outsource | D82: Security Assessment | E82: 3.12.4[b] | F82: 03.12.04.b | G82: CA.L2-3.12.4 | J82: the system boundary is described and documented in the system security plan. | M82: Implementation Begun
A83: 2 | B83: 2.02.c | C83: Outsource | D83: Security Assessment | E83: 3.12.4[c] | F83: 03.12.04.c | G83: CA.L2-3.12.4 | J83: the system environment of operation is described and documented in the system security plan. | M83: Implementation Begun
A84: 2 | B84: 2.02.d | C84: Outsource | D84: Security Assessment | E84: 3.12.4[d] | F84: 03.12.04.d | G84: CA.L2-3.12.4 | J84: the security requirements identified and approved by the designated authority as non-applicable are identified. | M84: Implementation Begun
A85: 2 | B85: 2.02.e | C85: Outsource | D85: Security Assessment | E85: 3.12.4[e] | F85: 03.12.04.e | G85: CA.L2-3.12.4 | J85: the method of security requirement implementation is described and documented in the system security plan. | M85: Implementation Begun
A86: 2 | B86: 2.02.f | C86: Outsource | D86: Security Assessment | E86: 3.12.4[f] | F86: 03.12.04.f | G86: CA.L2-3.12.4 | J86: the relationship with or connection to other systems is described and documented in the system security plan. | M86: Implementation Begun
A87: 2 | B87: 2.02.g | C87: DIY | D87: Security Assessment | E87: 3.12.4[g] | F87: 03.12.04.g | G87: CA.L2-3.12.4 | J87: the frequency to update the system security plan is defined. | M87: Implementation Begun
A88: 2 | B88: 2.02.h | C88: DIY | D88: Security Assessment | E88: 3.12.4[h] | F88: 3.12.04.h | G88: CA.L2-3.12.4 | J88: system security plan is updated with the defined frequency. | M88: Implementation Begun
A89: 2 | B89: 2.03.0 | C89: Outsource | D89: Identification and Authentication | E89: 3.5.3 | F89: 03.05.03.0 | G89: IA.L2-3.5.3 | H89: 5 | I89: Use multifactor authentication for local and network access to privileged accounts and for network access to non-privileged accounts. | J89: Determine if: | K89: Subtract 5 points if MFA not implemented. Subtract 3 points if implemented for remote and privileged users, but not the general user | M89: {=IF(AND(M90="Fully Implemented",M91="Fully Implemented",M92="Fully Implemented",M93="Fully Implemented"),"Fully Implemented","")} | O89: {=IF(AND(M90="Fully Implemented",M91="Fully Implemented",M92="Fully Implemented",M93="Fully Implemented"),0,IF(AND(M90="Fully Implemented",M91="Fully Implemented",M92="Fully Implemented"),-3,-5))} | T89: {=IF(O89=0,H89,0)}
A90: 2 | B90: 2.03.a | C90: Outsource | D90: Identification and Authentication | E90: 3.5.3[a] | F90: 03.05.03.a | G90: IA.L2-3.5.3 | J90: privileged accounts are identified. | M90: Implementation Begun
A91: 2 | B91: 2.03.b | C91: Outsource | D91: Identification and Authentication | E91: 3.5.3[b] | F91: 03.05.03.b | G91: IA.L2-3.5.3 | J91: multifactor authentication is implemented for local access to privileged accounts. | M91: Implementation Begun
A92: 2 | B92: 2.03.c | C92: Outsource | D92: Identification and Authentication | E92: 3.5.3[c] | F92: 03.05.03.c | G92: IA.L2-3.5.3 | J92: multifactor authentication is implemented for network access to privileged accounts. | M92: Implementation Begun
A93: 2 | B93: 2.03.d | C93: Outsource | D93: Identification and Authentication | E93: 3.5.3[d] | F93: 03.05.03.d | G93: IA.L2-3.5.3 | J93: multifactor authentication is implemented for network access to non-privileged accounts. | M93: Implementation Begun
A94: 2 | B94: 2.04.0 | C94: Outsource | D94: Maintenance | E94: 3.7.5 | F94: 03.07.05.0 | G94: MA.L2-3.7.5 | H94: 5 | I94: Require multifactor authentication to establish nonlocal maintenance sessions via external network connections and terminate such connections when nonlocal maintenance is complete. | J94: Determine if: | K94: [No Comment Provided] | L94: Overall Status - Pending policy/procedure review meeting and observation of controls in place. Updates required to documentation Test required for validating controls in place Examine - Policy updates may be required based on interviews/walkthroughs. Interview Controls are currently being implemented. - Test - Review testing measures in place. | M94: Implementation Begun | O94: {=IF(AND(M95="Fully Implemented",M96="Fully Implemented"),0,-1*H94)} | T94: {=IF(O94=0,H94,0)}
A95: 2 | B95: 2.04.a | C95: Outsource | D95: Maintenance | E95: 3.7.5[a] | F95: 03.07.05.a | G95: MA.L2-3.7.5 | J95: multifactor authentication is required to establish nonlocal maintenance sessions via external network connections. | M95: Implementation Begun
A96: 2 | B96: 2.04.b | C96: Outsource | D96: Maintenance | E96: 3.7.5[b] | F96: 03.07.05.b | G96: MA.L2-3.7.5 | J96: nonlocal maintenance sessions established via external network connections are terminated when nonlocal maintenance is complete. | M96: Implementation Begun
A97: 3 | B97: 3.15.0 | C97: DIY | D97: Access Control | E97: 3.1.10 | F97: 03.01.10.0 | G97: AC.L2-3.1.10 | H97: 1 | I97: Use session lock with pattern-hiding displays to prevent access and viewing of data after a period of inactivity. | J97: Determine if: | K97: [No Comment Provided] | L97: Session lock is enforced via Intune MDM configuration profiles on all enrolled devices, requiring screen lock after 15 minutes of inactivity. Cloudflare Access device posture checks verify that screen lock policy is active on the endpoint — devices failing the posture check are denied access. CrowdStrike Falcon device health feeds into Cloudflare posture evaluation. | M97: Implementation Begun | O97: {=IF(AND(OR(M98="Fully Implemented",M98="Not Permitted"),OR(M99="Fully Implemented",M99="Not Permitted"),OR(M100="Fully Implemented",M100="Not Permitted")),0,-1*H97)} | T97: {=IF(O97=0,H97,0)}
A98: 3 | B98: 3.15.a | C98: DIY | D98: Access Control | E98: 3.1.10[a] | F98: 03.01.10.a | G98: AC.L2-3.1.10 | J98: the period of inactivity after which the system initiates a session lock is defined. | M98: Implementation Begun
A99: 3 | B99: 3.15.b | C99: DIY | D99: Access Control | E99: 3.1.10[b] | F99: 03.01.10.b | G99: AC.L2-3.1.10 | J99: access to the system and viewing of data is prevented by initiating a session lock after the defined period of inactivity. | M99: Implementation Begun
A100: 2 | B100: 2.06.0 | C100: DIY | D100: Physical Protection | E100: 3.10.2 | F100: 03.10.02.0 | G100: PE.L2-3.10.2 | H100: 5 | I100: Protect and monitor the physical facility and support infrastructure for organizational systems. | J100: Determine if: | K100: [No Comment Provided] | L100: Overall Status Meets - Pending policy/procedure review meeting and observation of controls in place. Updates required to documentation Test required for validating controls in place Examine - Policy updates required. Interview Controls are currently being implemented. - Test - Review testing measures in place. Canopy A&D - 3.10 - Physical and Environmental Protection Policy, Page 1-4 | M100: Implementation Begun | O100: {=IF(AND(M101="Fully Implemented",M102="Fully Implemented",M103="Fully Implemented",M104="Fully Implemented"),0,-1*H100)} | T100: {=IF(O100=0,H100,0)}
...

Sheet POA&Ms
B1: Relevant Requirement(s)/Objective(s): | C1: 3.12.2a, 3.12.2b | D1: Last Reviewed by (and on): Genemar Lazo
A2: Plans of Action and Milestones (Scroll Down for Complete List)
A3: Requirement/Objective w/Other Than Fully Addressed Status | B3: Responsible Office/Organization | C3: Resource Estimate (Funded, Unfunded, Reallocated) | D3: Initial Remediation Plan Milestones with Interim Completion Dates | E3: Changes to Milestones
A4: {=IF('SSP - DoD SPRS & FAR and Above'!M410<>"Fully Addressed",'SSP - DoD SPRS & FAR and Above'!E410&" - "&IF('SSP - DoD SPRS & FAR and Above'!I410<>"",'SSP - DoD SPRS & FAR and Above'!I410,'SSP - DoD SPRS & FAR and Above'!J410))}
A5: {=IF('SSP - DoD SPRS & FAR and Above'!M54<>"Fully Addressed",'SSP - DoD SPRS & FAR and Above'!E54&" - "&IF('SSP - DoD SPRS & FAR and Above'!I54<>"",'SSP - DoD SPRS & FAR and Above'!I54,'SSP - DoD SPRS & FAR and Above'!J54))} | B5: ISO/CISO | C5: Funded | D5: Export Entra Conditional Access & PIM/PAM approvals; provide VPN/VDI/firewall configs enforcing managed access points and FIPS-validated crypto; wireless WPA-Enterprise configs; GPO/MDM for session lock/termination. | E5: Estimate - 60 days to remediate Policies and SSP available; attach configs/logs/records as noted
A6: {=IF('SSP - DoD SPRS & FAR and Above'!M55<>"Fully Addressed",'SSP - DoD SPRS & FAR and Above'!E55&" - "&IF('SSP - DoD SPRS & FAR and Above'!I55<>"",'SSP - DoD SPRS & FAR and Above'!I55,'SSP - DoD SPRS & FAR and Above'!J55))} | B6: ISO/CISO | C6: Funded | D6: Export Entra Conditional Access & PIM/PAM approvals; provide VPN/VDI/firewall configs enforcing managed access points and FIPS-validated crypto; wireless WPA-Enterprise configs; GPO/MDM for session lock/termination. | E6: Estimate - 60 days to remediate Policies and SSP available; attach configs/logs/records as noted
A7: {=IF('SSP - DoD SPRS & FAR and Above'!M56<>"Fully Addressed",'SSP - DoD SPRS & FAR and Above'!E56&" - "&IF('SSP - DoD SPRS & FAR and Above'!I56<>"",'SSP - DoD SPRS & FAR and Above'!I56,'SSP - DoD SPRS & FAR and Above'!J56))} | B7: ISO/CISO | C7: Funded | D7: Export Entra Conditional Access & PIM/PAM approvals; provide VPN/VDI/firewall configs enforcing managed access points and FIPS-validated crypto; wireless WPA-Enterprise configs; GPO/MDM for session lock/termination. | E7: Estimate - 60 days to remediate Policies and SSP available; attach configs/logs/records as noted
A8: {=IF('SSP - DoD SPRS & FAR and Above'!M57<>"Fully Addressed",'SSP - DoD SPRS & FAR and Above'!E57&" - "&IF('SSP - DoD SPRS & FAR and Above'!I57<>"",'SSP - DoD SPRS & FAR and Above'!I57,'SSP - DoD SPRS & FAR and Above'!J57))} | B8: ISO/CISO | C8: Funded | D8: Export Entra Conditional Access & PIM/PAM approvals; provide VPN/VDI/firewall configs enforcing managed access points and FIPS-validated crypto; wireless WPA-Enterprise configs; GPO/MDM for session lock/termination. | E8: Estimate - 60 days to remediate Policies and SSP available; attach configs/logs/records as noted
A9: {=IF('SSP - DoD SPRS & FAR and Above'!M58<>"Fully Addressed",'SSP - DoD SPRS & FAR and Above'!E58&" - "&IF('SSP - DoD SPRS & FAR and Above'!I58<>"",'SSP - DoD SPRS & FAR and Above'!I58,'SSP - DoD SPRS & FAR and Above'!J58))} | B9: ISO/CISO | C9: Funded | D9: Export Entra Conditional Access & PIM/PAM approvals; provide VPN/VDI/firewall configs enforcing managed access points and FIPS-validated crypto; wireless WPA-Enterprise configs; GPO/MDM for session lock/termination. | E9: Estimate - 60 days to remediate Policies and SSP available; attach configs/logs/records as noted
A10: {=IF('SSP - DoD SPRS & FAR and Above'!M59<>"Fully Addressed",'SSP - DoD SPRS & FAR and Above'!E59&" - "&IF('SSP - DoD SPRS & FAR and Above'!I59<>"",'SSP - DoD SPRS & FAR and Above'!I59,'SSP - DoD SPRS & FAR and Above'!J59))} | B10: ISO/CISO | C10: Funded | D10: Export Entra Conditional Access & PIM/PAM approvals; provide VPN/VDI/firewall configs enforcing managed access points and FIPS-validated crypto; wireless WPA-Enterprise configs; GPO/MDM for session lock/termination. | E10: Estimate - 60 days to remediate Policies and SSP available; attach configs/logs/records as noted
A11: {=IF('SSP - DoD SPRS & FAR and Above'!M60<>"Fully Addressed",'SSP - DoD SPRS & FAR and Above'!E60&" - "&IF('SSP - DoD SPRS & FAR and Above'!I60<>"",'SSP - DoD SPRS & FAR and Above'!I60,'SSP - DoD SPRS & FAR and Above'!J60))} | B11: ISO/CISO | C11: Funded | D11: Export Entra Conditional Access & PIM/PAM approvals; provide VPN/VDI/firewall configs enforcing managed access points and FIPS-validated crypto; wireless WPA-Enterprise configs; GPO/MDM for session lock/termination. | E11: Estimate - 60 days to remediate Policies and SSP available; attach configs/logs/records as noted
A12: {=IF('SSP - DoD SPRS & FAR and Above'!M217<>"Fully Addressed",'SSP - DoD SPRS & FAR and Above'!E217&" - "&IF('SSP - DoD SPRS & FAR and Above'!I217<>"",'SSP - DoD SPRS & FAR and Above'!I217,'SSP - DoD SPRS & FAR and Above'!J217))} | B12: ISO/CISO | C12: Funded | D12: Export Entra Conditional Access & PIM/PAM approvals; provide VPN/VDI/firewall configs enforcing managed access points and FIPS-validated crypto; wireless WPA-Enterprise configs; GPO/MDM for session lock/termination. | E12: Estimate - 60 days to remediate Policies and SSP available; attach configs/logs/records as noted
A13: {=IF('SSP - DoD SPRS & FAR and Above'!M218<>"Fully Addressed",'SSP - DoD SPRS & FAR and Above'!E218&" - "&IF('SSP - DoD SPRS & FAR and Above'!I218<>"",'SSP - DoD SPRS & FAR and Above'!I218,'SSP - DoD SPRS & FAR and Above'!J218))} | B13: ISO/CISO | C13: Funded | D13: Export Entra Conditional Access & PIM/PAM approvals; provide VPN/VDI/firewall configs enforcing managed access points and FIPS-validated crypto; wireless WPA-Enterprise configs; GPO/MDM for session lock/termination. | E13: Estimate - 60 days to remediate Policies and SSP available; attach configs/logs/records as noted
A14: {=IF('SSP - DoD SPRS & FAR and Above'!M219<>"Fully Addressed",'SSP - DoD SPRS & FAR and Above'!E219&" - "&IF('SSP - DoD SPRS & FAR and Above'!I219<>"",'SSP - DoD SPRS & FAR and Above'!I219,'SSP - DoD SPRS & FAR and Above'!J219))} | B14: ISO/CISO | C14: Funded | D14: Export Entra Conditional Access & PIM/PAM approvals; provide VPN/VDI/firewall configs enforcing managed access points and FIPS-validated crypto; wireless WPA-Enterprise configs; GPO/MDM for session lock/termination. | E14: Estimate - 60 days to remediate Policies and SSP available; attach configs/logs/records as noted
A15: {=IF('SSP - DoD SPRS & FAR and Above'!M220<>"Fully Addressed",'SSP - DoD SPRS & FAR and Above'!E220&" - "&IF('SSP - DoD SPRS & FAR and Above'!I220<>"",'SSP - DoD SPRS & FAR and Above'!I220,'SSP - DoD SPRS & FAR and Above'!J220))} | B15: ISO/CISO | C15: Funded | D15: Export Entra Conditional Access & PIM/PAM approvals; provide VPN/VDI/firewall configs enforcing managed access points and FIPS-validated crypto; wireless WPA-Enterprise configs; GPO/MDM for session lock/termination. | E15: Estimate - 60 days to remediate Policies and SSP available; attach configs/logs/records as noted
A16: {=IF('SSP - DoD SPRS & FAR and Above'!M379<>"Fully Addressed",'SSP - DoD SPRS & FAR and Above'!E379&" - "&IF('SSP - DoD SPRS & FAR and Above'!I379<>"",'SSP - DoD SPRS & FAR and Above'!I379,'SSP - DoD SPRS & FAR and Above'!J379))} | B16: ISO/CISO | C16: Funded | D16: Export Entra Conditional Access & PIM/PAM approvals; provide VPN/VDI/firewall configs enforcing managed access points and FIPS-validated crypto; wireless WPA-Enterprise configs; GPO/MDM for session lock/termination. | E16: Estimate - 60 days to remediate Policies and SSP available; attach configs/logs/records as noted
A17: {=IF('SSP - DoD SPRS & FAR and Above'!M380<>"Fully Addressed",'SSP - DoD SPRS & FAR and Above'!E380&" - "&IF('SSP - DoD SPRS & FAR and Above'!I380<>"",'SSP - DoD SPRS & FAR and Above'!I380,'SSP - DoD SPRS & FAR and Above'!J380))} | B17: ISO/CISO | C17: Funded | D17: Export Entra Conditional Access & PIM/PAM approvals; provide VPN/VDI/firewall configs enforcing managed access points and FIPS-validated crypto; wireless WPA-Enterprise configs; GPO/MDM for session lock/termination. | E17: Estimate - 60 days to remediate Policies and SSP available; attach configs/logs/records as noted
A18: {=IF('SSP - DoD SPRS & FAR and Above'!M381<>"Fully Addressed",'SSP - DoD SPRS & FAR and Above'!E381&" - "&IF('SSP - DoD SPRS & FAR and Above'!I381<>"",'SSP - DoD SPRS & FAR and Above'!I381,'SSP - DoD SPRS & FAR and Above'!J381))} | B18: ISO/CISO | C18: Funded | D18: Export Entra Conditional Access & PIM/PAM approvals; provide VPN/VDI/firewall configs enforcing managed access points and FIPS-validated crypto; wireless WPA-Enterprise configs; GPO/MDM for session lock/termination. | E18: Estimate - 60 days to remediate Policies and SSP available; attach configs/logs/records as noted
A19: {=IF('SSP - DoD SPRS & FAR and Above'!M176<>"Fully Addressed",'SSP - DoD SPRS & FAR and Above'!E176&" - "&IF('SSP - DoD SPRS & FAR and Above'!I176<>"",'SSP - DoD SPRS & FAR and Above'!I176,'SSP - DoD SPRS & FAR and Above'!J176))} | B19: ISO/CISO | C19: Funded | D19: Export Entra Conditional Access & PIM/PAM approvals; provide VPN/VDI/firewall configs enforcing managed access points and FIPS-validated crypto; wireless WPA-Enterprise configs; GPO/MDM for session lock/termination. | E19: Estimate - 60 days to remediate Policies and SSP available; attach configs/logs/records as noted
A20: {=IF('SSP - DoD SPRS & FAR and Above'!M177<>"Fully Addressed",'SSP - DoD SPRS & FAR and Above'!E177&" - "&IF('SSP - DoD SPRS & FAR and Above'!I177<>"",'SSP - DoD SPRS & FAR and Above'!I177,'SSP - DoD SPRS & FAR and Above'!J177))} | B20: ISO/CISO | C20: Funded | D20: Export Entra Conditional Access & PIM/PAM approvals; provide VPN/VDI/firewall configs enforcing managed access points and FIPS-validated crypto; wireless WPA-Enterprise configs; GPO/MDM for session lock/termination. | E20: Estimate - 60 days to remediate Policies and SSP available; attach configs/logs/records as noted
A21: {=IF('SSP - DoD SPRS & FAR and Above'!M178<>"Fully Addressed",'SSP - DoD SPRS & FAR and Above'!E178&" - "&IF('SSP - DoD SPRS & FAR and Above'!I178<>"",'SSP - DoD SPRS & FAR and Above'!I178,'SSP - DoD SPRS & FAR and Above'!J178))} | B21: ISO/CISO | C21: Funded | D21: Export Entra Conditional Access & PIM/PAM approvals; provide VPN/VDI/firewall configs enforcing managed access points and FIPS-validated crypto; wireless WPA-Enterprise configs; GPO/MDM for session lock/termination. | E21: Estimate - 60 days to remediate Policies and SSP available; attach configs/logs/records as noted
A22: {=IF('SSP - DoD SPRS & FAR and Above'!M179<>"Fully Addressed",'SSP - DoD SPRS & FAR and Above'!E179&" - "&IF('SSP - DoD SPRS & FAR and Above'!I179<>"",'SSP - DoD SPRS & FAR and Above'!I179,'SSP - DoD SPRS & FAR and Above'!J179))} | B22: ISO/CISO | C22: Funded | D22: Export Entra Conditional Access & PIM/PAM approvals; provide VPN/VDI/firewall configs enforcing managed access points and FIPS-validated crypto; wireless WPA-Enterprise configs; GPO/MDM for session lock/termination. | E22: Estimate - 60 days to remediate Policies and SSP available; attach configs/logs/records as noted
A23: {=IF('SSP - DoD SPRS & FAR and Above'!M180<>"Fully Addressed",'SSP - DoD SPRS & FAR and Above'!E180&" - "&IF('SSP - DoD SPRS & FAR and Above'!I180<>"",'SSP - DoD SPRS & FAR and Above'!I180,'SSP - DoD SPRS & FAR and Above'!J180))} | B23: ISO/CISO | C23: Funded | D23: Export Entra Conditional Access & PIM/PAM approvals; provide VPN/VDI/firewall configs enforcing managed access points and FIPS-validated crypto; wireless WPA-Enterprise configs; GPO/MDM for session lock/termination. | E23: Estimate - 60 days to remediate Policies and SSP available; attach configs/logs/records as noted
A24: {=IF('SSP - DoD SPRS & FAR and Above'!M181<>"Fully Addressed",'SSP - DoD SPRS & FAR and Above'!E181&" - "&IF('SSP - DoD SPRS & FAR and Above'!I181<>"",'SSP - DoD SPRS & FAR and Above'!I181,'SSP - DoD SPRS & FAR and Above'!J181))} | B24: ISO/CISO | C24: Funded | D24: Export Entra Conditional Access & PIM/PAM approvals; provide VPN/VDI/firewall configs enforcing managed access points and FIPS-validated crypto; wireless WPA-Enterprise configs; GPO/MDM for session lock/termination. | E24: Estimate - 60 days to remediate Policies and SSP available; attach configs/logs/records as noted
A25: {=IF('SSP - DoD SPRS & FAR and Above'!M182<>"Fully Addressed",'SSP - DoD SPRS & FAR and Above'!E182&" - "&IF('SSP - DoD SPRS & FAR and Above'!I182<>"",'SSP - DoD SPRS & FAR and Above'!I182,'SSP - DoD SPRS & FAR and Above'!J182))} | B25: ISO/CISO | C25: Funded | D25: Export Entra Conditional Access & PIM/PAM approvals; provide VPN/VDI/firewall configs enforcing managed access points and FIPS-validated crypto; wireless WPA-Enterprise configs; GPO/MDM for session lock/termination. | E25: Estimate - 60 days to remediate Policies and SSP available; attach configs/logs/records as noted
A26: {=IF('SSP - DoD SPRS & FAR and Above'!M183<>"Fully Addressed",'SSP - DoD SPRS & FAR and Above'!E183&" - "&IF('SSP - DoD SPRS & FAR and Above'!I183<>"",'SSP - DoD SPRS & FAR and Above'!I183,'SSP - DoD SPRS & FAR and Above'!J183))} | B26: ISO/CISO | C26: Funded | D26: Export Entra Conditional Access & PIM/PAM approvals; provide VPN/VDI/firewall configs enforcing managed access points and FIPS-validated crypto; wireless WPA-Enterprise configs; GPO/MDM for session lock/termination. | E26: Estimate - 60 days to remediate Policies and SSP available; attach configs/logs/records as noted
A27: {=IF('SSP - DoD SPRS & FAR and Above'!M399<>"Fully Addressed",'SSP - DoD SPRS & FAR and Above'!E399&" - "&IF('SSP - DoD SPRS & FAR and Above'!I399<>"",'SSP - DoD SPRS & FAR and Above'!I399,'SSP - DoD SPRS & FAR and Above'!J399))} | B27: ISO/CISO | C27: Funded | D27: Export Entra Conditional Access & PIM/PAM approvals; provide VPN/VDI/firewall configs enforcing managed access points and FIPS-validated crypto; wireless WPA-Enterprise configs; GPO/MDM for session lock/termination. | E27: Estimate - 60 days to remediate Policies and SSP available; attach configs/logs/records as noted
A28: {=IF('SSP - DoD SPRS & FAR and Above'!M400<>"Fully Addressed",'SSP - DoD SPRS & FAR and Above'!E400&" - "&IF('SSP - DoD SPRS & FAR and Above'!I400<>"",'SSP - DoD SPRS & FAR and Above'!I400,'SSP - DoD SPRS & FAR and Above'!J400))} | B28: ISO/CISO | C28: Funded | D28: Export Entra Conditional Access & PIM/PAM approvals; provide VPN/VDI/firewall configs enforcing managed access points and FIPS-validated crypto; wireless WPA-Enterprise configs; GPO/MDM for session lock/termination. | E28: Estimate - 60 days to remediate Policies and SSP available; attach configs/logs/records as noted
A29: {=IF('SSP - DoD SPRS & FAR and Above'!M401<>"Fully Addressed",'SSP - DoD SPRS & FAR and Above'!E401&" - "&IF('SSP - DoD SPRS & FAR and Above'!I401<>"",'SSP - DoD SPRS & FAR and Above'!I401,'SSP - DoD SPRS & FAR and Above'!J401))} | B29: ISO/CISO | C29: Funded | D29: Export Entra Conditional Access & PIM/PAM approvals; provide VPN/VDI/firewall configs enforcing managed access points and FIPS-validated crypto; wireless WPA-Enterprise configs; GPO/MDM for session lock/termination. | E29: Estimate - 60 days to remediate Policies and SSP available; attach configs/logs/records as noted
A30: {=IF('SSP - DoD SPRS & FAR and Above'!M402<>"Fully Addressed",'SSP - DoD SPRS & FAR and Above'!E402&" - "&IF('SSP - DoD SPRS & FAR and Above'!I402<>"",'SSP - DoD SPRS & FAR and Above'!I402,'SSP - DoD SPRS & FAR and Above'!J402))} | B30: ISO/CISO | C30: Funded | D30: Export Entra Conditional Access & PIM/PAM approvals; provide VPN/VDI/firewall configs enforcing managed access points and FIPS-validated crypto; wireless WPA-Enterprise configs; GPO/MDM for session lock/termination. | E30: Estimate - 60 days to remediate Policies and SSP available; attach configs/logs/records as noted
A31: {=IF('SSP - DoD SPRS & FAR and Above'!M403<>"Fully Addressed",'SSP - DoD SPRS & FAR and Above'!E403&" - "&IF('SSP - DoD SPRS & FAR and Above'!I403<>"",'SSP - DoD SPRS & FAR and Above'!I403,'SSP - DoD SPRS & FAR and Above'!J403))} | B31: ISO/CISO | C31: Funded | D31: Export Entra Conditional Access & PIM/PAM approvals; provide VPN/VDI/firewall configs enforcing managed access points and FIPS-validated crypto; wireless WPA-Enterprise configs; GPO/MDM for session lock/termination. | E31: Estimate - 60 days to remediate Policies and SSP available; attach configs/logs/records as noted
A32: {=IF('SSP - DoD SPRS & FAR and Above'!M404<>"Fully Addressed",'SSP - DoD SPRS & FAR and Above'!E404&" - "&IF('SSP - DoD SPRS & FAR and Above'!I404<>"",'SSP - DoD SPRS & FAR and Above'!I404,'SSP - DoD SPRS & FAR and Above'!J404))} | B32: ISO/CISO | C32: Funded | D32: Export Entra Conditional Access & PIM/PAM approvals; provide VPN/VDI/firewall configs enforcing managed access points and FIPS-validated crypto; wireless WPA-Enterprise configs; GPO/MDM for session lock/termination. | E32: Estimate - 60 days to remediate Policies and SSP available; attach configs/logs/records as noted
A33: {=IF('SSP - DoD SPRS & FAR and Above'!M405<>"Fully Addressed",'SSP - DoD SPRS & FAR and Above'!E405&" - "&IF('SSP - DoD SPRS & FAR and Above'!I405<>"",'SSP - DoD SPRS & FAR and Above'!I405,'SSP - DoD SPRS & FAR and Above'!J405))} | B33: ISO/CISO | C33: Funded | D33: Export Entra Conditional Access & PIM/PAM approvals; provide VPN/VDI/firewall configs enforcing managed access points and FIPS-validated crypto; wireless WPA-Enterprise configs; GPO/MDM for session lock/termination. | E33: Estimate - 60 days to remediate Policies and SSP available; attach configs/logs/records as noted
A34: {=IF('SSP - DoD SPRS & FAR and Above'!M406<>"Fully Addressed",'SSP - DoD SPRS & FAR and Above'!E406&" - "&IF('SSP - DoD SPRS & FAR and Above'!I406<>"",'SSP - DoD SPRS & FAR and Above'!I406,'SSP - DoD SPRS & FAR and Above'!J406))} | B34: ISO/CISO | C34: Funded | D34: Export Entra Conditional Access & PIM/PAM approvals; provide VPN/VDI/firewall configs enforcing managed access points and FIPS-validated crypto; wireless WPA-Enterprise configs; GPO/MDM for session lock/termination. | E34: Estimate - 60 days to remediate Policies and SSP available; attach configs/logs/records as noted
A35: {=IF('SSP - DoD SPRS & FAR and Above'!M173<>"Fully Addressed",'SSP - DoD SPRS & FAR and Above'!E173&" - "&IF('SSP - DoD SPRS & FAR and Above'!I173<>"",'SSP - DoD SPRS & FAR and Above'!I173,'SSP - DoD SPRS & FAR and Above'!J173))} | B35: ISO/CISO | C35: Funded | D35: Export Entra Conditional Access & PIM/PAM approvals; provide VPN/VDI/firewall configs enforcing managed access points and FIPS-validated crypto; wireless WPA-Enterprise configs; GPO/MDM for session lock/termination. | E35: Estimate - 60 days to remediate Policies and SSP available; attach configs/logs/records as noted
A36: {=IF('SSP - DoD SPRS & FAR and Above'!M174<>"Fully Addressed",'SSP - DoD SPRS & FAR and Above'!E174&" - "&IF('SSP - DoD SPRS & FAR and Above'!I174<>"",'SSP - DoD SPRS & FAR and Above'!I174,'SSP - DoD SPRS & FAR and Above'!J174))} | B36: ISO/CISO | C36: Funded | D36: Export Entra Conditional Access & PIM/PAM approvals; provide VPN/VDI/firewall configs enforcing managed access points and FIPS-validated crypto; wireless WPA-Enterprise configs; GPO/MDM for session lock/termination. | E36: Estimate - 60 days to remediate Policies and SSP available; attach configs/logs/records as noted
A37: {=IF('SSP - DoD SPRS & FAR and Above'!M175<>"Fully Addressed",'SSP - DoD SPRS & FAR and Above'!E175&" - "&IF('SSP - DoD SPRS & FAR and Above'!I175<>"",'SSP - DoD SPRS & FAR and Above'!I175,'SSP - DoD SPRS & FAR and Above'!J175))} | B37: ISO/CISO | C37: Funded | D37: Export Entra Conditional Access & PIM/PAM approvals; provide VPN/VDI/firewall configs enforcing managed access points and FIPS-validated crypto; wireless WPA-Enterprise configs; GPO/MDM for session lock/termination. | E37: Estimate - 60 days to remediate Policies and SSP available; attach configs/logs/records as noted
A38: {=IF('SSP - DoD SPRS & FAR and Above'!M170<>"Fully Addressed",'SSP - DoD SPRS & FAR and Above'!E170&" - "&IF('SSP - DoD SPRS & FAR and Above'!I170<>"",'SSP - DoD SPRS & FAR and Above'!I170,'SSP - DoD SPRS & FAR and Above'!J170))} | B38: ISO/CISO | C38: Funded | D38: Export Entra Conditional Access & PIM/PAM approvals; provide VPN/VDI/firewall configs enforcing managed access points and FIPS-validated crypto; wireless WPA-Enterprise configs; GPO/MDM for session lock/termination. | E38: Estimate - 60 days to remediate Policies and SSP available; attach configs/logs/records as noted
A39: {=IF('SSP - DoD SPRS & FAR and Above'!M171<>"Fully Addressed",'SSP - DoD SPRS & FAR and Above'!E171&" - "&IF('SSP - DoD SPRS & FAR and Above'!I171<>"",'SSP - DoD SPRS & FAR and Above'!I171,'SSP - DoD SPRS & FAR and Above'!J171))} | B39: ISO/CISO | C39: Funded | D39: Export Entra Conditional Access & PIM/PAM approvals; provide VPN/VDI/firewall configs enforcing managed access points and FIPS-validated crypto; wireless WPA-Enterprise configs; GPO/MDM for session lock/termination. | E39: Estimate - 60 days to remediate Policies and SSP available; attach configs/logs/records as noted
A40: {=IF('SSP - DoD SPRS & FAR and Above'!M172<>"Fully Addressed",'SSP - DoD SPRS & FAR and Above'!E172&" - "&IF('SSP - DoD SPRS & FAR and Above'!I172<>"",'SSP - DoD SPRS & FAR and Above'!I172,'SSP - DoD SPRS & FAR and Above'!J172))} | B40: ISO/CISO | C40: Funded | D40: Export Entra Conditional Access & PIM/PAM approvals; provide VPN/VDI/firewall configs enforcing managed access points and FIPS-validated crypto; wireless WPA-Enterprise configs; GPO/MDM for session lock/termination. | E40: Estimate - 60 days to remediate Policies and SSP available; attach configs/logs/records as noted
A41: {=IF('SSP - DoD SPRS & FAR and Above'!M213<>"Fully Addressed",'SSP - DoD SPRS & FAR and Above'!E213&" - "&IF('SSP - DoD SPRS & FAR and Above'!I213<>"",'SSP - DoD SPRS & FAR and Above'!I213,'SSP - DoD SPRS & FAR and Above'!J213))} | B41: ISO/CISO | C41: Funded | D41: Export Entra Conditional Access & PIM/PAM approvals; provide VPN/VDI/firewall configs enforcing managed access points and FIPS-validated crypto; wireless WPA-Enterprise configs; GPO/MDM for session lock/termination. | E41: Estimate - 60 days to remediate Policies and SSP available; attach configs/logs/records as noted
A42: {=IF('SSP - DoD SPRS & FAR and Above'!M214<>"Fully Addressed",'SSP - DoD SPRS & FAR and Above'!E214&" - "&IF('SSP - DoD SPRS & FAR and Above'!I214<>"",'SSP - DoD SPRS & FAR and Above'!I214,'SSP - DoD SPRS & FAR and Above'!J214))} | B42: ISO/CISO | C42: Funded | D42: Export Entra Conditional Access & PIM/PAM approvals; provide VPN/VDI/firewall configs enforcing managed access points and FIPS-validated crypto; wireless WPA-Enterprise configs; GPO/MDM for session lock/termination. | E42: Estimate - 60 days to remediate Policies and SSP available; attach configs/logs/records as noted
A43: {=IF('SSP - DoD SPRS & FAR and Above'!M215<>"Fully Addressed",'SSP - DoD SPRS & FAR and Above'!E215&" - "&IF('SSP - DoD SPRS & FAR and Above'!I215<>"",'SSP - DoD SPRS & FAR and Above'!I215,'SSP - DoD SPRS & FAR and Above'!J215))} | B43: ISO/CISO | C43: Funded | D43: Export Entra Conditional Access & PIM/PAM approvals; provide VPN/VDI/firewall configs enforcing managed access points and FIPS-validated crypto; wireless WPA-Enterprise configs; GPO/MDM for session lock/termination. | E43: Estimate - 60 days to remediate Policies and SSP available; attach configs/logs/records as noted
A44: {=IF('SSP - DoD SPRS & FAR and Above'!M216<>"Fully Addressed",'SSP - DoD SPRS & FAR and Above'!E216&" - "&IF('SSP - DoD SPRS & FAR and Above'!I216<>"",'SSP - DoD SPRS & FAR and Above'!I216,'SSP - DoD SPRS & FAR and Above'!J216))} | B44: ISO/CISO | C44: Funded | D44: Export Entra Conditional Access & PIM/PAM approvals; provide VPN/VDI/firewall configs enforcing managed access points and FIPS-validated crypto; wireless WPA-Enterprise configs; GPO/MDM for session lock/termination. | E44: Estimate - 60 days to remediate Policies and SSP available; attach configs/logs/records as noted
A45: {=IF('SSP - DoD SPRS & FAR and Above'!M315<>"Fully Addressed",'SSP - DoD SPRS & FAR and Above'!E315&" - "&IF('SSP - DoD SPRS & FAR and Above'!I315<>"",'SSP - DoD SPRS & FAR and Above'!I315,'SSP - DoD SPRS & FAR and Above'!J315))} | B45: ISO/CISO | C45: Funded | D45: Export Entra Conditional Access & PIM/PAM approvals; provide VPN/VDI/firewall configs enforcing managed access points and FIPS-validated crypto; wireless WPA-Enterprise configs; GPO/MDM for session lock/termination. | E45: Estimate - 60 days to remediate Policies and SSP available; attach configs/logs/records as noted
A46: {=IF('SSP - DoD SPRS & FAR and Above'!M316<>"Fully Addressed",'SSP - DoD SPRS & FAR and Above'!E316&" - "&IF('SSP - DoD SPRS & FAR and Above'!I316<>"",'SSP - DoD SPRS & FAR and Above'!I316,'SSP - DoD SPRS & FAR and Above'!J316))} | B46: ISO/CISO | C46: Funded | D46: Export Entra Conditional Access & PIM/PAM approvals; provide VPN/VDI/firewall configs enforcing managed access points and FIPS-validated crypto; wireless WPA-Enterprise configs; GPO/MDM for session lock/termination. | E46: Estimate - 60 days to remediate Policies and SSP available; attach configs/logs/records as noted
A47: {=IF('SSP - DoD SPRS & FAR and Above'!M317<>"Fully Addressed",'SSP - DoD SPRS & FAR and Above'!E317&" - "&IF('SSP - DoD SPRS & FAR and Above'!I317<>"",'SSP - DoD SPRS & FAR and Above'!I317,'SSP - DoD SPRS & FAR and Above'!J317))} | B47: ISO/CISO | C47: Funded | D47: Export Entra Conditional Access & PIM/PAM approvals; provide VPN/VDI/firewall configs enforcing managed access points and FIPS-validated crypto; wireless WPA-Enterprise configs; GPO/MDM for session lock/termination. | E47: Estimate - 60 days to remediate Policies and SSP available; attach configs/logs/records as noted
A48: {=IF('SSP - DoD SPRS & FAR and Above'!M61<>"Fully Addressed",'SSP - DoD SPRS & FAR and Above'!E61&" - "&IF('SSP - DoD SPRS & FAR and Above'!I61<>"",'SSP - DoD SPRS & FAR and Above'!I61,'SSP - DoD SPRS & FAR and Above'!J61))} | B48: ISO/CISO | C48: Funded | D48: Export Entra Conditional Access & PIM/PAM approvals; provide VPN/VDI/firewall configs enforcing managed access points and FIPS-validated crypto; wireless WPA-Enterprise configs; GPO/MDM for session lock/termination. | E48: Estimate - 60 days to remediate Policies and SSP available; attach configs/logs/records as noted
A49: {=IF('SSP - DoD SPRS & FAR and Above'!M62<>"Fully Addressed",'SSP - DoD SPRS & FAR and Above'!E62&" - "&IF('SSP - DoD SPRS & FAR and Above'!I62<>"",'SSP - DoD SPRS & FAR and Above'!I62,'SSP - DoD SPRS & FAR and Above'!J62))} | B49: ISO/CISO | C49: Funded | D49: Export Entra Conditional Access & PIM/PAM approvals; provide VPN/VDI/firewall configs enforcing managed access points and FIPS-validated crypto; wireless WPA-Enterprise configs; GPO/MDM for session lock/termination. | E49: Estimate - 60 days to remediate Policies and SSP available; attach configs/logs/records as noted
A50: {=IF('SSP - DoD SPRS & FAR and Above'!M63<>"Fully Addressed",'SSP - DoD SPRS & FAR and Above'!E63&" - "&IF('SSP - DoD SPRS & FAR and Above'!I63<>"",'SSP - DoD SPRS & FAR and Above'!I63,'SSP - DoD SPRS & FAR and Above'!J63))} | B50: ISO/CISO | C50: Funded | D50: Export Entra Conditional Access & PIM/PAM approvals; provide VPN/VDI/firewall configs enforcing managed access points and FIPS-validated crypto; wireless WPA-Enterprise configs; GPO/MDM for session lock/termination. | E50: Estimate - 60 days to remediate Policies and SSP available; attach configs/logs/records as noted
A51: {=IF('SSP - DoD SPRS & FAR and Above'!M64<>"Fully Addressed",'SSP - DoD SPRS & FAR and Above'!E64&" - "&IF('SSP - DoD SPRS & FAR and Above'!I64<>"",'SSP - DoD SPRS & FAR and Above'!I64,'SSP - DoD SPRS & FAR and Above'!J64))} | B51: ISO/CISO | C51: Funded | D51: Export Entra Conditional Access & PIM/PAM approvals; provide VPN/VDI/firewall configs enforcing managed access points and FIPS-validated crypto; wireless WPA-Enterprise configs; GPO/MDM for session lock/termination. | E51: Estimate - 60 days to remediate Policies and SSP available; attach configs/logs/records as noted
A52: {=IF('SSP - DoD SPRS & FAR and Above'!M65<>"Fully Addressed",'SSP - DoD SPRS & FAR and Above'!E65&" - "&IF('SSP - DoD SPRS & FAR and Above'!I65<>"",'SSP - DoD SPRS & FAR and Above'!I65,'SSP - DoD SPRS & FAR and Above'!J65))} | B52: ISO/CISO | C52: Funded | D52: Export Entra Conditional Access & PIM/PAM approvals; provide VPN/VDI/firewall configs enforcing managed access points and FIPS-validated crypto; wireless WPA-Enterprise configs; GPO/MDM for session lock/termination. | E52: Estimate - 60 days to remediate Policies and SSP available; attach configs/logs/records as noted
A53: {=IF('SSP - DoD SPRS & FAR and Above'!M66<>"Fully Addressed",'SSP - DoD SPRS & FAR and Above'!E66&" - "&IF('SSP - DoD SPRS & FAR and Above'!I66<>"",'SSP - DoD SPRS & FAR and Above'!I66,'SSP - DoD SPRS & FAR and Above'!J66))} | B53: ISO/CISO | C53: Funded | D53: Export Entra Conditional Access & PIM/PAM approvals; provide VPN/VDI/firewall configs enforcing managed access points and FIPS-validated crypto; wireless WPA-Enterprise configs; GPO/MDM for session lock/termination. | E53: Estimate - 60 days to remediate Policies and SSP available; attach configs/logs/records as noted
A54: {=IF('SSP - DoD SPRS & FAR and Above'!M67<>"Fully Addressed",'SSP - DoD SPRS & FAR and Above'!E67&" - "&IF('SSP - DoD SPRS & FAR and Above'!I67<>"",'SSP - DoD SPRS & FAR and Above'!I67,'SSP - DoD SPRS & FAR and Above'!J67))} | B54: ISO/CISO | C54: Funded | D54: Export Entra Conditional Access & PIM/PAM approvals; provide VPN/VDI/firewall configs enforcing managed access points and FIPS-validated crypto; wireless WPA-Enterprise configs; GPO/MDM for session lock/termination. | E54: Estimate - 60 days to remediate Policies and SSP available; attach configs/logs/records as noted
A55: {=IF('SSP - DoD SPRS & FAR and Above'!M68<>"Fully Addressed",'SSP - DoD SPRS & FAR and Above'!E68&" - "&IF('SSP - DoD SPRS & FAR and Above'!I68<>"",'SSP - DoD SPRS & FAR and Above'!I68,'SSP - DoD SPRS & FAR and Above'!J68))} | B55: ISO/CISO | C55: Funded | D55: Export Entra Conditional Access & PIM/PAM approvals; provide VPN/VDI/firewall configs enforcing managed access points and FIPS-validated crypto; wireless WPA-Enterprise configs; GPO/MDM for session lock/termination. | E55: Estimate - 60 days to remediate Policies and SSP available; attach configs/logs/records as noted
A56: {=IF('SSP - DoD SPRS & FAR and Above'!M69<>"Fully Addressed",'SSP - DoD SPRS & FAR and Above'!E69&" - "&IF('SSP - DoD SPRS & FAR and Above'!I69<>"",'SSP - DoD SPRS & FAR and Above'!I69,'SSP - DoD SPRS & FAR and Above'!J69))} | B56: ISO/CISO | C56: Funded | D56: Export Entra Conditional Access & PIM/PAM approvals; provide VPN/VDI/firewall configs enforcing managed access points and FIPS-validated crypto; wireless WPA-Enterprise configs; GPO/MDM for session lock/termination. | E56: Estimate - 60 days to remediate Policies and SSP available; attach configs/logs/records as noted
A57: {=IF('SSP - DoD SPRS & FAR and Above'!M70<>"Fully Addressed",'SSP - DoD SPRS & FAR and Above'!E70&" - "&IF('SSP - DoD SPRS & FAR and Above'!I70<>"",'SSP - DoD SPRS & FAR and Above'!I70,'SSP - DoD SPRS & FAR and Above'!J70))} | B57: ISO/CISO | C57: Funded | D57: Export Entra Conditional Access & PIM/PAM approvals; provide VPN/VDI/firewall configs enforcing managed access points and FIPS-validated crypto; wireless WPA-Enterprise configs; GPO/MDM for session lock/termination. | E57: Estimate - 60 days to remediate Policies and SSP available; attach configs/logs/records as noted
A58: {=IF('SSP - DoD SPRS & FAR and Above'!M307<>"Fully Addressed",'SSP - DoD SPRS & FAR and Above'!E307&" - "&IF('SSP - DoD SPRS & FAR and Above'!I307<>"",'SSP - DoD SPRS & FAR and Above'!I307,'SSP - DoD SPRS & FAR and Above'!J307))} | B58: ISO/CISO | C58: Funded | D58: Export Entra Conditional Access & PIM/PAM approvals; provide VPN/VDI/firewall configs enforcing managed access points and FIPS-validated crypto; wireless WPA-Enterprise configs; GPO/MDM for session lock/termination. | E58: Estimate - 60 days to remediate Policies and SSP available; attach configs/logs/records as noted
A59: {=IF('SSP - DoD SPRS & FAR and Above'!M308<>"Fully Addressed",'SSP - DoD SPRS & FAR and Above'!E308&" - "&IF('SSP - DoD SPRS & FAR and Above'!I308<>"",'SSP - DoD SPRS & FAR and Above'!I308,'SSP - DoD SPRS & FAR and Above'!J308))} | B59: ISO/CISO | C59: Funded | D59: Export Entra Conditional Access & PIM/PAM approvals; provide VPN/VDI/firewall configs enforcing managed access points and FIPS-validated crypto; wireless WPA-Enterprise configs; GPO/MDM for session lock/termination. | E59: Estimate - 60 days to remediate Policies and SSP available; attach configs/logs/records as noted
A60: {=IF('SSP - DoD SPRS & FAR and Above'!M309<>"Fully Addressed",'SSP - DoD SPRS & FAR and Above'!E309&" - "&IF('SSP - DoD SPRS & FAR and Above'!I309<>"",'SSP - DoD SPRS & FAR and Above'!I309,'SSP - DoD SPRS & FAR and Above'!J309))} | B60: ISO/CISO | C60: Funded | D60: Export Entra Conditional Access & PIM/PAM approvals; provide VPN/VDI/firewall configs enforcing managed access points and FIPS-validated crypto; wireless WPA-Enterprise configs; GPO/MDM for session lock/termination. | E60: Estimate - 60 days to remediate Policies and SSP available; attach configs/logs/records as noted
A61: {=IF('SSP - DoD SPRS & FAR and Above'!M310<>"Fully Addressed",'SSP - DoD SPRS & FAR and Above'!E310&" - "&IF('SSP - DoD SPRS & FAR and Above'!I310<>"",'SSP - DoD SPRS & FAR and Above'!I310,'SSP - DoD SPRS & FAR and Above'!J310))} | B61: ISO/CISO | C61: Funded | D61: Export Entra Conditional Access & PIM/PAM approvals; provide VPN/VDI/firewall configs enforcing managed access points and FIPS-validated crypto; wireless WPA-Enterprise configs; GPO/MDM for session lock/termination. | E61: Estimate - 60 days to remediate Policies and SSP available; attach configs/logs/records as noted
A62: {=IF('SSP - DoD SPRS & FAR and Above'!M71<>"Fully Addressed",'SSP - DoD SPRS & FAR and Above'!E71&" - "&IF('SSP - DoD SPRS & FAR and Above'!I71<>"",'SSP - DoD SPRS & FAR and Above'!I71,'SSP - DoD SPRS & FAR and Above'!J71))} | B62: ISO/CISO | C62: Funded | D62: Export Entra Conditional Access & PIM/PAM approvals; provide VPN/VDI/firewall configs enforcing managed access points and FIPS-validated crypto; wireless WPA-Enterprise configs; GPO/MDM for session lock/termination. | E62: Estimate - 60 days to remediate Policies and SSP available; attach configs/logs/records as noted
A63: {=IF('SSP - DoD SPRS & FAR and Above'!M72<>"Fully Addressed",'SSP - DoD SPRS & FAR and Above'!E72&" - "&IF('SSP - DoD SPRS & FAR and Above'!I72<>"",'SSP - DoD SPRS & FAR and Above'!I72,'SSP - DoD SPRS & FAR and Above'!J72))} | B63: ISO/CISO | C63: Funded | D63: Export Entra Conditional Access & PIM/PAM approvals; provide VPN/VDI/firewall configs enforcing managed access points and FIPS-validated crypto; wireless WPA-Enterprise configs; GPO/MDM for session lock/termination. | E63: Estimate - 60 days to remediate Policies and SSP available; attach configs/logs/records as noted
A64: {=IF('SSP - DoD SPRS & FAR and Above'!M73<>"Fully Addressed",'SSP - DoD SPRS & FAR and Above'!E73&" - "&IF('SSP - DoD SPRS & FAR and Above'!I73<>"",'SSP - DoD SPRS & FAR and Above'!I73,'SSP - DoD SPRS & FAR and Above'!J73))} | B64: ISO/CISO | C64: Funded | D64: Export Entra Conditional Access & PIM/PAM approvals; provide VPN/VDI/firewall configs enforcing managed access points and FIPS-validated crypto; wireless WPA-Enterprise configs; GPO/MDM for session lock/termination. | E64: Estimate - 60 days to remediate Policies and SSP available; attach configs/logs/records as noted
A65: {=IF('SSP - DoD SPRS & FAR and Above'!M74<>"Fully Addressed",'SSP - DoD SPRS & FAR and Above'!E74&" - "&IF('SSP - DoD SPRS & FAR and Above'!I74<>"",'SSP - DoD SPRS & FAR and Above'!I74,'SSP - DoD SPRS & FAR and Above'!J74))} | B65: ISO/CISO | C65: Funded | D65: Export Entra Conditional Access & PIM/PAM approvals; provide VPN/VDI/firewall configs enforcing managed access points and FIPS-validated crypto; wireless WPA-Enterprise configs; GPO/MDM for session lock/termination. | E65: Estimate - 60 days to remediate Policies and SSP available; attach configs/logs/records as noted
A66: {=IF('SSP - DoD SPRS & FAR and Above'!M75<>"Fully Addressed",'SSP - DoD SPRS & FAR and Above'!E75&" - "&IF('SSP - DoD SPRS & FAR and Above'!I75<>"",'SSP - DoD SPRS & FAR and Above'!I75,'SSP - DoD SPRS & FAR and Above'!J75))} | B66: ISO/CISO | C66: Funded | D66: Export Entra Conditional Access & PIM/PAM approvals; provide VPN/VDI/firewall configs enforcing managed access points and FIPS-validated crypto; wireless WPA-Enterprise configs; GPO/MDM for session lock/termination. | E66: Estimate - 60 days to remediate Policies and SSP available; attach configs/logs/records as noted
A67: {=IF('SSP - DoD SPRS & FAR and Above'!M76<>"Fully Addressed",'SSP - DoD SPRS & FAR and Above'!E76&" - "&IF('SSP - DoD SPRS & FAR and Above'!I76<>"",'SSP - DoD SPRS & FAR and Above'!I76,'SSP - DoD SPRS & FAR and Above'!J76))} | B67: ISO/CISO | C67: Funded | D67: Export Entra Conditional Access & PIM/PAM approvals; provide VPN/VDI/firewall configs enforcing managed access points and FIPS-validated crypto; wireless WPA-Enterprise configs; GPO/MDM for session lock/termination. | E67: Estimate - 60 days to remediate Policies and SSP available; attach configs/logs/records as noted
A68: {=IF('SSP - DoD SPRS & FAR and Above'!M359<>"Fully Addressed",'SSP - DoD SPRS & FAR and Above'!E359&" - "&IF('SSP - DoD SPRS & FAR and Above'!I359<>"",'SSP - DoD SPRS & FAR and Above'!I359,'SSP - DoD SPRS & FAR and Above'!J359))} | B68: ISO/CISO | C68: Funded | D68: Export Entra Conditional Access & PIM/PAM approvals; provide VPN/VDI/firewall configs enforcing managed access points and FIPS-validated crypto; wireless WPA-Enterprise configs; GPO/MDM for session lock/termination. | E68: Estimate - 60 days to remediate Policies and SSP available; attach configs/logs/records as noted
A69: {=IF('SSP - DoD SPRS & FAR and Above'!M360<>"Fully Addressed",'SSP - DoD SPRS & FAR and Above'!E360&" - "&IF('SSP - DoD SPRS & FAR and Above'!I360<>"",'SSP - DoD SPRS & FAR and Above'!I360,'SSP - DoD SPRS & FAR and Above'!J360))} | B69: ISO/CISO | C69: Funded | D69: Export Entra Conditional Access & PIM/PAM approvals; provide VPN/VDI/firewall configs enforcing managed access points and FIPS-validated crypto; wireless WPA-Enterprise configs; GPO/MDM for session lock/termination. | E69: Estimate - 60 days to remediate Policies and SSP available; attach configs/logs/records as noted
A70: {=IF('SSP - DoD SPRS & FAR and Above'!M361<>"Fully Addressed",'SSP - DoD SPRS & FAR and Above'!E361&" - "&IF('SSP - DoD SPRS & FAR and Above'!I361<>"",'SSP - DoD SPRS & FAR and Above'!I361,'SSP - DoD SPRS & FAR and Above'!J361))} | B70: ISO/CISO | C70: Funded | D70: Export Entra Conditional Access & PIM/PAM approvals; provide VPN/VDI/firewall configs enforcing managed access points and FIPS-validated crypto; wireless WPA-Enterprise configs; GPO/MDM for session lock/termination. | E70: Estimate - 60 days to remediate Policies and SSP available; attach configs/logs/records as noted
A71: {=IF('SSP - DoD SPRS & FAR and Above'!M362<>"Fully Addressed",'SSP - DoD SPRS & FAR and Above'!E362&" - "&IF('SSP - DoD SPRS & FAR and Above'!I362<>"",'SSP - DoD SPRS & FAR and Above'!I362,'SSP - DoD SPRS & FAR and Above'!J362))} | B71: ISO/CISO | C71: Funded | D71: Export Entra Conditional Access & PIM/PAM approvals; provide VPN/VDI/firewall configs enforcing managed access points and FIPS-validated crypto; wireless WPA-Enterprise configs; GPO/MDM for session lock/termination. | E71: Estimate - 60 days to remediate Policies and SSP available; attach configs/logs/records as noted
A72: {=IF('SSP - DoD SPRS & FAR and Above'!M363<>"Fully Addressed",'SSP - DoD SPRS & FAR and Above'!E363&" - "&IF('SSP - DoD SPRS & FAR and Above'!I363<>"",'SSP - DoD SPRS & FAR and Above'!I363,'SSP - DoD SPRS & FAR and Above'!J363))} | B72: ISO/CISO | C72: Funded | D72: Export Entra Conditional Access & PIM/PAM approvals; provide VPN/VDI/firewall configs enforcing managed access points and FIPS-validated crypto; wireless WPA-Enterprise configs; GPO/MDM for session lock/termination. | E72: Estimate - 60 days to remediate Policies and SSP available; attach configs/logs/records as noted
A73: {=IF('SSP - DoD SPRS & FAR and Above'!M364<>"Fully Addressed",'SSP - DoD SPRS & FAR and Above'!E364&" - "&IF('SSP - DoD SPRS & FAR and Above'!I364<>"",'SSP - DoD SPRS & FAR and Above'!I364,'SSP - DoD SPRS & FAR and Above'!J364))} | B73: ISO/CISO | C73: Funded | D73: Export Entra Conditional Access & PIM/PAM approvals; provide VPN/VDI/firewall configs enforcing managed access points and FIPS-validated crypto; wireless WPA-Enterprise configs; GPO/MDM for session lock/termination. | E73: Estimate - 60 days to remediate Policies and SSP available; attach configs/logs/records as noted
A74: {=IF('SSP - DoD SPRS & FAR and Above'!M221<>"Fully Addressed",'SSP - DoD SPRS & FAR and Above'!E221&" - "&IF('SSP - DoD SPRS & FAR and Above'!I221<>"",'SSP - DoD SPRS & FAR and Above'!I221,'SSP - DoD SPRS & FAR and Above'!J221))} | B74: ISO/CISO | C74: Funded | D74: Export Entra Conditional Access & PIM/PAM approvals; provide VPN/VDI/firewall configs enforcing managed access points and FIPS-validated crypto; wireless WPA-Enterprise configs; GPO/MDM for session lock/termination. | E74: Estimate - 60 days to remediate Policies and SSP available; attach configs/logs/records as noted
A75: {=IF('SSP - DoD SPRS & FAR and Above'!M222<>"Fully Addressed",'SSP - DoD SPRS & FAR and Above'!E222&" - "&IF('SSP - DoD SPRS & FAR and Above'!I222<>"",'SSP - DoD SPRS & FAR and Above'!I222,'SSP - DoD SPRS & FAR and Above'!J222))} | B75: ISO/CISO | C75: Funded | D75: Export Entra Conditional Access & PIM/PAM approvals; provide VPN/VDI/firewall configs enforcing managed access points and FIPS-validated crypto; wireless WPA-Enterprise configs; GPO/MDM for session lock/termination. | E75: Estimate - 60 days to remediate Policies and SSP available; attach configs/logs/records as noted
A76: {=IF('SSP - DoD SPRS & FAR and Above'!M223<>"Fully Addressed",'SSP - DoD SPRS & FAR and Above'!E223&" - "&IF('SSP - DoD SPRS & FAR and Above'!I223<>"",'SSP - DoD SPRS & FAR and Above'!I223,'SSP - DoD SPRS & FAR and Above'!J223))} | B76: ISO/CISO | C76: Funded | D76: Export Entra Conditional Access & PIM/PAM approvals; provide VPN/VDI/firewall configs enforcing managed access points and FIPS-validated crypto; wireless WPA-Enterprise configs; GPO/MDM for session lock/termination. | E76: Estimate - 60 days to remediate Policies and SSP available; attach configs/logs/records as noted
A77: {=IF('SSP - DoD SPRS & FAR and Above'!M224<>"Fully Addressed",'SSP - DoD SPRS & FAR and Above'!E224&" - "&IF('SSP - DoD SPRS & FAR and Above'!I224<>"",'SSP - DoD SPRS & FAR and Above'!I224,'SSP - DoD SPRS & FAR and Above'!J224))} | B77: ISO/CISO | C77: Funded | D77: Export Entra Conditional Access & PIM/PAM approvals; provide VPN/VDI/firewall configs enforcing managed access points and FIPS-validated crypto; wireless WPA-Enterprise configs; GPO/MDM for session lock/termination. | E77: Estimate - 60 days to remediate Policies and SSP available; attach configs/logs/records as noted
A78: {=IF('SSP - DoD SPRS & FAR and Above'!M225<>"Fully Addressed",'SSP - DoD SPRS & FAR and Above'!E225&" - "&IF('SSP - DoD SPRS & FAR and Above'!I225<>"",'SSP - DoD SPRS & FAR and Above'!I225,'SSP - DoD SPRS & FAR and Above'!J225))} | B78: ISO/CISO | C78: Funded | D78: Export Entra Conditional Access & PIM/PAM approvals; provide VPN/VDI/firewall configs enforcing managed access points and FIPS-validated crypto; wireless WPA-Enterprise configs; GPO/MDM for session lock/termination. | E78: Estimate - 60 days to remediate Policies and SSP available; attach configs/logs/records as noted
A79: {=IF('SSP - DoD SPRS & FAR and Above'!M226<>"Fully Addressed",'SSP - DoD SPRS & FAR and Above'!E226&" - "&IF('SSP - DoD SPRS & FAR and Above'!I226<>"",'SSP - DoD SPRS & FAR and Above'!I226,'SSP - DoD SPRS & FAR and Above'!J226))} | B79: ISO/CISO | C79: Funded | D79: Export Entra Conditional Access & PIM/PAM approvals; provide VPN/VDI/firewall configs enforcing managed access points and FIPS-validated crypto; wireless WPA-Enterprise configs; GPO/MDM for session lock/termination. | E79: Estimate - 60 days to remediate Policies and SSP available; attach configs/logs/records as noted
A80: {=IF('SSP - DoD SPRS & FAR and Above'!M227<>"Fully Addressed",'SSP - DoD SPRS & FAR and Above'!E227&" - "&IF('SSP - DoD SPRS & FAR and Above'!I227<>"",'SSP - DoD SPRS & FAR and Above'!I227,'SSP - DoD SPRS & FAR and Above'!J227))} | B80: ISO/CISO | C80: Funded | D80: Export Entra Conditional Access & PIM/PAM approvals; provide VPN/VDI/firewall configs enforcing managed access points and FIPS-validated crypto; wireless WPA-Enterprise configs; GPO/MDM for session lock/termination. | E80: Estimate - 60 days to remediate Policies and SSP available; attach configs/logs/records as noted
A81: {=IF('SSP - DoD SPRS & FAR and Above'!M228<>"Fully Addressed",'SSP - DoD SPRS & FAR and Above'!E228&" - "&IF('SSP - DoD SPRS & FAR and Above'!I228<>"",'SSP - DoD SPRS & FAR and Above'!I228,'SSP - DoD SPRS & FAR and Above'!J228))} | B81: ISO/CISO | C81: Funded | D81: Export Entra Conditional Access & PIM/PAM approvals; provide VPN/VDI/firewall configs enforcing managed access points and FIPS-validated crypto; wireless WPA-Enterprise configs; GPO/MDM for session lock/termination. | E81: Estimate - 60 days to remediate Policies and SSP available; attach configs/logs/records as noted
A82: {=IF('SSP - DoD SPRS & FAR and Above'!M229<>"Fully Addressed",'SSP - DoD SPRS & FAR and Above'!E229&" - "&IF('SSP - DoD SPRS & FAR and Above'!I229<>"",'SSP - DoD SPRS & FAR and Above'!I229,'SSP - DoD SPRS & FAR and Above'!J229))} | B82: ISO/CISO | C82: Funded | D82: Export Entra Conditional Access & PIM/PAM approvals; provide VPN/VDI/firewall configs enforcing managed access points and FIPS-validated crypto; wireless WPA-Enterprise configs; GPO/MDM for session lock/termination. | E82: Estimate - 60 days to remediate Policies and SSP available; attach configs/logs/records as noted
A83: {=IF('SSP - DoD SPRS & FAR and Above'!M113<>"Fully Addressed",'SSP - DoD SPRS & FAR and Above'!E113&" - "&IF('SSP - DoD SPRS & FAR and Above'!I113<>"",'SSP - DoD SPRS & FAR and Above'!I113,'SSP - DoD SPRS & FAR and Above'!J113))} | B83: ISO/CISO | C83: Funded | D83: Export Entra Conditional Access & PIM/PAM approvals; provide VPN/VDI/firewall configs enforcing managed access points and FIPS-validated crypto; wireless WPA-Enterprise configs; GPO/MDM for session lock/termination. | E83: Estimate - 60 days to remediate Policies and SSP available; attach configs/logs/records as noted
A84: {=IF('SSP - DoD SPRS & FAR and Above'!M114<>"Fully Addressed",'SSP - DoD SPRS & FAR and Above'!E114&" - "&IF('SSP - DoD SPRS & FAR and Above'!I114<>"",'SSP - DoD SPRS & FAR and Above'!I114,'SSP - DoD SPRS & FAR and Above'!J114))} | B84: ISO/CISO | C84: Funded | D84: Export Entra Conditional Access & PIM/PAM approvals; provide VPN/VDI/firewall configs enforcing managed access points and FIPS-validated crypto; wireless WPA-Enterprise configs; GPO/MDM for session lock/termination. | E84: Estimate - 60 days to remediate Policies and SSP available; attach configs/logs/records as noted
A85: {=IF('SSP - DoD SPRS & FAR and Above'!M115<>"Fully Addressed",'SSP - DoD SPRS & FAR and Above'!E115&" - "&IF('SSP - DoD SPRS & FAR and Above'!I115<>"",'SSP - DoD SPRS & FAR and Above'!I115,'SSP - DoD SPRS & FAR and Above'!J115))} | B85: ISO/CISO | C85: Funded | D85: Export Entra Conditional Access & PIM/PAM approvals; provide VPN/VDI/firewall configs enforcing managed access points and FIPS-validated crypto; wireless WPA-Enterprise configs; GPO/MDM for session lock/termination. | E85: Estimate - 60 days to remediate Policies and SSP available; attach configs/logs/records as noted
A86: {=IF('SSP - DoD SPRS & FAR and Above'!M327<>"Fully Addressed",'SSP - DoD SPRS & FAR and Above'!E327&" - "&IF('SSP - DoD SPRS & FAR and Above'!I327<>"",'SSP - DoD SPRS & FAR and Above'!I327,'SSP - DoD SPRS & FAR and Above'!J327))} | B86: ISO/CISO | C86: Funded | D86: Export Entra Conditional Access & PIM/PAM approvals; provide VPN/VDI/firewall configs enforcing managed access points and FIPS-validated crypto; wireless WPA-Enterprise configs; GPO/MDM for session lock/termination. | E86: Estimate - 60 days to remediate Policies and SSP available; attach configs/logs/records as noted
A87: {=IF('SSP - DoD SPRS & FAR and Above'!M328<>"Fully Addressed",'SSP - DoD SPRS & FAR and Above'!E328&" - "&IF('SSP - DoD SPRS & FAR and Above'!I328<>"",'SSP - DoD SPRS & FAR and Above'!I328,'SSP - DoD SPRS & FAR and Above'!J328))} | B87: ISO/CISO | C87: Funded | D87: Export Entra Conditional Access & PIM/PAM approvals; provide VPN/VDI/firewall configs enforcing managed access points and FIPS-validated crypto; wireless WPA-Enterprise configs; GPO/MDM for session lock/termination. | E87: Estimate - 60 days to remediate Policies and SSP available; attach configs/logs/records as noted
A88: {=IF('SSP - DoD SPRS & FAR and Above'!M329<>"Fully Addressed",'SSP - DoD SPRS & FAR and Above'!E329&" - "&IF('SSP - DoD SPRS & FAR and Above'!I329<>"",'SSP - DoD SPRS & FAR and Above'!I329,'SSP - DoD SPRS & FAR and Above'!J329))} | B88: ISO/CISO | C88: Funded | D88: Export Entra Conditional Access & PIM/PAM approvals; provide VPN/VDI/firewall configs enforcing managed access points and FIPS-validated crypto; wireless WPA-Enterprise configs; GPO/MDM for session lock/termination. | E88: Estimate - 60 days to remediate Policies and SSP available; attach configs/logs/records as noted
A89: {=IF('SSP - DoD SPRS & FAR and Above'!M330<>"Fully Addressed",'SSP - DoD SPRS & FAR and Above'!E330&" - "&IF('SSP - DoD SPRS & FAR and Above'!I330<>"",'SSP - DoD SPRS & FAR and Above'!I330,'SSP - DoD SPRS & FAR and Above'!J330))} | B89: ISO/CISO | C89: Funded | D89: Export Entra Conditional Access & PIM/PAM approvals; provide VPN/VDI/firewall configs enforcing managed access points and FIPS-validated crypto; wireless WPA-Enterprise configs; GPO/MDM for session lock/termination. | E89: Estimate - 60 days to remediate Policies and SSP available; attach configs/logs/records as noted
A90: {=IF('SSP - DoD SPRS & FAR and Above'!M331<>"Fully Addressed",'SSP - DoD SPRS & FAR and Above'!E331&" - "&IF('SSP - DoD SPRS & FAR and Above'!I331<>"",'SSP - DoD SPRS & FAR and Above'!I331,'SSP - DoD SPRS & FAR and Above'!J331))} | B90: ISO/CISO | C90: Funded | D90: Export Entra Conditional Access & PIM/PAM approvals; provide VPN/VDI/firewall configs enforcing managed access points and FIPS-validated crypto; wireless WPA-Enterprise configs; GPO/MDM for session lock/termination. | E90: Estimate - 60 days to remediate Policies and SSP available; attach configs/logs/records as noted
A91: {=IF('SSP - DoD SPRS & FAR and Above'!M97<>"Fully Addressed",'SSP - DoD SPRS & FAR and Above'!E97&" - "&IF('SSP - DoD SPRS & FAR and Above'!I97<>"",'SSP - DoD SPRS & FAR and Above'!I97,'SSP - DoD SPRS & FAR and Above'!J97))} | B91: ISO/CISO | C91: Funded | D91: Export Entra Conditional Access & PIM/PAM approvals; provide VPN/VDI/firewall configs enforcing managed access points and FIPS-validated crypto; wireless WPA-Enterprise configs; GPO/MDM for session lock/termination. | E91: Estimate - 60 days to remediate Policies and SSP available; attach configs/logs/records as noted
A92: {=IF('SSP - DoD SPRS & FAR and Above'!M98<>"Fully Addressed",'SSP - DoD SPRS & FAR and Above'!E98&" - "&IF('SSP - DoD SPRS & FAR and Above'!I98<>"",'SSP - DoD SPRS & FAR and Above'!I98,'SSP - DoD SPRS & FAR and Above'!J98))} | B92: ISO/CISO | C92: Funded | D92: Export Entra Conditional Access & PIM/PAM approvals; provide VPN/VDI/firewall configs enforcing managed access points and FIPS-validated crypto; wireless WPA-Enterprise configs; GPO/MDM for session lock/termination. | E92: Estimate - 60 days to remediate Policies and SSP available; attach configs/logs/records as noted
A93: {=IF('SSP - DoD SPRS & FAR and Above'!M99<>"Fully Addressed",'SSP - DoD SPRS & FAR and Above'!E99&" - "&IF('SSP - DoD SPRS & FAR and Above'!I99<>"",'SSP - DoD SPRS & FAR and Above'!I99,'SSP - DoD SPRS & FAR and Above'!J99))} | B93: ISO/CISO | C93: Funded | D93: Export Entra Conditional Access & PIM/PAM approvals; provide VPN/VDI/firewall configs enforcing managed access points and FIPS-validated crypto; wireless WPA-Enterprise configs; GPO/MDM for session lock/termination. | E93: Estimate - 60 days to remediate Policies and SSP available; attach configs/logs/records as noted
A94: {=IF('SSP - DoD SPRS & FAR and Above'!M354<>"Fully Addressed",'SSP - DoD SPRS & FAR and Above'!E354&" - "&IF('SSP - DoD SPRS & FAR and Above'!I354<>"",'SSP - DoD SPRS & FAR and Above'!I354,'SSP - DoD SPRS & FAR and Above'!J354))} | B94: ISO/CISO | C94: Funded | D94: Export Entra Conditional Access & PIM/PAM approvals; provide VPN/VDI/firewall configs enforcing managed access points and FIPS-validated crypto; wireless WPA-Enterprise configs; GPO/MDM for session lock/termination. | E94: Estimate - 60 days to remediate Policies and SSP available; attach configs/logs/records as noted
A95: {=IF('SSP - DoD SPRS & FAR and Above'!M355<>"Fully Addressed",'SSP - DoD SPRS & FAR and Above'!E355&" - "&IF('SSP - DoD SPRS & FAR and Above'!I355<>"",'SSP - DoD SPRS & FAR and Above'!I355,'SSP - DoD SPRS & FAR and Above'!J355))} | B95: ISO/CISO | C95: Funded | D95: Export Entra Conditional Access & PIM/PAM approvals; provide VPN/VDI/firewall configs enforcing managed access points and FIPS-validated crypto; wireless WPA-Enterprise configs; GPO/MDM for session lock/termination. | E95: Estimate - 60 days to remediate Policies and SSP available; attach configs/logs/records as noted
A96: {=IF('SSP - DoD SPRS & FAR and Above'!M356<>"Fully Addressed",'SSP - DoD SPRS & FAR and Above'!E356&" - "&IF('SSP - DoD SPRS & FAR and Above'!I356<>"",'SSP - DoD SPRS & FAR and Above'!I356,'SSP - DoD SPRS & FAR and Above'!J356))} | B96: ISO/CISO | C96: Funded | D96: Export Entra Conditional Access & PIM/PAM approvals; provide VPN/VDI/firewall configs enforcing managed access points and FIPS-validated crypto; wireless WPA-Enterprise configs; GPO/MDM for session lock/termination. | E96: Estimate - 60 days to remediate Policies and SSP available; attach configs/logs/records as noted
A97: {=IF('SSP - DoD SPRS & FAR and Above'!M15<>"Fully Addressed",'SSP - DoD SPRS & FAR and Above'!E15&" - "&IF('SSP - DoD SPRS & FAR and Above'!I15<>"",'SSP - DoD SPRS & FAR and Above'!I15,'SSP - DoD SPRS & FAR and Above'!J15))} | B97: ISO/CISO | C97: Funded | D97: Provide badge/door access logs, visitor sign-in/escort records, CCTV spot-checks, access device inventory, and remote/alternate site safeguards. | E97: Estimate - 60 days to remediate Policies and SSP available; attach configs/logs/records as noted
A98: {=IF('SSP - DoD SPRS & FAR and Above'!M16<>"Fully Addressed",'SSP - DoD SPRS & FAR and Above'!E16&" - "&IF('SSP - DoD SPRS & FAR and Above'!I16<>"",'SSP - DoD SPRS & FAR and Above'!I16,'SSP - DoD SPRS & FAR and Above'!J16))} | B98: ISO/CISO | C98: Funded | D98: Provide badge/door access logs, visitor sign-in/escort records, CCTV spot-checks, access device inventory, and remote/alternate site safeguards. | E98: Estimate - 60 days to remediate Policies and SSP available; attach configs/logs/records as noted
A99: {=IF('SSP - DoD SPRS & FAR and Above'!M17<>"Fully Addressed",'SSP - DoD SPRS & FAR and Above'!E17&" - "&IF('SSP - DoD SPRS & FAR and Above'!I17<>"",'SSP - DoD SPRS & FAR and Above'!I17,'SSP - DoD SPRS & FAR and Above'!J17))} | B99: ISO/CISO | C99: Funded | D99: Provide badge/door access logs, visitor sign-in/escort records, CCTV spot-checks, access device inventory, and remote/alternate site safeguards. | E99: Estimate - 60 days to remediate Policies and SSP available; attach configs/logs/records as noted
A100: {=IF('SSP - DoD SPRS & FAR and Above'!M18<>"Fully Addressed",'SSP - DoD SPRS & FAR and Above'!E18&" - "&IF('SSP - DoD SPRS & FAR and Above'!I18<>"",'SSP - DoD SPRS & FAR and Above'!I18,'SSP - DoD SPRS & FAR and Above'!J18))} | B100: ISO/CISO | C100: Funded | D100: Provide badge/door access logs, visitor sign-in/escort records, CCTV spot-checks, access device inventory, and remote/alternate site safeguards. | E100: Estimate - 60 days to remediate Policies and SSP available; attach configs/logs/records as noted
...

Sheet Privileged Accounts
A1: Relevant Requirement(s)/Objective(s): | B1: 3.1.5a, 3.1.15a, 3.1.15b, 3.5.3a | C1: Last Reviewed by: | E1: Last Reviewed on:
A2: Account Name | B2: Account Purpose | C2: List of Cloud Services and External Systems Account is Authorized to Access | D2: List of Systems/Subsystems/ Hardware Account is Authorized to Access | E2: List of Software Account is Authorized to Access | F2: Is Account Authorized to Access System Remotely? (Yes/No) | G2: Is Account Authorized to Access System Security Information Remotely? (Yes/No) | H2: List of Privileged Commands Account is Authorized to Remotely Execute | I2: List of Security Information Types Account is Authorized to Remotely Access | J2: List of User(s)/Role(s) of Which Account is Authorized to Act on Behalf | K2: Date Password Last Changed

Sheet Physical Location(s) Info.
A1: Relevant Requirement(s)/ Objective(s): | B1: 3.10.1a, 3.10.5a | C1: Last Reviewed By: | E1: Last Reviewed On:
C2: Location 1 | D2: Location 2 | E2: Location 3 | F2: Location 4 | G2: Location 5
A3: Location Name/Description | C3: California (Hera A&D | West) | D3: California (MSM A&D) | E3: Colorado (Canopy Technologies) | F3: Florida (Hera A&D | East)
A4: Address 1 | C4: 1055 E Francis St | D4: 12660 Magnolia Ave | E4: 8101 Midway Dr | F4: 350 Imperial Blvd
A5: Address 2 | E5: Ste 100
A6: City | C6: Ontario | D6: Riverside | E6: Littleton | F6: Cape Canaveral
A7: State | C7: CA | D7: CA | E7: CO | F7: FL
A8: Country | C8: USA | D8: USA | E8: USA | F8: USA
A9: Postal Code | C9: 91761 | D9: 92503 | E9: 80125 | F9: 32920
A10: Room(s)/Floor(s)/Cage(s)
A11: Accountable Role/Individual
A12: Entry 1 | B12: Location
B13: Physical Access Device
B14: Other Description
A15: Entry 2 | B15: Location
B16: Physical Access Device
B17: Other Description
A18: Entry 3 | B18: Location
B19: Physical Access Device
B20: Other Description
A21: Entry 4 | B21: Location
B22: Physical Access Device
B23: Other Description

Sheet Users Auth. to Access System
A1: Relevant Requirement(s)/ Objective(s): | B1: 3.1.1a, 3.5.1a | C1: Last Reviewed By: | E1: Last Reviewed On:
A2: User ID | B2: Access Authorization Start Date | C2: Access Authorization End Date | D2: Account Authorized By (Name) | E2: User First Name | F2: User Last Name | G2: Organization Name | H2: E-mail Address | I2: User Role(s) | J2: Date Account Created | K2: Date Account Disabled

Sheet User Roles
A1: Relevant Requirement(s)/ Objective(s): | B1: 3.1.22b | C1: Last Reviewed By: | E1: Last Reviewed On:
A2: Role Name/Description | B2: Authorized to Access System Remotely (Yes/No) | C2: Authorized to Post or Process Information on Publicly Accessible Systems (Yes/No) | D2: Authorized to Read FCI (Yes/No) | E2: Authorized to Create FCI (Yes/No) | F2: Authorized to Delete FCI (Yes/No) | G2: Authorized to Modify/Update FCI (Yes/No) | H2: Type(s) of CUI Users in this Role are Authorized to Read | I2: Type(s) of CUI Users in this Role are Authorized to Create | J2: Type(s) of CUI Users in this Role are Authorized to Delete | K2: Type(s) of CUI Users in this Role are Authorized to Modify/Update

Sheet Authorized Visitor List
A1: Visitor First Name | B1: Visitor Last Name | C1: Visitor Organization | D1: Role | E1: Mobile Phone | F1: Purpose of Visit(s) | G1: Visit Authorized By | H1: Authorization Begins | I1: Authorization Ends | J1: Information Categories Individual is Authorized to View/Access | K1: Area(s) Invididual is Authorized to Visit | L1: Escort Required

Sheet Visitor Access Log
A1: Visitor First Name | B1: Visitor Last Name | C1: Arrival Date | D1: Arrival Time | E1: Previously Authorized? | F1: Authorized By | G1: Escort Name | H1: Departure Date | I1: Departure Time

Sheet Sub-Systems
A1: Organization Name: | G1: Inventory Date | I1: Inventoried By
A2: System Name/ Description | B2: Accessible by the Public? | C2: Potential Business Impact | F2: Physical Machine(s)/ Cloud Service Provider | G2: Virtual Machine(s)/ Capabilities | H2: Datacenter/Office | I2: Subnet/VLAN | J2: Responsible Technical Point(s) of Contact (Role/Person) | K2: Accountable System Owner (Role)
C3: Confidentiality | D3: Integrity | E3: Availability

Sheet Hardware Inventory
A1: Relevant Requirement(s)/ Objective(s): | B1: 3.1.1c, 3.1.16a, 3.1.14a, 3.1.13a, 3.1.18a, 3.1.19a, 3.1.19b, 3.5.1c, 3.10.1a, 3.13.5a, 3.13.12a, 3.14.2a | C1: Last Reviewed By: | E1: Last Reviewed On:
A2: Asset Name/ID | B2: Of Which System(s)/ Subsystem(s) is this a Part (if any)? | C2: Hardware Make/OEM | D2: Mobile Device (Yes/No) | E2: Model | F2: Version | G2: BIOS Version | H2: Operating System | I2: Operating System Version | J2: Includes Wireless Access Point (Yes/No) | K2: Name and Version of Encryption Module Used to Secure Wireless Access (Include link to FIPS 140 Validation) | L2: Provides Managed Remote Access to System (Yes/No) | M2: Publicly Accessible? (Yes/No) | N2: Collaborative Computing Device? (Yes/No) | O2: Authorized to Connect Remotely (Yes/No) | P2: Name and Version of Encryption Module used to Secure Remote Access Sessions (Include link to FIPS 140 Validation) | Q2: Malicious Code Protection Required (Yes/No) | R2: End of Life/End of Support Date | S2: Accountable person/role | T2: Physical Location(s) from which Hardware Operates | U2: Role(s) Permitted Physical Access | V2: Stores, Transmits, or Processes FCI (Yes/No) | W2: CUI Type(s) Stored, Processed, or Transmitted | X2: Is Data Stored on the Device Encrypted by Default? (Yes/No) | Y2: Name and Version Number of Encryption Module used to Secure Data Stored on the Device (Include link to FIPS 140 Validation) | Z2: Asset Category*
AA3: *See CMMC Scoping Guide for Asset Category Descriptions
AA4: OUSD A&S - Cybersecurity Maturity Model Certification (CMMC) (osd.mil)

Sheet Software Inventory
A1: Relevant Requirement(s)/ Objective(s): | B1: 3.1.1b, 3.4.8b, 3.5.1b | C1: Last Reviewed By: | E1: Last Reviewed On:
A2: Category/Purpose | B2: Developer | C2: Software Title/Name | D2: Version | E2: Latest Update | F2: Installed on System/Hardware | G2: Responsible Person or Role | H2: Authorized to Perform Actions on Behalf of a User? (Yes/No) | I2: Stores, Transmits, or Processes FCI | J2: CUI Type(s) Stored, Processed, or Transmitted | K2: Asset Category
M3: See CMMC Scoping Guide for Asset Category Descriptions
M4: OUSD A&S - Cybersecurity Maturity Model Certification (CMMC) (osd.mil)

Sheet Cloud Svc. & Ext. Syst Invent.
A1: Relevant Requirement(s)/ Objective(s): | B1: 3.1.20a, 3.1.20b | C1: Last Reviewed By: | E1: Last Reviewed On:
A2: Category/Purpose | B2: External System/Cloud Service Provider Name | C2: Service Title/Name | D2: Version/Subscription Type | E2: URL | F2: Responsible Person or Role | G2: Service Responsibility Matrix Location | H2: Stores, Transmits, or Processes FCI | I2: CUI Type(s) Stored, Processed, or Transmitted | J2: Asset Category
L4: See CMMC Scoping Guide for Asset Category Descriptions
L5: OUSD A&S - Cybersecurity Maturity Model Certification (CMMC) (osd.mil)

Sheet Info. Sources and Destinations
A1: Relevant Requirement(s)/ Objective(s): | B1: 3.1.3c, 3.13.8a | C1: Last Reviewed By: | E1: Last Reviewed On:
A2: Information Definition | F2: Information Origination Details | I2: Information Sharing | M2: Information Movement | O2: Organization Systems and Devices Involved in the Receipt, Creation, Storage, Processing, and/or Sharing of the Information (including network and mobile devices, workstations, servers, etc.) | S2: Data Storage Details | W2: People and Groups (e.g. Business Units, Organizational Roles, etc.) with Express or Inherent Access | Y2: Additional Details for Personally Identifiable Information, Personal Health Information, Financial Information
A3: Information Description | B3: Relevant Contract Number(s) | C3: Details Specific to Cybersecurity Maturity Model Certification (CMMC) | E3: Export Controls | F3: Incoming Information | H3: Internally Created Information | I3: Information Transmission Type | J3: Transmission Protocol (Name and Version) | K3: Government Agencies/Offices with which Info. was/will be Shared | L3: Subcontractor(s) or Vendor(s) with which Info. was/will be Shared | M3: Encryption Module (Name and Version) Used by Source to Secure the Transmission (Include Link to FIPS 140 Validation) | N3: Encryption Module (Name and Version) Used by Destination to Secure the Transmission (Include Link to FIPS 140 Validation) | O3: Involved in Origination/Receipt | P3: Involved in Storage (including backup/long term storage equipment, file cabinets, off-site storage, etc.) | Q3: Involved in Processing the Information | R3: Involved in Sharing/Transmitting | S3: Are Copies Made of the Information, such as for use in Production or Manufacturing Equipment? If so, are all Restrictive Markings Preserved? | T3: Are Copies of the Information Kept by the Organization after the Contract ends? If so, are all Restrictive Markings Preserved? | U3: If the Information is stored on, or transmitted or processed via, a cloud-based service provider, is the information encrypted such that the service provider cannot view/edit the information? | V3: Are all Electronic Copies of the Information Encrypted Using FIPS 140-2 Validated Module? | W3: Express Access (i.e., access expressly granted via access controls) | X3: Inherent Access (i.e., groups with access granted due to information being accessible to everyone, or users/groups with authority to modify access controls) | Y3: Data Source (from where does the data originate?) | Z3: Accountable Individual/Role at Source | AB3: Data Subject Type (e.g., consumer, customer, business prospect, employee, etc.) | AC3: Data Subject Location(s) (Country and State) | AD3: Personal Data Categories (e.g., race, ethnic origin, political opinions, religious beliefs, union membership, genetic/biometric data, health data, sex life, sexual orientation) | AE3: Data Element(s) Collected (e.g., height, weight, eye color, fingerprint, race, prescribed medicines, medical history, etc.) | AF3: Data Controller | AG3: Data Controller Representative | AH3: Data Protection Officer | AI3: Purpose of Processing and/or Transfer (i.e., why are you collecting the data or giving it to someone else) | AJ3: Time Limits for Erasure of the Information (i.e., how long after you receive the data do you delete it?)
C4: Information Type | D4: Designating Agency (if CUI) | E4: Is the Information Subject to Export Control (e.g., ITAR/EAR) Regulations? | F4: Government Agency/Office from which Information was Received | G4: Prime Contractor/Customer from which Information was Received | H4: Organizational/ Business Unit Creating Information | AA4: Accountable Individual/Role at Destination

Sheet Media Library or Catalog
A1: Relevant Requirement(s)/Objective(s): | B1: 3.8.1, 3.8.2, 3.8.3, 3.8.4, 3.8.5, 3.8.6, 3.8.7, 3.8.8, 3.8.9 | C1: Last Reviewed By: | E1: Last Reviewed On:
A2: Unique Media ID | B2: Media Creator | C2: Employee Accountable for Media | D2: Date Created | E2: Media Type (e.g., paper, magnetic tape, CD-ROM, DVD, USB Drive) | F2: Media Contents | G2: Relevant Contract(s) | H2: Media Marking(s) | I2: Is the Media Backup Media? | J2: Media Storage Location | K2: Does the Media Support Hardware Encryption? If so, is it Enabled? | L2: User(s)/Role(s) Authorized to View/Access Media | M2: Media Sanitized/ Destroyed By | N2: Media Santitization/Destruction Date | O2: Media Sanitization/Destruction Method | P2: Media Sanitization/Destruction Evidence
A3: AAA0
A4: AAA1
A5: AAA2
A6: AAA3
A7: AAA4
A8: AAA5
A9: AAA6
A10: AAA7
A11: AAA8
A12: AAA9
A13: AAB0
A14: AAB1
... A43: [Continue list as necessary - do NOT reuse Media IDs]

Sheet Media Access Log
A1: Relevant Requirement(s)/ Objective(s): | B1: 3.8.1, 3.8.2, 3.8.3, 3.8.4, 3.8.5, 3.8.6, 3.8.7, 3.8.8, 3.8.9 | C1: Last Reviewed By: | E1: Last Reviewed On:
A2: Media ID (from Media Library) | B2: Checked Out By | C2: Check Out Date | D2: Check-out Purpose | E2: Expected Return Date | F2: Is the Contents of the Media Encrypted? (if no, list alternate security control(s) to protect media during transport) | G2: Will media leave storage area? (If so, to where?) | H2: Copy Media Markings | I2: Date Returned | J2: Return Witnessed By

Sheet SRM Template
A1: Tool/Service and Provider: | D1: Last Reviewed By: | F1: Last Review Date:
A2: NIST SP 800-171 Requirement ID | B2: CMMC ID | C2: Requirement | D2: Responsibility Inheritance from Provider | E2: Provider Responsibilities | F2: OSC Responsibilities | G2: MSP/MSSP Responsibilities
A3: 3.1.2* | B3: AC.L1-3.1.2 | C3: Limit system access to the types of transactions and functions that authorized users are permitted to execute.
A4: 3.1.3 | B4: AC.L2-3.1.3 | C4: Control the flow of CUI in accordance with approved authorizations.
A5: 3.1.4 | B5: AC.L2-3.1.4 | C5: Separate the duties of individuals to reduce the risk of malevolent activity without collusion.
A6: 3.1.5 | B6: AC.L2-3.1.5 | C6: Employ the principle of least privilege, including for specific security functions and privileged accounts.
A7: 3.1.6 | B7: AC.L2-3.1.6 | C7: Use non-privileged accounts or roles when accessing non-security functions.
A8: 3.1.7 | B8: AC.L2-3.1.7 | C8: Prevent non-privileged users from executing privileged functions and capture the execution of such functions in audit logs.
A9: 3.1.8 | B9: AC.L2-3.1.8 | C9: Limit unsuccessful logon attempts.
A10: 3.1.9 | B10: AC.L2-3.1.9 | C10: Provide privacy and security notices consistent with applicable CUI rules.
A11: 3.1.10 | B11: AC.L2-3.1.10 | C11: Use session lock with pattern-hiding displays to prevent access and viewing of data after a period of inactivity.
A12: 3.1.11 | B12: AC.L2-3.1.11 | C12: Terminate (automatically) a user session after a defined condition.
A13: 3.1.12 | B13: AC.L2-3.1.12 | C13: Monitor and control remote access sessions.
A14: 3.1.13 | B14: AC.L2-3.1.13 | C14: Employ cryptographic mechanisms to protect the confidentiality of remote access sessions.
... A97: 3.13.9 | B97: SC.L2-3.13.9 | C97: Terminate network connections associated with communications sessions at the end of the sessions or after
C98: a defined period of inactivity.
A99: 3.13.10 | B99: SC.L2-3.13.10 | C99: Establish and manage cryptographic keys for cryptography employed in organizational systems.
A100: 3.13.11 | B100: SC.L2-3.13.11 | C100: Employ FIPS-validated cryptography when used to protect the confidentiality of CUI.
A101: 3.13.12 | B101: SC.L2-3.13.12 | C101: Prohibit remote activation of collaborative computing devices and provide indication of devices in use to users present at the device.
A102: 3.13.13 | B102: SC.L2-3.13.13 | C102: Control and monitor the use of mobile code.
A103: 3.13.14 | B103: SC.L2-3.13.14 | C103: Control and monitor the use of Voice over Internet Protocol (VoIP) technologies.
A104: 3.13.15 | B104: SC.L2-3.13.15 | C104: Protect the authenticity of communications sessions.
A105: 3.13.16 | B105: SC.L2-3.13.16 | C105: Protect the confidentiality of CUI at rest.
A106: 3.14.1* | B106: SI.L1-3.14.1 | C106: Identify, report, and correct system flaws in a timely manner.
A107: 3.14.2* | B107: SI.L1-3.14.2 | C107: Provide protection from malicious code at designated locations within organizational systems.
A108: 3.14.3 | B108: SI.L2-3.14.3 | C108: Monitor system security alerts and advisories and take action in response.
A109: 3.14.4* | B109: SI.L1-3.14.4 | C109: Update malicious code protection mechanisms when new releases are available.
A110: 3.14.5* | B110: SI.L1-3.14.5 | C110: Perform periodic scans of organizational systems and real-time scans of files from external sources as files are downloaded, opened, or executed.
... A112: 3.14.7 | B112: SI.L2-3.14.7 | C112: Identify unauthorized use of organizational systems

Sheet Potential Assessment Consid.
A1: Phase | B1: FAR and Above Sort Order | C1: NIST SP 800-171 Family | D1: NIST SP 800-171 Identifier | E1: NIST SP 800-171 Sort-As | F1: Potential Assessment Method and Objects: Examine | G1: Potential Assessment Method and Objects: Interview | H1: Potential Assessment Method and Objects: Test
A2: 1 | B2: 1.01.0 | C2: System and Communications Protection | D2: 3.13.1 | E2: 03.13.01.0 | F2: [SELECT FROM: System and communications protection policy; procedures addressing boundary protection; security plan; list of key internal boundaries of the system; system design documentation; boundary protection hardware and software; enterprise security architecture documentation; system audit logs and records; system configuration settings and associated documentation; other relevant documents or records]. | G2: [SELECT FROM: System or network administrators; personnel with information security responsibilities; system developer; personnel with boundary protection responsibilities]. | H2: [SELECT FROM: Mechanisms implementing boundary protection capability].
A3: 1 | B3: 1.02.0 | C3: System and Communications Protection | D3: 3.13.5 | E3: 03.13.05.0 | F3: [SELECT FROM: System and communications protection policy; procedures addressing boundary protection; security plan; list of key internal boundaries of the system; system design documentation; boundary protection hardware and software; system configuration settings and associated documentation; enterprise security architecture documentation; system audit logs and records; other relevant documents or records]. | G3: [SELECT FROM: System or network administrators; personnel with information security responsibilities; system developer; personnel with boundary protection responsibilities]. | H3: [SELECT FROM: Mechanisms implementing boundary protection capability].
A4: 1 | B4: 1.03.0 | C4: Personnel Security | D4: 3.10.1 | E4: 03.10.01.0 | F4: [SELECT FROM: Physical and environmental protection policy; procedures addressing physical access authorizations; security plan; authorized personnel access list; authorization credentials; physical access list reviews; physical access termination records and associated documentation; other relevant documents or records]. | G4: [SELECT FROM: Personnel with physical access authorization responsibilities; personnel with physical access to system facility; personnel with information security responsibilities]. | H4: [SELECT FROM: Organizational processes for physical access authorizations; mechanisms supporting or implementing physical access authorizations].
A5: 1 | B5: 1.04.0 | C5: Physical Protection | D5: 3.10.3 | E5: 03.10.03.0 | F5: [SELECT FROM: Physical and environmental protection policy; procedures addressing physical access control; security plan; physical access control logs or records; inventory records of physical access control devices; system entry and exit points; records of key and lock combination changes; storage locations for physical access control devices; physical access control devices; list of security safeguards controlling access to designated publicly accessible areas within facility; other relevant documents or records]. | G5: [SELECT FROM: Personnel with physical access control responsibilities; personnel with information security responsibilities]. | H5: [SELECT FROM: Organizational processes for physical access control; mechanisms supporting or implementing physical access control; physical access control devices].
A6: 1 | B6: 1.05.0 | C6: Physical Protection | D6: 3.10.4 | E6: 03.10.04.0 | F6: [SELECT FROM: Physical and environmental protection policy; procedures addressing physical access control; security plan; physical access control logs or records; inventory records of physical access control devices; system entry and exit points; records of key and lock combination changes; storage locations for physical access control devices; physical access control devices; list of security safeguards controlling access to designated publicly accessible areas within facility; other relevant documents or records]. | G6: [SELECT FROM: Personnel with physical access control responsibilities; personnel with information security responsibilities | H6: [SELECT FROM: Organizational processes for physical access control; mechanisms supporting or implementing physical access control; physical access control devices].
A7: 1 | B7: 1.06.0 | C7: Physical Protection | D7: 3.10.5 | E7: 03.10.05.0 | F7: [SELECT FROM: Physical and environmental protection policy; procedures addressing physical access control; security plan; physical access control logs or records; inventory records of physical access control devices; system entry and exit points; records of key and lock combination changes; storage locations for physical access control devices; physical access control devices; list of security safeguards controlling access to designated publicly accessible areas within facility; other relevant documents or records]. | G7: [SELECT FROM: Personnel with physical access control responsibilities; personnel with information security responsibilities]. | H7: [SELECT FROM: Organizational processes for physical access control; mechanisms supporting or implementing physical access control; physical access control devices].
A8: 1 | B8: 1.07.0 | C8: Media Protection | D8: 3.8.3 | E8: 03.08.03.0 | F8: [SELECT FROM: System media protection policy; procedures addressing media sanitization and disposal; applicable standards and policies addressing media sanitization; security plan; media sanitization records; system audit logs and records; system design documentation; system configuration settings and associated documentation; other relevant documents or records]. | G8: [SELECT FROM: Personnel with media sanitization responsibilities; personnel with information security responsibilities; system or network administrators]. | H8: [SELECT FROM: Organizational processes for media sanitization; mechanisms supporting or implementing media sanitization].
A9: 1 | B9: 1.08.0 | C9: System and Information Integrity | D9: 3.14.1 | E9: 03.14.01.0 | F9: [SELECT FROM: System and information integrity policy; procedures addressing flaw remediation; procedures addressing configuration management; security plan; list of flaws and vulnerabilities potentially affecting the system; list of recent security flaw remediation actions performed on the system (e.g., list of installed patches, service packs, hot fixes, and other software updates to correct system flaws); test results from the installation of software and firmware updates to correct system flaws; installation/change control records for security-relevant software and firmware updates; other relevant documents or records]. | G9: [SELECT FROM: System or network administrators; personnel with information security responsibilities; personnel installing, configuring, and maintaining the system; personnel with responsibility for flaw remediation; personnel with configuration management responsibility]. | H9: [SELECT FROM: Organizational processes for identifying, reporting, and correcting system flaws; organizational process for installing software and firmware updates; mechanisms supporting or implementing reporting, and correcting system flaws; mechanisms supporting or implementing testing software and firmware updates].
A10: 1 | B10: 1.09.0 | C10: System and Information Integrity | D10: 3.14.2 | E10: 03.14.02.0 | F10: [SELECT FROM: System and information integrity policy; configuration management policy and procedures; procedures addressing malicious code protection; records of malicious code protection updates; malicious code protection mechanisms; security plan; system design documentation; system configuration settings and associated documentation; record of actions initiated by malicious code protection mechanisms in response to malicious code detection; scan results from malicious code protection mechanisms; system audit logs and records; other relevant documents or records]. | G10: [SELECT FROM: System or network administrators; personnel with information security responsibilities; personnel installing, configuring, and maintaining the system; personnel with responsibility for malicious code protection; personnel with configuration management responsibility]. | H10: [SELECT FROM: Organizational processes for employing, updating, and configuring malicious code protection mechanisms; organizational process for addressing false positives and resulting potential impact; mechanisms supporting or implementing employing, updating, and configuring malicious code protection mechanisms; mechanisms supporting or implementing malicious code scanning and subsequent actions].
A11: 1 | B11: 1.10.0 | C11: System and Information Integrity | D11: 3.14.4 | E11: 03.14.04.0 | F11: [SELECT FROM: System and information integrity policy; configuration management policy and procedures; procedures addressing malicious code protection; malicious code protection mechanisms; records of malicious code protection updates; security plan; system design documentation; system configuration settings and associated documentation; scan results from malicious code protection mechanisms; record of actions initiated by malicious code protection mechanisms in response to malicious code detection; system audit logs and records; other relevant documents or records]. | G11: [SELECT FROM: System or network administrators; personnel with information security responsibilities; personnel installing, configuring, and maintaining the system; personnel with responsibility for malicious code protection; personnel with configuration management responsibility]. | H11: [SELECT FROM: Organizational processes for employing, updating, and configuring malicious code protection mechanisms; organizational process for addressing false positives and resulting potential impact; mechanisms supporting or implementing malicious code protection mechanisms (including updates and configurations); mechanisms supporting or implementing malicious code scanning and subsequent actions].
A12: 1 | B12: 1.11.0 | C12: System and Information Integrity | D12: 3.14.5 | E12: 03.14.05.0 | F12: [SELECT FROM: System and information integrity policy; configuration management policy and procedures; procedures addressing malicious code protection; malicious code protection mechanisms; records of malicious code protection updates; security plan; system design documentation; system configuration settings and associated documentation; scan results from malicious code protection mechanisms; record of actions initiated by malicious code protection mechanisms in response to malicious code detection; system audit logs and records; other relevant documents or records]. | G12: [SELECT FROM: System or network administrators; personnel with information security responsibilities; personnel installing, configuring, and maintaining the system; personnel with responsibility for malicious code protection; personnel with configuration management responsibility]. | H12: [SELECT FROM: Organizational processes for employing, updating, and configuring malicious code protection mechanisms; organizational process for addressing false positives and resulting potential impact; mechanisms supporting or implementing malicious code protection mechanisms (including updates and configurations); mechanisms supporting or implementing malicious code scanning and subsequent actions].
... A52: 3 | B52: 3.11.0 | C52: Incident Response | D52: 3.6.2 | E52: 03.06.02.0 | F52: [SELECT FROM: Incident response policy; procedures addressing incident monitoring; incident response records and documentation; procedures addressing incident reporting; incident reporting records and documentation; incident response plan; security plan; other relevant documents or records]. | G52: [SELECT FROM: Personnel with incident monitoring responsibilities; personnel with incident reporting responsibilities; personnel who have or should have reported incidents; personnel (authorities) to whom incident information is to be reported; personnel with information security responsibilities]. | H52: [SELECT FROM: Incident monitoring capability for the organization; mechanisms supporting or implementing tracking and documenting of system security incidents; organizational processes for incident reporting; mechanisms supporting or implementing incident reporting].
A53: 3 | B53: 3.12.0 | C53: Incident Response | D53: 3.6.3 | E53: 03.06.03.0 | F53: [SELECT FROM: Incident response policy; contingency planning policy; procedures addressing incident response testing; procedures addressing contingency plan testing; incident response testing material; incident response test results; incident response test plan; incident response plan; contingency plan; security plan; other relevant documents or records]. | G53: [SELECT FROM: Personnel with incident response testing responsibilities; personnel with information security responsibilities].
A54: 3 | B54: 3.13.0 | C54: Awareness and Training | D54: 3.3.7 | E54: 03.03.07.0 | F54: [SELECT FROM: Audit and accountability policy; procedures addressing time stamp generation; system design documentation; security plan; system configuration settings and associated documentation; system audit logs and records; other relevant documents or records]. | G54: [SELECT FROM: Personnel with information security responsibilities; system or network administrators; system developers]. | H54: [SELECT FROM: Mechanisms implementing time stamp generation].
A55: 3 | B55: 3.14.0 | C55: Access Control | D55: 3.1.18 | E55: 03.01.18.0 | F55: [SELECT FROM: Access control policy; authorizations for mobile device connections to organizational systems; procedures addressing access control for mobile device usage (including restrictions); system design documentation; configuration management plan; security plan; system audit logs and records; system configuration settings and associated documentation; other relevant documents or records]. | G55: [SELECT FROM: Personnel using mobile devices to access organizational systems; system or network administrators; personnel with information security responsibilities]. | H55: [SELECT FROM: Access control capability authorizing mobile device connections to organizational systems].
A56: 3 | B56: 3.15.0 | C56: Access Control | D56: 3.1.10 | E56: 03.01.10.0 | F56: [SELECT FROM: Access control policy; procedures addressing session lock; procedures addressing identification and authentication; system design documentation; system configuration settings and associated documentation; security plan; other relevant documents or records]. | G56: [SELECT FROM: System or network administrators; personnel with information security responsibilities; system developers]. | H56: [SELECT FROM: Mechanisms implementing access control policy for session lock].
A57: 3 | B57: 3.16.0 | C57: Access Control | D57: 3.1.4 | E57: 03.01.04.0 | F57: [SELECT FROM: Access control policy; procedures addressing divisions of responsibility and separation of duties; security plan; system configuration settings and associated documentation; list of divisions of responsibility and separation of duties; system access authorizations; system audit logs and records; other relevant documents or records]. | G57: [SELECT FROM: Personnel with responsibilities for defining divisions of responsibility and separation of duties; personnel with information security responsibilities; system or network administrators]. | H57: [SELECT FROM: Mechanisms implementing separation of duties policy].
A58: 3 | B58: 3.17.0 | C58: Access Control | D58: 3.1.5 | E58: 03.01.05.0 | F58: [SELECT FROM: Access control policy; procedures addressing account management; security plan; system design documentation; system configuration settings and associated documentation; list of active system accounts and the name of the individual associated with each account; list of conditions for group and role membership; notifications or records of recently transferred, separated, or terminated employees; list of recently disabled system accounts along with the name of the individual associated with each account; access authorization records; account management compliance reviews; system monitoring/audit records; other relevant documents or records; procedures addressing least privilege; list of security functions (deployed in hardware, software, and firmware) and security-relevant information for which access must be explicitly authorized; list of system-generated privileged accounts; list of system administration personnel]. | G58: [SELECT FROM: Personnel with account management responsibilities; system or network administrators; personnel with information security responsibilities; personnel with responsibilities for defining least privileges necessary to accomplish specified tasks]. | H58: [SELECT FROM: Organizational processes for managing system accounts; mechanisms for implementing account management; mechanisms implementing least privilege functions; mechanisms prohibiting privileged access to the system].
A59: 3 | B59: 3.18.0 | C59: Awareness and Training | D59: 3.3.2 | E59: 03.03.02.0 | F59: [SELECT FROM: Audit and accountability policy; procedures addressing audit records and event types; security plan; system design documentation; system configuration settings and associated documentation; system audit logs and records; system events; system incident reports; other relevant documents or records]. | G59: [SELECT FROM: Personnel with audit and accountability responsibilities; personnel with information security responsibilities; system or network administrators]. | H59: [SELECT FROM: Mechanisms implementing system audit logging].
A60: 4 | B60: 4.01.0 | C60: Awareness and Training | D60: 3.3.1 | E60: 03.03.01.0 | F60: [SELECT FROM: Audit and accountability policy; procedures addressing auditable events; security plan; system design documentation; system configuration settings and associated documentation; system audit logs and records; system auditable events; system incident reports; other relevant documents or records]. | G60: [SELECT FROM: Personnel with audit and accountability responsibilities; personnel with information security responsibilities; system or network administrators]. | H60: [SELECT FROM: Mechanisms implementing system audit logging].
A61: 4 | B61: 4.02.0 | C61: Awareness and Training | D61: 3.3.3 | E61: 03.03.03.0 | F61: [SELECT FROM: Audit and accountability policy; procedures addressing audit records and event types; security plan; list of organization-defined event types to be logged; reviewed and updated records of logged event types; system audit logs and records; system incident reports; other relevant documents or records]. | G61: [SELECT FROM: Personnel with audit and accountability responsibilities; personnel with information security responsibilities]. | H61: [SELECT FROM: Mechanisms supporting review and update of logged event types].
A62: 4 | B62: 4.03.0 | C62: Awareness and Training | D62: 3.3.4 | E62: 03.03.04.0 | F62: [SELECT FROM: Audit and accountability policy; procedures addressing response to audit logging processing failures; system design documentation; security plan; system configuration settings and associated documentation; list of personnel to be notified in case of an audit logging processing failure; system incident reports; system audit logs and records; other relevant documents or records]. | G62: [SELECT FROM: Personnel with audit and accountability responsibilities; personnel with information security responsibilities; system or network administrators; system developers]. | H62: [SELECT FROM: Mechanisms implementing system response to audit logging processing failures].
A63: 4 | B63: 4.04.0 | C63: Awareness and Training | D63: 3.3.5 | E63: 03.03.05.0 | F63: [SELECT FROM: Audit and accountability policy; procedures addressing audit record review, analysis, and reporting; security plan; system design documentation; system configuration settings and associated documentation; system audit logs and records across different repositories; other relevant documents or records]. | G63: [SELECT FROM: Personnel with audit record review, analysis, and reporting responsibilities; personnel with information security responsibilities]. | H63: : [SELECT FROM: Mechanisms supporting analysis and correlation of audit records].
A64: 4 | B64: 4.05.0 | C64: System and Information Integrity | D64: 3.14.7 | E64: 03.14.07.0 | F64: [SELECT FROM: Continuous monitoring strategy; system and information integrity policy; procedures addressing system monitoring tools and techniques; facility diagram/layout; security plan; system design documentation; system monitoring tools and techniques documentation; locations within system where monitoring devices are deployed; system configuration settings and associated documentation; other relevant documents or records]. | G64: [SELECT FROM: System or network administrators; personnel with information security responsibilities; personnel installing, configuring, and maintaining the system; personnel with responsibility for monitoring the system]. | H64: [SELECT FROM: Organizational processes for system monitoring; mechanisms supporting or implementing system monitoring capability].
A65: 4 | B65: 4.06.0 | C65: Awareness and Training | D65: 3.3.6 | E65: 03.03.06.0 | F65: [SELECT FROM: Audit and accountability policy; procedures addressing audit record reduction and report generation; system design documentation; security plan; system configuration settings and associated documentation; audit record reduction, review, analysis, and reporting tools; system audit logs and records; other relevant documents or records]. | G65: [SELECT FROM: Personnel with audit record reduction and report generation responsibilities; personnel with information security responsibilities]. | H65: [SELECT FROM: Audit record reduction and report generation capability].
... A111: 5 | B111: 5.29.0 | C111: Physical Protection | D111: 3.10.6 | E111: 03.10.06.0 | F111: [SELECT FROM: Physical and environmental protection policy; procedures addressing alternate work sites for personnel; security plan; list of safeguards required for alternate work sites; assessments of safeguards at alternate work sites; other relevant documents or records]. | G111: [SELECT FROM: Personnel approving use of alternate work sites; personnel using alternate work sites; personnel assessing controls at alternate work sites; personnel with information security responsibilities]. | H111: [SELECT FROM: Organizational processes for security at alternate work sites; mechanisms supporting alternate work sites; safeguards employed at alternate work sites; means of communications between personnel at alternate work sites and security personnel].

Sheet CUI Types
A1: Organizational Index Grouping | B1: CUI Categories
A2: Critical Infrastructure | B2: Ammonium Nitrate
B3: Chemical-terrorism Vulnerability Information
B4: Critical Energy Infrastructure Information
B5: Emergency Management
B6: General Critical Infrastructure Information
B7: Information Systems Vulnerability Information
B8: Physical Security
B9: Protected Critical Infrastructure Information
B10: SAFETY Act Information
B11: Toxic Substances
B12: Water Assessments
A13: Defense | B13: Controlled Technical Information
B14: DoD Critical Infrastructure Security Information
B15: Naval Nuclear Propulsion Information
B16: Unclassified Controlled Nuclear Information - Defense
A17: Export Control | B17: Export Controlled
B18: Export Controlled Research
A19: Financial | B19: Bank Secrecy
B20: Budget
B21: Comptroller General
B22: Consumer Complaint Information
B23: Electronic Funds Transfer
B24: Federal Housing Finance Non-Public Information
B25: Financial Supervision Information
B26: General Financial Information
B27: International Financial Institutions
B28: Mergers
B29: Net Worth
B30: Retirement
A31: Immigration | B31: Asylee
B32: Battered Spouse or Child
B33: Permanent Resident Status
B34: Status Adjustment
B35: Temporary Protected Status
B36: Victims of Human Trafficking
B37: Visas
A38: Intelligence | B38: Agriculture
B39: Foreign Intelligence Surveillance Act
B40: Foreign Intelligence Surveillance Act Business Records
B41: General Intelligence
B42: Geodetic Product Information
B43: Intelligence Financial Records
B44: Internal Data
B45: Operations Security
A46: International Agreements | B46: International Agreement Information
A47: Law Enforcement | B47: Accident Investigation
B48: Campaign Funds
B49: Committed Person
B50: Communications
B51: Controlled Substances
B52: Criminal History Records Information
B53: DNA
B54: General Law Enforcement
B55: Informant
B56: Investigation
B57: Juvenile
B58: Law Enforcement Financial Records
B59: National Security Letter
... B64: Whistleblower Identity
A65: Legal | B65: Administrative Proceedings
B66: Child Pornography
B67: Child Victim/Witness
B68: Collective Bargaining
B69: Federal Grand Jury
B70: Legal Privilege
B71: Legislative Materials
B72: Presentence Report
B73: Prior Arrest
B74: Protective Order
B75: Victim
B76: Witness Protection
A77: Natural and Cultural Resources | B77: Archaeological Resources
B78: Historic Properties
B79: National Park System Resources
A80: North Atlantic Treaty Organization (NATO) | B80: NATO Restricted
B81: NATO Unclassified
A82: Nuclear | B82: General Nuclear
B83: Nuclear Recommendation Material
B84: Nuclear Security-Related Information
B85: Safeguards Information
B86: Unclassified Controlled Nuclear Information - Energy
A87: Patent | B87: Patent Applications
B88: Inventions
B89: Secrecy Orders
A90: Privacy | B90: Contract Use
B91: Death Records
B92: General Privacy
B93: Genetic Information
B94: Health Information
B95: Inspector General Protected
B96: Military Personnel Records
B97: Personnel Records
B98: Student Records
A99: Procurement and Acquisition | B99: General Procurement and Acquisition
B100: Small Business Research and Technology
B101: Source Selection
A102: Proprietary Business Information | B102: Entity Registration Information
B103: General Proprietary Business Information
B104: Ocean Common Carrier and Marine Terminal Operator Agreements
...

Sheet Old DoD 800-171 Score Template
A1: Information for SPRS Submission | H1: Self-Assessment Against NIST SP 800-171 using NIST SP 800-171A criteria and DoD template and scoring | Q1: Plan of Action and Milestones
A2: Date of Assessment | B2: CAGE Code | C2: System Description | D2: SPRS Score | E2: Date when 110 Score Expected | H2: Security Requirement | J2: DoD Score Value | K2: DoD Comment to Assessor | L2: Assessor Notes | M2: Implementation Status | N2: Target Implementation Completion Date | O2: Score Impact | Q2: Responsible Office/Organization | R2: Resource Estimate (Funded, Unfunded, Reallocated) | S2: Milestones with Interim Completion Dates | T2: Changes to Milestones
D3: {=IF(O89=-1000,"No SSP, therefore an assessment could not be completed due to incomplete information and noncompliance with DFARS clause 252.204-7012. See 3.12.4.",110+(SUM(O3:O112)))} | E3: N/A | G3: Access Control | H3: 3.1.1* | I3: Limit system access to authorized users, processes acting on behalf of authorized users, and devices (including other systems). | J3: 5 | M3: Not Yet Assessed | O3: {=IF(M3<>"Fully Implemented",-1*J3,0)}
A4: Prepared for (Organization Name) | B4: Prepared by (Assessor Name) | H4: 3.1.2* | I4: Limit system access to the types of transactions and functions that authorized users are permitted to execute. | J4: 5 | M4: Not Yet Assessed | O4: {=IF(M4<>"Fully Implemented",-1*J4,0)}
H5: 3.1.3 | I5: Control the flow of CUI in accordance with approved authorizations. | J5: 1 | M5: Not Yet Assessed | O5: {=IF(M5<>"Fully Implemented",-1*J5,0)}
H6: 3.1.4 | I6: Separate the duties of individuals to reduce the risk of malevolent activity without collusion. | J6: 1 | M6: Not Yet Assessed | O6: {=IF(M6<>"Fully Implemented",-1*J6,0)}
H7: 3.1.5 | I7: Employ the principle of least privilege, including for specific security functions and privileged accounts. | J7: 3 | M7: Not Yet Assessed | O7: {=IF(M7<>"Fully Implemented",-1*J7,0)}
H8: 3.1.6 | I8: Use non-privileged accounts or roles when accessing non-security functions. | J8: 1 | M8: Not Yet Assessed | O8: {=IF(M8<>"Fully Implemented",-1*J8,0)}
H9: 3.1.7 | I9: Prevent non-privileged users from executing privileged functions and capture the execution of such functions in audit logs. | J9: 1 | M9: Not Yet Assessed | O9: {=IF(M9<>"Fully Implemented",-1*J9,0)}
H10: 3.1.8 | I10: Limit unsuccessful logon attempts. | J10: 1 | M10: Not Yet Assessed | O10: {=IF(M10<>"Fully Implemented",-1*J10,0)}
H11: 3.1.9 | I11: Provide privacy and security notices consistent with applicable CUI rules. | J11: 1 | M11: Not Yet Assessed | O11: {=IF(M11<>"Fully Implemented",-1*J11,0)}
H12: 40238 | I12: Use session lock with pattern-hiding displays to prevent access and viewing of data after a period of inactivity. | J12: 1 | M12: Not Yet Assessed | O12: {=IF(M12<>"Fully Implemented",-1*J12,0)}
H13: 40603 | I13: Terminate (automatically) a user session after a defined condition. | J13: 1 | M13: Not Yet Assessed | O13: {=IF(M13<>"Fully Implemented",-1*J13,0)}
H14: 40969 | I14: Monitor and control remote access sessions. | J14: 5 | K14: Do not subtract points if remote access not permitted | M14: Not Yet Assessed | O14: {=IF(OR(M14="Fully Implemented",M14="Not Permitted"),0,-1*J14)}
H15: 41334 | I15: Employ cryptographic mechanisms to protect the confidentiality of remote access sessions. | J15: 5 | K15: Do not subtract points if remote access not permitted | M15: Not Yet Assessed | O15: {=IF(OR(M15="Fully Implemented",M15="Not Permitted"),0,-1*J15)}
H16: 41699 | I16: Route remote access via managed access control points. | J16: 1 | M16: Not Yet Assessed | O16: {=IF(M16<>"Fully Implemented",-1*J16,0)}
H17: 42064 | I17: Authorize remote execution of privileged commands and remote access to security- relevant information. | J17: 1 | M17: Not Yet Assessed | O17: {=IF(M17<>"Fully Implemented",-1*J17,0)}
H18: 42430 | I18: Authorize wireless access prior to allowing such connections. | J18: 5 | K18: Do not subtract points if wireless access not permitted | M18: Not Yet Assessed | O18: {=IF(OR(M18="Fully Implemented",M18="Not Permitted"),0,-1*J18)}
H19: 42795 | I19: Protect wireless access using authentication and encryption. | J19: 5 | K19: Do not subtract points if wireless access not permitted | M19: Not Yet Assessed | O19: {=IF(OR(M19="Fully Implemented",M19="Not Permitted"),0,-1*J19)}
H20: 43160 | I20: Control connection of mobile devices. | J20: 5 | K20: Do not subtract points if connection of mobile devices is not permitted. | M20: Not Yet Assessed | O20: {=IF(OR(M20="Fully Implemented",M20="Not Permitted"),0,-1*J20)}
H21: 43525 | I21: Encrypt CUI on mobile devices and mobile computing platforms | J21: 3 | K21: Exposure limited to CUI on mobile platform | M21: Not Yet Assessed | O21: {=IF(M21<>"Fully Implemented",-1*J21,0)}
H22: 3.1.20* | I22: Verify and control/limit connections to and use of external systems. | J22: 1 | M22: Not Yet Assessed | O22: {=IF(M22<>"Fully Implemented",-1*J22,0)}
H23: 44256 | I23: Limit use of portable storage devices on external systems. | J23: 1 | M23: Not Yet Assessed | O23: {=IF(M23<>"Fully Implemented",-1*J23,0)}
H24: 3.1.22* | I24: Control CUI posted or processed on publicly accessible systems. | J24: 1 | M24: Not Yet Assessed | O24: {=IF(M24<>"Fully Implemented",-1*J24,0)}
G25: Awareness and Training | H25: 3.2.1 | I25: Ensure that managers, systems administrators, and users of organizational systems are made aware of the security risks associated with their activities and of the applicable policies, standards, and procedures related to the security of those systems. | J25: 5 | M25: Not Yet Assessed | O25: {=IF(M25<>"Fully Implemented",-1*J25,0)}
H26: 3.2.2 | I26: Ensure that personnel are trained to carry out their assigned information security- related duties and responsibilities. | J26: 5 | M26: Not Yet Assessed | O26: {=IF(M26<>"Fully Implemented",-1*J26,0)}
H27: 3.2.3 | I27: Provide security awareness training on recognizing and reporting potential indicators of insider threat. | J27: 1 | M27: Not Yet Assessed | O27: {=IF(M27<>"Fully Implemented",-1*J27,0)}
G28: Audit and Accountability | H28: 3.3.1 | I28: Create and retain system audit logs and records to the extent needed to enable the monitoring, analysis, investigation, and reporting of unlawful or unauthorized system activity. | J28: 5 | M28: Not Yet Assessed | O28: {=IF(M28<>"Fully Implemented",-1*J28,0)}
H29: 3.3.2 | I29: Ensure that the actions of individual system users can be uniquely traced to those users so they can be held accountable for their actions. | J29: 3 | M29: Not Yet Assessed | O29: {=IF(M29<>"Fully Implemented",-1*J29,0)}
H30: 3.3.3 | I30: Review and update logged events. | J30: 1 | M30: Not Yet Assessed | O30: {=IF(M30<>"Fully Implemented",-1*J30,0)}
H31: 3.3.4 | I31: Alert in the event of an audit logging process failure. | J31: 1 | M31: Not Yet Assessed | O31: {=IF(M31<>"Fully Implemented",-1*J31,0)}
H32: 3.3.5 | I32: Correlate audit record review, analysis, and reporting processes for investigation and response to indications of unlawful, unauthorized, suspicious, or unusual activity. | J32: 5 | M32: Not Yet Assessed | O32: {=IF(M32<>"Fully Implemented",-1*J32,0)}
H33: 3.3.6 | I33: Provide audit record reduction and report generation to support on-demand analysis and reporting. | J33: 1 | M33: Not Yet Assessed | O33: {=IF(M33<>"Fully Implemented",-1*J33,0)}
H34: 3.3.7 | I34: Provide a system capability that compares and synchronizes internal system clocks with an authoritative source to generate time stamps for audit records. | J34: 1 | M34: Not Yet Assessed | O34: {=IF(M34<>"Fully Implemented",-1*J34,0)}
H35: 3.3.8 | I35: Protect audit information and audit logging tools from unauthorized access, modification, and deletion. | J35: 1 | M35: Not Yet Assessed | O35: {=IF(M35<>"Fully Implemented",-1*J35,0)}
H36: 3.3.9 | I36: Limit management of audit logging functionality to a subset of privileged users. | J36: 1 | M36: Not Yet Assessed | O36: {=IF(M36<>"Fully Implemented",-1*J36,0)}
G37: Configuration Management | H37: 3.4.1 | I37: Establish and maintain baseline configurations and inventories of organizational systems (including hardware, software, firmware, and documentation) throughout the respective system development life cycles. | J37: 5 | M37: Not Yet Assessed | O37: {=IF(M37<>"Fully Implemented",-1*J37,0)}
H38: 3.4.2 | I38: Establish and enforce security configuration settings for information technology products employed in organizational systems. | J38: 5 | M38: Not Yet Assessed | O38: {=IF(M38<>"Fully Implemented",-1*J38,0)}
H39: 3.4.3 | I39: Track, review, approve or disapprove, and log changes to organizational systems. | J39: 1 | M39: Not Yet Assessed | O39: {=IF(M39<>"Fully Implemented",-1*J39,0)}
H40: 3.4.4 | I40: Analyze the security impact of changes prior to implementation. | J40: 1 | M40: Not Yet Assessed | O40: {=IF(M40<>"Fully Implemented",-1*J40,0)}
H41: 3.4.5 | I41: Define, document, approve, and enforce physical and logical access restrictions associated with changes to organizational systems. | J41: 5 | M41: Not Yet Assessed | O41: {=IF(M41<>"Fully Implemented",-1*J41,0)}
H42: 3.4.6 | I42: Employ the principle of least functionality by configuring organizational systems to provide only essential capabilities. | J42: 5 | M42: Not Yet Assessed | O42: {=IF(M42<>"Fully Implemented",-1*J42,0)}
H43: 3.4.7 | I43: Restrict, disable, or prevent the use of nonessential programs, functions, ports, protocols, and services. | J43: 5 | M43: Not Yet Assessed | O43: {=IF(M43<>"Fully Implemented",-1*J43,0)}
H44: 3.4.8 | I44: Apply deny-by-exception (blacklisting) policy to prevent the use of unauthorized software or deny-all, permit-by-exception (whitelisting) policy to allow the execution of authorized software. | J44: 5 | M44: Not Yet Assessed | O44: {=IF(M44<>"Fully Implemented",-1*J44,0)}
H45: 3.4.9 | I45: Control and monitor user-installed software. | J45: 1 | M45: Not Yet Assessed | O45: {=IF(M45<>"Fully Implemented",-1*J45,0)}
G46: Identificiation and Authorization | H46: 3.5.1* | I46: Identify system users, processes acting on behalf of users, and devices. | J46: 5 | M46: Not Yet Assessed | O46: {=IF(M46<>"Fully Implemented",-1*J46,0)}
H47: 3.5.2* | I47: Authenticate (or verify) the identities of users, processes, or devices, as a prerequisite to allowing access to organizational systems. | J47: 5 | M47: Not Yet Assessed | O47: {=IF(M47<>"Fully Implemented",-1*J47,0)}
H48: 3.5.3 | I48: Use multifactor authentication (MFA) for local and network access to privileged accounts and for network access to non- privileged accounts. | J48: 3 to 5 | K48: Subtract 5 points if MFA not implemented. Subtract 3 points if implemented for remote and privileged users, but not the general user | M48: Not Yet Assessed | O48: {=IF(M48="Implemented for Remote and Privileged Users",-3,IF(M48<>"Fully Implemented",-5,0))}
H49: 3.5.4 | I49: Employ replay-resistant authentication mechanisms for network access to privileged and non-privileged accounts. | J49: 1 | M49: Not Yet Assessed | O49: {=IF(M49<>"Fully Implemented",-1*J49,0)}
H50: 3.5.5 | I50: Prevent reuse of identifiers for a defined period. | J50: 1 | M50: Not Yet Assessed | O50: {=IF(M50<>"Fully Implemented",-1*J50,0)}
H51: 3.5.6 | I51: Disable identifiers after a defined period of inactivity. | J51: 1 | M51: Not Yet Assessed | O51: {=IF(M51<>"Fully Implemented",-1*J51,0)}
H52: 3.5.7 | I52: Enforce a minimum password complexity and change of characters when new passwords are created. | J52: 1 | M52: Not Yet Assessed | O52: {=IF(M52<>"Fully Implemented",-1*J52,0)}
H53: 3.5.8 | I53: Prohibit password reuse for a specified number of generations. | J53: 1 | M53: Not Yet Assessed | O53: {=IF(M53<>"Fully Implemented",-1*J53,0)}
H54: 3.5.9 | I54: Allow temporary password use for system logons with an immediate change to a permanent password. | J54: 1 | M54: Not Yet Assessed | O54: {=IF(M54<>"Fully Implemented",-1*J54,0)}
H55: 40242 | I55: Store and transmit only cryptographically- protected passwords. | J55: 5 | K55: Encrypted representations of passwords include, for example, encrypted versions of passwords and one-way cryptographic hashes of passwords | M55: Not Yet Assessed | O55: {=IF(M55<>"Fully Implemented",-1*J55,0)}
H56: 40607 | I56: Obscure feedback of authentication information. | J56: 1 | M56: Not Yet Assessed | O56: {=IF(M56<>"Fully Implemented",-1*J56,0)}
G57: Incident Response | H57: 3.6.1 | I57: Establish an operational incident-handling capability for organizational systems that includes preparation, detection, analysis, containment, recovery, and user response activities. | J57: 5 | M57: Not Yet Assessed | O57: {=IF(M57<>"Fully Implemented",-1*J57,0)}
H58: 3.6.2 | I58: Track, document, and report incidents to designated officials and/or authorities both internal and external to the organization. | J58: 5 | M58: Not Yet Assessed | O58: {=IF(M58<>"Fully Implemented",-1*J58,0)}
H59: 3.6.3 | I59: Test the organizational incident response capability. | J59: 1 | M59: Not Yet Assessed | O59: {=IF(M59<>"Fully Implemented",-1*J59,0)}
G60: Maintenance | H60: 3.7.1 | I60: Perform maintenance on organizational systems. | J60: 3 | M60: Not Yet Assessed | O60: {=IF(M60<>"Fully Implemented",-1*J60,0)}
H61: 3.7.2 | I61: Provide controls on the tools, techniques, mechanisms, and personnel used to conduct system maintenance. | J61: 5 | M61: Not Yet Assessed | O61: {=IF(M61<>"Fully Implemented",-1*J61,0)}
H62: 3.7.3 | I62: Ensure equipment removed for off-site maintenance is sanitized of any CUI. | J62: 1 | M62: Not Yet Assessed | O62: {=IF(M62<>"Fully Implemented",-1*J62,0)}
H63: 3.7.4 | I63: Check media containing diagnostic and test programs for malicious code before the media are used in organizational systems. | J63: 3 | M63: Not Yet Assessed | O63: {=IF(M63<>"Fully Implemented",-1*J63,0)}
H64: 3.7.5 | I64: Require multifactor authentication to establish nonlocal maintenance sessions via external network connections and terminate such connections when nonlocal maintenance is complete. | J64: 5 | M64: Not Yet Assessed | O64: {=IF(M64<>"Fully Implemented",-1*J64,0)}
H65: 3.7.6 | I65: Supervise the maintenance activities of maintenance personnel without required access authorization. | J65: 1 | M65: Not Yet Assessed | O65: {=IF(M65<>"Fully Implemented",-1*J65,0)}
G66: Media Protection | H66: 3.8.1 | I66: Protect (i.e., physically control and securely store) system media containing CUI, both paper and digital. | J66: 3 | K66: Exposure limited to CUI on media | M66: Not Yet Assessed | O66: {=IF(M66<>"Fully Implemented",-1*J66,0)}
H67: 3.8.2 | I67: Limit access to CUI on system media to authorized users. | J67: 3 | K67: Exposure limited to CUI on media | M67: Not Yet Assessed | O67: {=IF(M67<>"Fully Implemented",-1*J67,0)}
H68: 3.8.3* | I68: Sanitize or destroy system media containing CUI before disposal or release for reuse. | J68: 5 | K68: While exposure limited to CUI on media, failure to sanitize can result in continual exposure of CUI | M68: Not Yet Assessed | O68: {=IF(M68<>"Fully Implemented",-1*J68,0)}
H69: 3.8.4 | I69: Mark media with necessary CUI markings and distribution limitations. | J69: 1 | M69: Not Yet Assessed | O69: {=IF(M69<>"Fully Implemented",-1*J69,0)}
H70: 3.8.5 | I70: Control access to media containing CUI and maintain accountability for media during transport outside of controlled areas. | J70: 1 | M70: Not Yet Assessed | O70: {=IF(M70<>"Fully Implemented",-1*J70,0)}
H71: 3.8.6 | I71: Implement cryptographic mechanisms to protect the confidentiality of CUI stored on digital media during transport unless otherwise protected by alternative physical safeguards. | J71: 1 | M71: Not Yet Assessed | O71: {=IF(M71<>"Fully Implemented",-1*J71,0)}
H72: 3.8.7 | I72: Control the use of removable media on system components. | J72: 5 | M72: Not Yet Assessed | O72: {=IF(M72<>"Fully Implemented",-1*J72,0)}
H73: 3.8.8 | I73: Prohibit the use of portable storage devices when such devices have no identifiable owner. | J73: 3 | M73: Not Yet Assessed | O73: {=IF(M73<>"Fully Implemented",-1*J73,0)}
H74: 3.8.9 | I74: Protect the confidentiality of backup CUI at storage locations. | J74: 1 | M74: Not Yet Assessed | O74: {=IF(M74<>"Fully Implemented",-1*J74,0)}
G75: Personnel Security | H75: 3.9.1 | I75: Screen individuals prior to authorizing access to organizational systems containing CUI. | J75: 3 | M75: Not Yet Assessed | O75: {=IF(M75<>"Fully Implemented",-1*J75,0)}
H76: 3.9.2 | I76: Ensure that organizational systems containing CUI are protected during and after personnel actions such as terminations and transfers. | J76: 5 | M76: Not Yet Assessed | O76: {=IF(M76<>"Fully Implemented",-1*J76,0)}
G77: Physical Protection | H77: 3.10.1* | I77: Limit physical access to organizational systems, equipment, and the respective operating environments to authorized individuals. | J77: 5 | M77: Not Yet Assessed | O77: {=IF(M77<>"Fully Implemented",-1*J77,0)}
H78: 3.10.2 | I78: Protect and monitor the physical facility and support infrastructure for organizational systems. | J78: 5 | M78: Not Yet Assessed | O78: {=IF(M78<>"Fully Implemented",-1*J78,0)}
H79: 3.10.3* | I79: Escort visitors and monitor visitor activity. | J79: 1 | M79: Not Yet Assessed | O79: {=IF(M79<>"Fully Implemented",-1*J79,0)}
H80: 3.10.4* | I80: Maintain audit logs of physical access. | J80: 1 | M80: Not Yet Assessed | O80: {=IF(M80<>"Fully Implemented",-1*J80,0)}
H81: 3.10.5* | I81: Control and manage physical access devices. | J81: 1 | M81: Not Yet Assessed | O81: {=IF(M81<>"Fully Implemented",-1*J81,0)}
H82: 3.10.6 | I82: Enforce safeguarding measures for CUI at alternate work sites. | J82: 1 | M82: Not Yet Assessed | O82: {=IF(M82<>"Fully Implemented",-1*J82,0)}
G83: Risk Assessment | H83: 3.11.1 | I83: Periodically assess the risk to organizational operations (including mission, functions, image, or reputation), organizational assets, and individuals, resulting from the operation of organizational systems and the associated processing, storage, or transmission of CUI. | J83: 3 | M83: Not Yet Assessed | O83: {=IF(M83<>"Fully Implemented",-1*J83,0)}
H84: 3.11.2 | I84: Scan for vulnerabilities in organizational systems and applications periodically and when new vulnerabilities affecting those systems and applications are identified. | J84: 5 | M84: Not Yet Assessed | O84: {=IF(M84<>"Fully Implemented",-1*J84,0)}
H85: 3.11.3 | I85: Remediate vulnerabilities in accordance with risk assessments. | J85: 1 | M85: Not Yet Assessed | O85: {=IF(M85<>"Fully Implemented",-1*J85,0)}
G86: Security Assessment | H86: 3.12.1 | I86: Periodically assess the security controls in organizational systems to determine if the controls are effective in their application. | J86: 5 | M86: Not Yet Assessed | O86: {=IF(M86<>"Fully Implemented",-1*J86,0)}
H87: 3.12.2 | I87: Develop and implement plans of action designed to correct deficiencies and reduce or eliminate vulnerabilities in organizational systems. | J87: 3 | M87: Not Yet Assessed | O87: {=IF(M87<>"Fully Implemented",-1*J87,0)}
H88: 3.12.3 | I88: Monitor security controls on an ongoing basis to ensure the continued effectiveness of the controls. | J88: 5 | M88: Not Yet Assessed | O88: {=IF(M88<>"Fully Implemented",-1*J88,0)}
H89: 3.12.4 | I89: Develop, document, and periodically update system security plans that describe system boundaries, system environments of operation, how security requirements are implemented, and the relationships with or connections to other systems. | J89: NA | K89: The absence of a system security plan would result in a finding that ‘an assessment could not be completed due to incomplete information and noncompliance with DFARS clause 252.204-7012.’ | M89: Not Yet Assessed | O89: {=IF(M89<>"Fully Implemented",-1000,0)}
G90: System and Communications Protection | H90: 3.13.1* | I90: Monitor, control, and protect communications (i.e., information transmitted or received by organizational systems) at the external boundaries and key internal boundaries of organizational systems. | J90: 5 | M90: Not Yet Assessed | O90: {=IF(M90<>"Fully Implemented",-1*J90,0)}
H91: 3.13.2 | I91: Employ architectural designs, software development techniques, and systems engineering principles that promote effective information security within organizational systems. | J91: 5 | M91: Not Yet Assessed | O91: {=IF(M91<>"Fully Implemented",-1*J91,0)}
H92: 3.13.3 | I92: Separate user functionality from system management functionality. | J92: 1 | M92: Not Yet Assessed | O92: {=IF(M92<>"Fully Implemented",-1*J92,0)}
H93: 3.13.4 | I93: Prevent unauthorized and unintended information transfer via shared system resources. | J93: 1 | M93: Not Yet Assessed | O93: {=IF(M93<>"Fully Implemented",-1*J93,0)}
H94: 3.13.5* | I94: Implement subnetworks for publicly accessible system components that are physically or logically separated from internal networks. | J94: 5 | M94: Not Yet Assessed | O94: {=IF(M94<>"Fully Implemented",-1*J94,0)}
H95: 3.13.6 | I95: Deny network communications traffic by default and allow network communications traffic by exception (i.e., deny all, permit by exception). | J95: 5 | M95: Not Yet Assessed | O95: {=IF(M95<>"Fully Implemented",-1*J95,0)}
H96: 3.13.7 | I96: Prevent remote devices from simultaneously establishing non-remote connections with organizational systems and communicating via some other connection to resources in external networks (i.e., split tunneling). | J96: 1 | M96: Not Yet Assessed | O96: {=IF(M96<>"Fully Implemented",-1*J96,0)}
H97: 3.13.8 | I97: Implement cryptographic mechanisms to prevent unauthorized disclosure of CUI during transmission unless otherwise protected by alternative physical safeguards. | J97: 3 | M97: Not Yet Assessed | O97: {=IF(M97<>"Fully Implemented",-1*J97,0)}
H98: 3.13.9 | I98: Terminate network connections associated with communications sessions at the end of the sessions or after a defined period of inactivity. | J98: 1 | M98: Not Yet Assessed | O98: {=IF(M98<>"Fully Implemented",-1*J98,0)}
H99: 40250 | I99: Establish and manage cryptographic keys for cryptography employed in organizational systems. | J99: 1 | M99: Not Yet Assessed | O99: {=IF(M99<>"Fully Implemented",-1*J99,0)}
H100: 40615 | I100: Employ FIPS-validated cryptography when used to protect the confidentiality of CUI. | J100: 3 to 5 | K100: Subtract 5 points if no cryptography is employed; 3 points if mostly not FIPS validated | M100: Not Yet Assessed | O100: {=IF(M100="CUI is encrypted but not using FIPS-validated cryptography",-3,IF(M100="All CUI is encrypted using FIPS-validated cryptography",0,-5))}
...

Sheet References
A1: Fully Implemented | C1: TM
A2: Implementation Begun | I2: FAR and Above Order | J2: NIST SP 800-171 Control | K2: NIST Sort Order | L2: NIST SP 800-171 Basic or Derived | M2: DoD Score Value | N2: CMMC Domain Abbrev. | O2: CMMC Domain Desc. | P2: CMMC Practice | T2: NIST Requirement | U2: NIST Family/CMMC Domain
A3: Implementation Planned | I3: 1.14 | J3: 3.1.1 | K3: 03.01.01.0 | L3: Basic | M3: 5 | N3: AC | O3: Access Control | P3: AC.L1-3.1.1 | T3: 3.1.1 | U3: AC | V3: Access Cont
A4: Not Yet Addressed | I4: 1.15 | J4: 3.1.2 | K4: 03.01.02.0 | L4: Basic | M4: 5 | N4: AC | O4: Access Control | P4: AC.L1-3.1.2 | T4: 3.2.1 | U4: AT | V4: Awareness and Training
A5: Not Yet Assessed | I5: 5.13 | J5: 3.1.3 | K5: 03.01.03.0 | L5: Derived | M5: 1 | N5: AC | O5: Access Control | P5: AC.L2-3.1.3 | T5: 3.3.1 | U5: AU | V5: Autdit and Accountability
I6: 3.16 | J6: 3.1.4 | K6: 03.01.04.0 | L6: Derived | M6: 1 | N6: AC | O6: Access Control | P6: AC.L2-3.1.4 | T6: 3.4.1 | U6: CM | V6: Configuration Management
A7: Fully Implemented | I7: 3.17 | J7: 3.1.5 | K7: 03.01.05.0 | L7: Derived | M7: 3 | N7: AC | O7: Access Control | P7: AC.L2-3.1.5 | T7: 3.5.1 | U7: IA | V7: Identification and Authentication
A8: Implemented for Remote and Privileged Users | I8: 2.09 | J8: 3.1.6 | K8: 03.01.06.0 | L8: Derived | M8: 1 | N8: AC | O8: Access Control | P8: AC.L2-3.1.6 | T8: 3.6.1 | U8: IR | V8: Incident Response
A9: Implementation Planned | I9: 5.03 | J9: 3.1.7 | K9: 03.01.07.0 | L9: Derived | M9: 1 | N9: AC | O9: Access Control | P9: AC.L2-3.1.7 | T9: 3.7.1 | U9: MA | V9: Maintenance
A10: Not Yet Addressed | I10: 2.05 | J10: 3.1.8 | K10: 03.01.08.0 | L10: Derived | M10: 1 | N10: AC | O10: Access Control | P10: AC.L2-3.1.8 | T10: 3.8.1 | U10: MP | V10: Media Protection
A11: Not Yet Assessed | I11: 5.1 | J11: 3.1.9 | K11: 03.01.09.0 | L11: Derived | M11: 1 | N11: AC | O11: Access Control | P11: AC.L2-3.1.9 | T11: 3.9.1 | U11: PS | V11: Personnel Security
I12: 3.15 | J12: 3.1.10 | K12: 03.01.10.0 | L12: Derived | M12: 1 | N12: AC | O12: Access Control | P12: AC.L2-3.1.10 | T12: 3.10.1 | U12: PE | V12: Physical Protection
I13: 5.2 | J13: 3.1.11 | K13: 03.01.11.0 | L13: Derived | M13: 1 | N13: AC | O13: Access Control | P13: AC.L2-3.1.11 | T13: 3.11.1 | U13: RA | V13: Risk Assessment
A14: All CUI is encrypted using FIPS-validated cryptography | I14: 3.05 | J14: 3.1.12 | K14: 03.01.12.0 | L14: Derived | M14: 5 | N14: AC | O14: Access Control | P14: AC.L2-3.1.12 | T14: 3.12.1 | U14: CA | V14: Security Assessment
A15: CUI is encrypted but not using FIPS-validated cryptography | C15: Copyright 2022 CMMC Information Institute, Inc. All Rights Reserved. | I15: 3.06 | J15: 3.1.13 | K15: 03.01.13.0 | L15: Derived | M15: 5 | N15: AC | O15: Access Control | P15: AC.L2-3.1.13 | T15: 3.13.1 | U15: SC | V15: System and Communication Protection
A16: CUI is not encrypted | I16: 5.27 | J16: 3.1.14 | K16: 03.01.14.0 | L16: Derived | M16: 1 | N16: AC | O16: Access Control | P16: AC.L2-3.1.14 | T16: 3.14.1 | U16: SI | V16: System and Information Integrity
A17: Not Yet Addressed | C17: This tool was created by the CMMC Information Institute, Inc. and is released under the Creative Commons CC-BY-ND license. | I17: 5.28 | J17: 3.1.15 | K17: 03.01.15.0 | L17: Derived | M17: 1 | N17: AC | O17: Access Control | P17: AC.L2-3.1.15
A18: Not Yet Assessed | I18: 3.04 | J18: 3.1.16 | K18: 03.01.16.0 | L18: Derived | M18: 5 | N18: AC | O18: Access Control | P18: AC.L2-3.1.16
I19: 3.03 | J19: 3.1.17 | K19: 03.01.17.0 | L19: Derived | M19: 5 | N19: AC | O19: Access Control | P19: AC.L2-3.1.17 | T19: 800-171 Basic Controls
I20: 3.14 | J20: 3.1.18 | K20: 03.01.18.0 | L20: Derived | M20: 5 | N20: AC | O20: Access Control | P20: AC.L2-3.1.18 | T20: 3.1.1
A21: Fully Implemented | I21: 4.22 | J21: 3.1.19 | K21: 03.01.19.0 | L21: Derived | M21: 3 | N21: AC | O21: Access Control | P21: AC.L2-3.1.19 | T21: 3.1.2
A22: Implementation Begun | C22: IN ADDITION, THIS TOOL IS PROVIDED BY THE COPYRIGHT HOLDERS AND CONTRIBUTORS "AS IS" AND ANY EXPRESS OR IMPLIED WARRANTIES, INCLUDING, BUT NOT LIMITED TO, THE IMPLIED WARRANTIES OF MERCHANTABILITY AND FITNESS FOR A PARTICULAR PURPOSE ARE DISCLAIMED. IN NO EVENT SHALL THE COPYRIGHT HOLDER OR CONTRIBUTORS BE LIABLE FOR ANY DIRECT, INDIRECT, INCIDENTAL, SPECIAL, EXEMPLARY, OR CONSEQUENTIAL DAMAGES (INCLUDING, BUT NOT LIMITED TO, PROCUREMENT OF SUBSTITUTE GOODS OR SERVICES; LOSS OF USE, DATA, OR PROFITS; OR BUSINESS INTERRUPTION) HOWEVER CAUSED AND ON ANY THEORY OF LIABILITY, WHETHER IN CONTRACT, STRICT LIABILITY, OR TORT (INCLUDING NEGLIGENCE OR OTHERWISE) ARISING IN ANY WAY OUT OF THE USE OF THIS SOFTWARE, EVEN IF ADVISED OF THE POSSIBILITY OF SUCH DAMAGE. | I22: 1.16 | J22: 3.1.20 | K22: 03.01.20.0 | L22: Derived | M22: 1 | N22: AC | O22: Access Control | P22: AC.L1-3.1.20 | T22: 3.2.1
A23: Implementation Planned | I23: 4.17 | J23: 3.1.21 | K23: 03.01.21.0 | L23: Derived | M23: 1 | N23: AC | O23: Access Control | P23: AC.L2-3.1.21 | T23: 3.2.2
A24: Not Yet Addressed | I24: 1.17 | J24: 3.1.22 | K24: 03.01.22.0 | L24: Derived | M24: 1 | N24: AC | O24: Access Control | P24: AC.L1-3.1.22 | T24: 3.3.1
A25: Not Permitted | I25: 2.12 | J25: 3.2.1 | K25: 03.02.01.0 | L25: Basic | M25: 5 | N25: AT | O25: Awareness and Training | P25: AT.L2-3.2.1 | T25: 3.3.2
A26: Not Yet Assessed | I26: 2.13 | J26: 3.2.2 | K26: 03.02.02.0 | L26: Basic | M26: 5 | N26: AT | O26: Awareness and Training | P26: AT.L2-3.2.2 | T26: 3.4.1
I27: 2.14 | J27: 3.2.3 | K27: 03.02.03.0 | L27: Derived | M27: 1 | N27: AT | O27: Awareness and Training | P27: AT.L2-3.2.3 | T27: 3.4.2
A28: No | I28: 4.01 | J28: 3.3.1 | K28: 03.03.01.0 | L28: Basic | M28: 5 | N28: AU | O28: Autdit and Accountability | P28: AU.L2-3.3.1 | T28: 3.5.1
A29: Yes - Admins and privileged users (3 points) | I29: 3.18 | J29: 3.3.2 | K29: 03.03.02.0 | L29: Basic | M29: 3 | N29: AU | O29: Autdit and Accountability | P29: AU.L2-3.3.2 | T29: 3.5.2
A30: Yes - All employees, including senior mgmt (5 points) | I30: 4.02 | J30: 3.3.3 | K30: 03.03.03.0 | L30: Derived | M30: 1 | N30: AU | O30: Autdit and Accountability | P30: AU.L2-3.3.3 | T30: 3.6.1
I31: 4.03 | J31: 3.3.4 | K31: 03.03.04.0 | L31: Derived | M31: 1 | N31: AU | O31: Autdit and Accountability | P31: AU.L2-3.3.4 | T31: 3.6.2
A32: No | I32: 4.04 | J32: 3.3.5 | K32: 03.03.05.0 | L32: Derived | M32: 5 | N32: AU | O32: Autdit and Accountability | P32: AU.L2-3.3.5 | T32: 3.7.1
A33: Yes - without role-based access definitions (3 points) | I33: 4.06 | J33: 3.3.6 | K33: 03.03.06.0 | L33: Derived | M33: 1 | N33: AU | O33: Autdit and Accountability | P33: AU.L2-3.3.6 | T33: 3.7.2
A34: Yes - with role-based information access definitions (5 points) | I34: 3.13 | J34: 3.3.7 | K34: 03.03.07.0 | L34: Derived | M34: 1 | N34: AU | O34: Autdit and Accountability | P34: AU.L2-3.3.7 | T34: 3.8.1
I35: 4.12 | J35: 3.3.8 | K35: 03.03.08.0 | L35: Derived | M35: 1 | N35: AU | O35: Autdit and Accountability | P35: AU.L2-3.3.8 | T35: 3.8.2
A36: No (3 points) | I36: 4.13 | J36: 3.3.9 | K36: 03.03.09.0 | L36: Derived | M36: 1 | N36: AU | O36: Autdit and Accountability | P36: AU.L2-3.3.9 | T36: 3.8.3
A37: Yes - WiFi is part of our network | I37: 4.14 | J37: 3.4.1 | K37: 03.04.01.0 | L37: Basic | M37: 5 | N37: CM | O37: Configuration Management | P37: CM.L2-3.4.1 | T37: 3.9.1
A38: Yes - WiFi goes to a guest network separate from our internal network (3 points) | I38: 4.15 | J38: 3.4.2 | K38: 03.04.02.0 | L38: Basic | M38: 5 | N38: CM | O38: Configuration Management | P38: CM.L2-3.4.2 | T38: 3.9.2
I39: 5.06 | J39: 3.4.3 | K39: 03.04.03.0 | L39: Derived | M39: 1 | N39: CM | O39: Configuration Management | P39: CM.L2-3.4.3 | T39: 3.10.1
A40: No | I40: 5.07 | J40: 3.4.4 | K40: 03.04.04.0 | L40: Derived | M40: 1 | N40: CM | O40: Configuration Management | P40: CM.L2-3.4.4 | T40: 3.10.2
A41: Yes - without objectives (3 points) | I41: 5.04 | J41: 3.4.5 | K41: 03.04.05.0 | L41: Derived | M41: 5 | N41: CM | O41: Configuration Management | P41: CM.L2-3.4.5 | T41: 3.11.1
A42: Yes - with objectives (8 points) | I42: 5.05 | J42: 3.4.6 | K42: 03.04.06.0 | L42: Derived | M42: 5 | N42: CM | O42: Configuration Management | P42: CM.L2-3.4.6 | T42: 3.12.1
I43: 4.09 | J43: 3.4.7 | K43: 03.04.07.0 | L43: Derived | M43: 5 | N43: CM | O43: Configuration Management | P43: CM.L2-3.4.7 | T43: 3.12.2
A44: No | I44: 4.07 | J44: 3.4.8 | K44: 03.04.08.0 | L44: Derived | M44: 5 | N44: CM | O44: Configuration Management | P44: CM.L2-3.4.8 | T44: 3.12.3
A45: Yes - Partial/incomplete (3 points) | I45: 4.08 | J45: 3.4.9 | K45: 03.04.09.0 | L45: Derived | M45: 1 | N45: CM | O45: Configuration Management | P45: CM.L2-3.4.9 | T45: 3.12.4
A46: Yes - Comprehensive (8 points) | I46: 1.12 | J46: 3.5.1 | K46: 03.05.01.0 | L46: Basic | M46: 5 | N46: IA | O46: Identification and Authentication | P46: IA.L1-3.5.1 | T46: 3.13.1
I47: 1.13 | J47: 3.5.2 | K47: 03.05.02.0 | L47: Basic | M47: 5 | N47: IA | O47: Identification and Authentication | P47: IA.L1-3.5.2 | T47: 3.13.2
A48: Incoming | I48: 2.03 | J48: 3.5.3 | K48: 03.05.03.0 | L48: Derived | M48: 5 | N48: IA | O48: Identification and Authentication | P48: IA.L2-3.5.3 | T48: 3.14.1
A49: Internal - Subsystems Only | I49: 5.22 | J49: 3.5.4 | K49: 03.05.04.0 | L49: Derived | M49: 1 | N49: IA | O49: Identification and Authentication | P49: IA.L2-3.5.4 | T49: 3.14.2
A50: Internal - To Cloud Provider | I50: 5.23 | J50: 3.5.5 | K50: 03.05.05.0 | L50: Derived | M50: 1 | N50: IA | O50: Identification and Authentication | P50: IA.L2-3.5.5 | T50: 3.14.3
A51: Internal - From Cloud Provider | I51: 5.24 | J51: 3.5.6 | K51: 03.05.06.0 | L51: Derived | M51: 1 | N51: IA | O51: Identification and Authentication | P51: IA.L2-3.5.6
A52: Outgoing | I52: 2.07 | J52: 3.5.7 | K52: 03.05.07.0 | L52: Derived | M52: 1 | N52: IA | O52: Identification and Authentication | P52: IA.L2-3.5.7
I53: 2.08 | J53: 3.5.8 | K53: 03.05.08.0 | L53: Derived | M53: 1 | N53: IA | O53: Identification and Authentication | P53: IA.L2-3.5.8
I54: 2.11 | J54: 3.5.9 | K54: 03.05.09.0 | L54: Derived | M54: 1 | N54: IA | O54: Identification and Authentication | P54: IA.L2-3.5.9
I55: 3.02 | J55: 3.5.10 | K55: 03.05.10.0 | L55: Derived | M55: 5 | N55: IA | O55: Identification and Authentication | P55: IA.L2-3.5.10
I56: 4.16 | J56: 3.5.11 | K56: 03.05.11.0 | L56: Derived | M56: 1 | N56: IA | O56: Identification and Authentication | P56: IA.L2-3.5.11
I57: 3.1 | J57: 3.6.1 | K57: 03.06.01.0 | L57: Basic | M57: 5 | N57: IR | O57: Incident Response | P57: IR.L2-3.6.1
I58: 3.11 | J58: 3.6.2 | K58: 03.06.02.0 | L58: Basic | M58: 5 | N58: IR | O58: Incident Response | P58: IR.L2-3.6.2
I59: 3.12 | J59: 3.6.3 | K59: 03.06.03.0 | L59: Derived | M59: 1 | N59: IR | O59: Incident Response | P59: IR.L2-3.6.3
I60: 2.18 | J60: 3.7.1 | K60: 03.07.01.0 | L60: Basic | M60: 3 | N60: MA | O60: Maintenance | P60: MA.L2-3.7.1
I61: 2.19 | J61: 3.7.2 | K61: 03.07.02.0 | L61: Basic | M61: 5 | N61: MA | O61: Maintenance | P61: MA.L2-3.7.2
I62: 5.19 | J62: 3.7.3 | K62: 03.07.03.0 | L62: Derived | M62: 1 | N62: MA | O62: Maintenance | P62: MA.L2-3.7.3
I63: 4.2 | J63: 3.7.4 | K63: 03.07.04.0 | L63: Derived | M63: 3 | N63: MA | O63: Maintenance | P63: MA.L2-3.7.4
I64: 2.04 | J64: 3.7.5 | K64: 03.07.05.0 | L64: Derived | M64: 5 | N64: MA | O64: Maintenance | P64: MA.L2-3.7.5
... I112: 4.05 | J112: 3.14.7 | K112: 03.14.07.0 | L112: Derived | M112: 3 | N112: SI | O112: System and Information Integrity | P112: SI.L2-3.14.7

Sheet Change Log
A1: Version | B1: Change(s)
A2: 44686 | B2: Added Media Library and Media Access Log Worksheets
A3: 2022-08a | B3: Added DIY/Outsource/Hybrid deisgnations to Requirements and Objectives; Added missing objective in 3.12.1; Added Roles worksheet; Added the Privileged Accounts worksheet; Added fields to the Hardware and Software Inventory Worksheets; Added the CUI Sources and Destinations Worksheet.
A4: 2022-08b | B4: Added date reviewed and reviewed by fields to many of the worksheets.
